Workbook
Name rFecha: 'Registro'!$B$6:$B$5005
Name rTipo: 'Registro'!$C$6:$C$5005
Name rCat: 'Registro'!$D$6:$D$5005
Name rSub: 'Registro'!$E$6:$E$5005
Name rDesc: 'Registro'!$F$6:$F$5005
Name rMonto: 'Registro'!$G$6:$G$5005
Name rMon: 'Registro'!$H$6:$H$5005
Name rTasa: 'Registro'!$I$6:$I$5005
Name rCta: 'Registro'!$J$6:$J$5005
Name rDest: 'Registro'!$K$6:$K$5005
Name rCom: 'Registro'!$L$6:$L$5005
Name rClas: 'Registro'!$M$6:$M$5005
Name rObs: 'Registro'!$N$6:$N$5005
Name rEstado: 'Registro'!$O$6:$O$5005
Name rTipoE: 'Registro'!$P$6:$P$5005
Name rCtaE: 'Registro'!$Q$6:$Q$5005
Name rTasaRef: 'Registro'!$R$6:$R$5005
Name rDOP: 'Registro'!$S$6:$S$5005
Name rUSD: 'Registro'!$T$6:$T$5005
Name rGasto: 'Registro'!$U$6:$U$5005
Name rIng: 'Registro'!$V$6:$V$5005
Name rTrad: 'Registro'!$W$6:$W$5005
Name rClasE: 'Registro'!$X$6:$X$5005
Name rGrupo: 'Registro'!$Y$6:$Y$5005
Name rDia: 'Registro'!$Z$6:$Z$5005
Name rHorm: 'Registro'!$AA$6:$AA$5005
Name rCtaSO: 'Registro'!$AB$6:$AB$5005
Name rCtaSD: 'Registro'!$AC$6:$AC$5005
Name rTCO: 'Registro'!$AD$6:$AD$5005
Name rTCD: 'Registro'!$AE$6:$AE$5005
Name rEfO: 'Registro'!$AF$6:$AF$5005
Name rEfD: 'Registro'!$AG$6:$AG$5005
Name rFlujo: 'Registro'!$AH$6:$AH$5005
Name rComIdx: 'Registro'!$AI$6:$AI$5005
Name catCat: 'Categorías'!$B$6:$B$205
Name catSub: 'Categorías'!$C$6:$C$205
Name catTipo: 'Categorías'!$D$6:$D$205
Name catClasif: 'Categorías'!$E$6:$E$205
Name catGrupo: 'Categorías'!$F$6:$F$205
Name catComida: 'Categorías'!$G$6:$G$205
Name catClave: 'Categorías'!$P$6:$P$205
Name catIdx: 'Categorías'!$Q$6:$Q$205
Name catFoodIdx: 'Categorías'!$R$6:$R$205
Name catUList: 'Categorías'!$L$6:$L$45
Name lstCat: OFFSET('Categorías'!$L$6,0,0,MAX(1,COUNTIF('Categorías'!$L$6:$L$45,"?*")),1)
Name ctaNombre: 'Cuentas'!$B$7:$B$36
Name ctaTipo: 'Cuentas'!$C$7:$C$36
Name ctaMoneda: 'Cuentas'!$D$7:$D$36
Name ctaVinc: 'Cuentas'!$E$7:$E$36
Name ctaIni: 'Cuentas'!$F$7:$F$36
Name ctaFechaIni: 'Cuentas'!$G$7:$G$36
Name ctaLiq: 'Cuentas'!$I$7:$I$36
Name ctaMov: 'Cuentas'!$J$7:$J$36
Name ctaSaldo: 'Cuentas'!$K$7:$K$36
Name ctaSaldoDOP: 'Cuentas'!$L$7:$L$36
Name lstCuentas: OFFSET('Cuentas'!$B$7,0,0,MAX(1,COUNTIF('Cuentas'!$B$7:$B$36,"?*")),1)
Name TasaUSD: 'Config'!$C$5
Name CuentaPred: 'Config'!$C$6
Name catAlim: 'Config'!$C$7
Name catTrading: 'Config'!$C$8

Sheet Inicio
B1: Finanzas Personales | H1: Excel 365 · sin macros · moneda base DOP
B2: ● Inicio | C2: Registro | D2: Dashboard | E2: Alimentación | F2: Hormiga | G2: Recurrentes | H2: Presupuestos | I2: Cuentas | J2: Categorías | K2: Config
B4: Registra cada movimiento en segundos, entiende a dónde va tu dinero y, cuando tengas datos suficientes, define límites y metas. Todas las cifras se recalculan automáticamente al agregar filas en «Registro».
B7: Ir a…
B8: Registrar movimientos → | E8: Dashboard → | H8: Alimentación → | K8: Gastos hormiga →
B9: Una fila por transacción. Fecha + monto + categoría + cuenta. | E9: KPIs, filtros, gráficos, top 10 y comparación mensual. | H9: Comer fuera vs. cocinar, costos por comida y simulador. | K9: Consumos pequeños y frecuentes y su peso real.
B12: Suscripciones → | E12: Presupuestos y metas → | H12: Cuentas → | K12: Categorías →
B13: Agenda de cobros recurrentes y próximos vencimientos. | E13: Etapa 2: límites, alertas, fondo de emergencia, boda, inversión. | H13: Saldos iniciales, saldo actual, conciliación y deuda de tarjetas. | K13: Edita, agrega o elimina categorías y subcategorías.
B16: Estado del sistema | I16: Primeros pasos
B17: Movimientos registrados | F17: =COUNTIF(rTipoE,"?*") | I17: 1. Explora el Dashboard con los datos DEMO (filas lilas del Registro).
B18: Filas de DEMOSTRACIÓN | F18: =COUNTIF(rObs,"DEMOSTRACIÓN") | I18: 2. Borra los DEMO (ver «Eliminar datos de demostración» abajo).
B19: Filas con advertencias | F19: =COUNTIF(rEstado,"⚠*") | I19: 3. En Cuentas, renombra tus cuentas/tarjetas y, si quieres saldos reales, escribe saldo inicial y su fecha.
B20: Último movimiento | F20: =IF(COUNT(rFecha)=0,"—",MAX(rFecha)) | I20: 4. En Config, actualiza la tasa USD→DOP.
B21: Capacidad usada del Registro | F21: =COUNTA(rFecha)/5000 | I21: 5. Ajusta Categorías a tu gusto (opcional).
B22: Cuentas con saldo inicial | F22: ='Cuentas'!L41 | I22: 6. Registra cada gasto el mismo día: ~10 segundos por fila.
B23: Tasa USD→DOP en uso | F23: =TasaUSD | I23: 7. Tras 2–3 meses, revisa Alimentación y Hormiga y define límites en Presupuestos.
B24: Suscripciones que vencen en ≤ 7 días | F24: =recProximos
B26: Cómo registrar (reglas que evitan duplicar)
B27: Gasto cotidiano | E27: Fecha · (Tipo vacío = Gasto) · Categoría · Subcategoría · Monto · Cuenta. Comercio y descripción son opcionales.
B28: Compra con tarjeta de crédito | E28: Regístrala como Gasto en la fecha de consumo, con Cuenta = la tarjeta. Así el gasto cuenta una sola vez y la deuda de la tarjeta crece.
B29: Pago de la tarjeta | E29: Tipo «Pago tarjeta», Cuenta = banco que paga, Cuenta destino = la tarjeta. NO es gasto: solo reduce la deuda y sale dinero del banco.
B30: Transferencias propias | E30: Tipo «Transferencia» (banco→efectivo, banco→billetera…). No suma ni a ingresos ni a gastos; solo mueve saldos.
B31: Trading | E31: Depósito o retiro = Transferencia hacia/desde la cuenta de trading. Ganancia o pérdida realizada = «Resultado trading» (+/−). Evaluaciones, plataformas y comisiones = Gasto en la categoría de trading.
B32: Reembolsos | E32: Si te devuelven dinero, usa «Reembolso» con la misma categoría del gasto original: el gasto neto se reduce.
B33: Dólares | E33: Moneda USD. Si conoces la tasa real aplicada, escríbela en «Tasa USD»; si no, se usa la de Config. Todos los reportes salen en DOP.
B34: Ajustes | E34: Si el saldo real no coincide con el calculado (Cuentas › Conciliación), registra un «Ajuste» por la diferencia.
B36: Eliminar datos de demostración
B37: • Las filas DEMO están juntas al inicio del Registro (filas 6 a 194), marcadas «DEMOSTRACIÓN» en Observaciones y con fondo lila.
B38: • Opción rápida: en Registro selecciona B6:N194 y pulsa Suprimir. Las fórmulas automáticas (columnas O en adelante) no se tocan.
B39: • En Recurrentes, borra igual las filas marcadas «DEMOSTRACIÓN» (columnas B:L).
B40: • Las cuentas y categorías de ejemplo NO son datos personales: renómbralas o bórralas. No hay saldos ni límites precargados.
B41: • Cuando el estado de arriba muestre 0 filas DEMO, todo el sistema queda listo con tus datos.
B43: Buenas prácticas
B44: • No insertes columnas dentro de la tabla del Registro ni escribas sobre las columnas grises: son el motor del sistema.
B45: • El Registro tiene capacidad para 5,000 filas. Si te acercas al límite, selecciona la última fila completa y arrastra el controlador de la tabla hacia abajo para ampliarla.
B46: • Puedes ordenar y filtrar la tabla (flechas del encabezado) sin romper nada. Filtra la columna Estado por «⚠» para corregir errores.
B47: • Celdas amarillas = editables. Celdas grises = cálculo automático. Filas lilas = demostración.
B48: • En el celular: abre el archivo con la app de Excel (OneDrive) y registra desde la hoja Registro.

Sheet Registro
B1: Registro de movimientos | AC1: Una fila = una transacción
B2: Inicio | C2: ● Registro | D2: Dashboard | E2: Alimentación | F2: Hormiga | G2: Recurrentes | H2: Presupuestos | J2: Cuentas | K2: Categorías | L2: Config
B3: =HYPERLINK("#'Registro'!B"&IFERROR(MATCH(TRUE,INDEX(rFecha="",0),0)+5,5005),"＋ Nuevo movimiento") | D3: Atajos: Ctrl+; = fecha de hoy · Alt+↓ = abrir lista · Tab = siguiente campo · Solo Fecha y Monto son obligatorios: si dejas Tipo vacío se asume «Gasto». | J3: ="Movimientos: "&COUNTIF(rTipoE,"?*") | K3: ="Advertencias: "&COUNTIF(rEstado,"⚠*") | L3: =IF(COUNTIF(rObs,"DEMOSTRACIÓN")>0,"Filas DEMO: "&COUNTIF(rObs,"DEMOSTRACIÓN"),"")
B4: TUS DATOS · llena estas columnas | O4: CÁLCULOS AUTOMÁTICOS · no editar (pulsa «+» arriba de la columna P para ver el detalle)
B5: Fecha | C5: Tipo | D5: Categoría | E5: Subcategoría | F5: Descripción | G5: Monto | H5: Moneda | I5: Tasa USD | J5: Cuenta / método | K5: Cuenta destino | L5: Comercio | M5: Fijo/Variable | N5: Observaciones | O5: Estado | P5: Tipo efectivo | Q5: Cuenta efectiva | R5: Tasa aplicada | S5: Monto DOP | T5: Monto USD | U5: Gasto real DOP | V5: Ingreso DOP | W5: Resultado trading DOP | X5: Clasificación efectiva | Y5: Grupo alimentación | Z5: Día semana | AA5: Es hormiga | AB5: Cuenta saldo origen | AC5: Cuenta saldo destino | AD5: Tipo cta origen | AE5: Tipo cta destino | AF5: Efecto saldo origen | AG5: Efecto saldo destino | AH5: Flujo líquido DOP | AI5: Índice comercio
B6: 46235 | C6: Gasto | D6: Alimentación | E6: Cenas compradas | F6: DEMO · Cena comprada | G6: 600 | H6: DOP | J6: Tarjeta de crédito | L6: Pica pollo de la esquina | N6: DEMOSTRACIÓN | O6: =IF(AND(B6="",G6="",C6="",D6="",J6=""),"",IF(B6="","⚠ Falta fecha",IF(G6="","⚠ Falta monto",IF(Q6="","⚠ Falta cuenta",IF(ISNA(MATCH(Q6,ctaNombre,0)),"⚠ Cuenta no registrada",IF(AND(OR(P6="Gasto",P6="Reembolso"),D6=""),"⚠ Falta categoría",IF(AND(D6<>"",E6<>"",ISNA(MATCH(D6&"|"&E6,catClave,0))),"⚠ Subcategoría no corresponde",IF(AND(OR(P6="Transferencia",P6="Pago tarjeta"),K6=""),"⚠ Falta cuenta destino",IF(AND(K6<>"",P6<>"Transferencia",P6<>"Pago tarjeta"),"⚠ Destino solo aplica a transferencias",IF(AND(K6<>"",K6=Q6),"⚠ Origen igual a destino",IF(AND(K6<>"",ISNA(MATCH(K6,ctaNombre,0))),"⚠ Destino no registrado",IF(AND(P6="Pago tarjeta",AE6<>"Tarjeta de crédito"),"⚠ El destino debe ser tarjeta de crédito",IF(AND(P6="Gasto",E6="Depósitos y retiros"),"⚠ Usa tipo Transferencia",IF(AND(P6="Resultado trading",AD6<>"Cuenta de trading"),"⚠ Usa una cuenta de trading",IF(AND(G6<=0,P6<>"Ajuste",P6<>"Resultado trading"),"⚠ El monto debe ser positivo","✓"))))))))))))))) | P6: =IF(OR(B6="",G6=""),"",IF(C6="","Gasto",C6)) | Q6: =IF(P6="","",IF(J6<>"",J6,CuentaPred&"")) | R6: =IF(P6="","",IF(ISNUMBER(I6),I6,TasaUSD)) | S6: =IF(P6="","",IF(H6="USD",G6*R6,G6)) | T6: =IF(P6="","",IF(H6="USD",G6,IF(R6>0,G6/R6,0))) | U6: =IF(P6="","",IF(P6="Gasto",S6,IF(P6="Reembolso",-S6,0))) | V6: =IF(P6="","",IF(P6="Ingreso",S6,0)) | W6: =IF(P6="","",IF(P6="Resultado trading",S6,0)) | X6: =IF(OR(P6="Gasto",P6="Reembolso"),IF(M6<>"",M6,IFERROR(INDEX(catClasif,MATCH(D6&"|"&E6,catClave,0))&"","Variable")),"") | Y6: =IF(P6="","",IFERROR(INDEX(catGrupo,MATCH(D6&"|"&E6,catClave,0))&"","")) | Z6: =IF(P6="","",WEEKDAY(B6,2)) | AA6: =IF(P6="","",IF(AND(P6="Gasto",X6="Variable",D6<>catTrading,S6>0,S6<=Umbral),1,0)) | AB6: =IF(OR(P6="",Q6=""),"",IFERROR(IF(INDEX(ctaVinc,MATCH(Q6,ctaNombre,0))&""<>"",INDEX(ctaVinc,MATCH(Q6,ctaNombre,0))&"",Q6),Q6)) | AC6: =IF(OR(K6="",AND(P6<>"Transferencia",P6<>"Pago tarjeta")),"",IFERROR(IF(INDEX(ctaVinc,MATCH(K6,ctaNombre,0))&""<>"",INDEX(ctaVinc,MATCH(K6,ctaNombre,0))&"",K6),K6)) | AD6: =IF(AB6="","",IFERROR(INDEX(ctaTipo,MATCH(AB6,ctaNombre,0))&"","")) | AE6: =IF(AC6="","",IFERROR(INDEX(ctaTipo,MATCH(AC6,ctaNombre,0))&"","")) | AF6: =IF(OR(P6="",AB6=""),"",IF(OR(P6="Gasto",P6="Transferencia",P6="Pago tarjeta"),-1,1)*IF(IFERROR(INDEX(ctaMoneda,MATCH(AB6,ctaNombre,0))&"","DOP")="USD",T6,S6)) | AG6: =IF(AC6="","",IF(IFERROR(INDEX(ctaMoneda,MATCH(AC6,ctaNombre,0))&"","DOP")="USD",T6,S6)) | AH6: =IF(P6="","",IF(AND(AD6<>"",COUNTIFS(tcTipo,AD6,tcLiq,"Sí")>0),IF(OR(P6="Gasto",P6="Transferencia",P6="Pago tarjeta"),-1,1)*S6,0)+IF(AND(AE6<>"",COUNTIFS(tcTipo,AE6,tcLiq,"Sí")>0),S6,0)) | AI6: =IF(OR(L6="",P6=""),"",IF(COUNTIFS(L$6:L6,L6,P$6:P6,"?*")=1,MAX(AI$5:AI5)+1,""))
B7: 46235 | C7: Transferencia | F7: DEMO · Retiro en cajero | G7: 5000 | H7: DOP | J7: Banco principal | K7: Efectivo | N7: DEMOSTRACIÓN | O7: =IF(AND(B7="",G7="",C7="",D7="",J7=""),"",IF(B7="","⚠ Falta fecha",IF(G7="","⚠ Falta monto",IF(Q7="","⚠ Falta cuenta",IF(ISNA(MATCH(Q7,ctaNombre,0)),"⚠ Cuenta no registrada",IF(AND(OR(P7="Gasto",P7="Reembolso"),D7=""),"⚠ Falta categoría",IF(AND(D7<>"",E7<>"",ISNA(MATCH(D7&"|"&E7,catClave,0))),"⚠ Subcategoría no corresponde",IF(AND(OR(P7="Transferencia",P7="Pago tarjeta"),K7=""),"⚠ Falta cuenta destino",IF(AND(K7<>"",P7<>"Transferencia",P7<>"Pago tarjeta"),"⚠ Destino solo aplica a transferencias",IF(AND(K7<>"",K7=Q7),"⚠ Origen igual a destino",IF(AND(K7<>"",ISNA(MATCH(K7,ctaNombre,0))),"⚠ Destino no registrado",IF(AND(P7="Pago tarjeta",AE7<>"Tarjeta de crédito"),"⚠ El destino debe ser tarjeta de crédito",IF(AND(P7="Gasto",E7="Depósitos y retiros"),"⚠ Usa tipo Transferencia",IF(AND(P7="Resultado trading",AD7<>"Cuenta de trading"),"⚠ Usa una cuenta de trading",IF(AND(G7<=0,P7<>"Ajuste",P7<>"Resultado trading"),"⚠ El monto debe ser positivo","✓"))))))))))))))) | P7: =IF(OR(B7="",G7=""),"",IF(C7="","Gasto",C7)) | Q7: =IF(P7="","",IF(J7<>"",J7,CuentaPred&"")) | R7: =IF(P7="","",IF(ISNUMBER(I7),I7,TasaUSD)) | S7: =IF(P7="","",IF(H7="USD",G7*R7,G7)) | T7: =IF(P7="","",IF(H7="USD",G7,IF(R7>0,G7/R7,0))) | U7: =IF(P7="","",IF(P7="Gasto",S7,IF(P7="Reembolso",-S7,0))) | V7: =IF(P7="","",IF(P7="Ingreso",S7,0)) | W7: =IF(P7="","",IF(P7="Resultado trading",S7,0)) | X7: =IF(OR(P7="Gasto",P7="Reembolso"),IF(M7<>"",M7,IFERROR(INDEX(catClasif,MATCH(D7&"|"&E7,catClave,0))&"","Variable")),"") | Y7: =IF(P7="","",IFERROR(INDEX(catGrupo,MATCH(D7&"|"&E7,catClave,0))&"","")) | Z7: =IF(P7="","",WEEKDAY(B7,2)) | AA7: =IF(P7="","",IF(AND(P7="Gasto",X7="Variable",D7<>catTrading,S7>0,S7<=Umbral),1,0)) | AB7: =IF(OR(P7="",Q7=""),"",IFERROR(IF(INDEX(ctaVinc,MATCH(Q7,ctaNombre,0))&""<>"",INDEX(ctaVinc,MATCH(Q7,ctaNombre,0))&"",Q7),Q7)) | AC7: =IF(OR(K7="",AND(P7<>"Transferencia",P7<>"Pago tarjeta")),"",IFERROR(IF(INDEX(ctaVinc,MATCH(K7,ctaNombre,0))&""<>"",INDEX(ctaVinc,MATCH(K7,ctaNombre,0))&"",K7),K7)) | AD7: =IF(AB7="","",IFERROR(INDEX(ctaTipo,MATCH(AB7,ctaNombre,0))&"","")) | AE7: =IF(AC7="","",IFERROR(INDEX(ctaTipo,MATCH(AC7,ctaNombre,0))&"","")) | AF7: =IF(OR(P7="",AB7=""),"",IF(OR(P7="Gasto",P7="Transferencia",P7="Pago tarjeta"),-1,1)*IF(IFERROR(INDEX(ctaMoneda,MATCH(AB7,ctaNombre,0))&"","DOP")="USD",T7,S7)) | AG7: =IF(AC7="","",IF(IFERROR(INDEX(ctaMoneda,MATCH(AC7,ctaNombre,0))&"","DOP")="USD",T7,S7)) | AH7: =IF(P7="","",IF(AND(AD7<>"",COUNTIFS(tcTipo,AD7,tcLiq,"Sí")>0),IF(OR(P7="Gasto",P7="Transferencia",P7="Pago tarjeta"),-1,1)*S7,0)+IF(AND(AE7<>"",COUNTIFS(tcTipo,AE7,tcLiq,"Sí")>0),S7,0)) | AI7: =IF(OR(L7="",P7=""),"",IF(COUNTIFS(L$6:L7,L7,P$6:P7,"?*")=1,MAX(AI$5:AI6)+1,""))
B8: 46236 | C8: Gasto | D8: Alimentación | E8: Supermercado | F8: DEMO · Compra de supermercado | G8: 5850 | H8: DOP | J8: Tarjeta de crédito | L8: Supermercado principal | N8: DEMOSTRACIÓN | O8: =IF(AND(B8="",G8="",C8="",D8="",J8=""),"",IF(B8="","⚠ Falta fecha",IF(G8="","⚠ Falta monto",IF(Q8="","⚠ Falta cuenta",IF(ISNA(MATCH(Q8,ctaNombre,0)),"⚠ Cuenta no registrada",IF(AND(OR(P8="Gasto",P8="Reembolso"),D8=""),"⚠ Falta categoría",IF(AND(D8<>"",E8<>"",ISNA(MATCH(D8&"|"&E8,catClave,0))),"⚠ Subcategoría no corresponde",IF(AND(OR(P8="Transferencia",P8="Pago tarjeta"),K8=""),"⚠ Falta cuenta destino",IF(AND(K8<>"",P8<>"Transferencia",P8<>"Pago tarjeta"),"⚠ Destino solo aplica a transferencias",IF(AND(K8<>"",K8=Q8),"⚠ Origen igual a destino",IF(AND(K8<>"",ISNA(MATCH(K8,ctaNombre,0))),"⚠ Destino no registrado",IF(AND(P8="Pago tarjeta",AE8<>"Tarjeta de crédito"),"⚠ El destino debe ser tarjeta de crédito",IF(AND(P8="Gasto",E8="Depósitos y retiros"),"⚠ Usa tipo Transferencia",IF(AND(P8="Resultado trading",AD8<>"Cuenta de trading"),"⚠ Usa una cuenta de trading",IF(AND(G8<=0,P8<>"Ajuste",P8<>"Resultado trading"),"⚠ El monto debe ser positivo","✓"))))))))))))))) | P8: =IF(OR(B8="",G8=""),"",IF(C8="","Gasto",C8)) | Q8: =IF(P8="","",IF(J8<>"",J8,CuentaPred&"")) | R8: =IF(P8="","",IF(ISNUMBER(I8),I8,TasaUSD)) | S8: =IF(P8="","",IF(H8="USD",G8*R8,G8)) | T8: =IF(P8="","",IF(H8="USD",G8,IF(R8>0,G8/R8,0))) | U8: =IF(P8="","",IF(P8="Gasto",S8,IF(P8="Reembolso",-S8,0))) | V8: =IF(P8="","",IF(P8="Ingreso",S8,0)) | W8: =IF(P8="","",IF(P8="Resultado trading",S8,0)) | X8: =IF(OR(P8="Gasto",P8="Reembolso"),IF(M8<>"",M8,IFERROR(INDEX(catClasif,MATCH(D8&"|"&E8,catClave,0))&"","Variable")),"") | Y8: =IF(P8="","",IFERROR(INDEX(catGrupo,MATCH(D8&"|"&E8,catClave,0))&"","")) | Z8: =IF(P8="","",WEEKDAY(B8,2)) | AA8: =IF(P8="","",IF(AND(P8="Gasto",X8="Variable",D8<>catTrading,S8>0,S8<=Umbral),1,0)) | AB8: =IF(OR(P8="",Q8=""),"",IFERROR(IF(INDEX(ctaVinc,MATCH(Q8,ctaNombre,0))&""<>"",INDEX(ctaVinc,MATCH(Q8,ctaNombre,0))&"",Q8),Q8)) | AC8: =IF(OR(K8="",AND(P8<>"Transferencia",P8<>"Pago tarjeta")),"",IFERROR(IF(INDEX(ctaVinc,MATCH(K8,ctaNombre,0))&""<>"",INDEX(ctaVinc,MATCH(K8,ctaNombre,0))&"",K8),K8)) | AD8: =IF(AB8="","",IFERROR(INDEX(ctaTipo,MATCH(AB8,ctaNombre,0))&"","")) | AE8: =IF(AC8="","",IFERROR(INDEX(ctaTipo,MATCH(AC8,ctaNombre,0))&"","")) | AF8: =IF(OR(P8="",AB8=""),"",IF(OR(P8="Gasto",P8="Transferencia",P8="Pago tarjeta"),-1,1)*IF(IFERROR(INDEX(ctaMoneda,MATCH(AB8,ctaNombre,0))&"","DOP")="USD",T8,S8)) | AG8: =IF(AC8="","",IF(IFERROR(INDEX(ctaMoneda,MATCH(AC8,ctaNombre,0))&"","DOP")="USD",T8,S8)) | AH8: =IF(P8="","",IF(AND(AD8<>"",COUNTIFS(tcTipo,AD8,tcLiq,"Sí")>0),IF(OR(P8="Gasto",P8="Transferencia",P8="Pago tarjeta"),-1,1)*S8,0)+IF(AND(AE8<>"",COUNTIFS(tcTipo,AE8,tcLiq,"Sí")>0),S8,0)) | AI8: =IF(OR(L8="",P8=""),"",IF(COUNTIFS(L$6:L8,L8,P$6:P8,"?*")=1,MAX(AI$5:AI7)+1,""))
B9: 46237 | C9: Gasto | D9: Transporte y vehículo | E9: Combustible | F9: DEMO · Combustible | G9: 2900 | H9: DOP | J9: Tarjeta de crédito | L9: Estación de combustible | N9: DEMOSTRACIÓN | O9: =IF(AND(B9="",G9="",C9="",D9="",J9=""),"",IF(B9="","⚠ Falta fecha",IF(G9="","⚠ Falta monto",IF(Q9="","⚠ Falta cuenta",IF(ISNA(MATCH(Q9,ctaNombre,0)),"⚠ Cuenta no registrada",IF(AND(OR(P9="Gasto",P9="Reembolso"),D9=""),"⚠ Falta categoría",IF(AND(D9<>"",E9<>"",ISNA(MATCH(D9&"|"&E9,catClave,0))),"⚠ Subcategoría no corresponde",IF(AND(OR(P9="Transferencia",P9="Pago tarjeta"),K9=""),"⚠ Falta cuenta destino",IF(AND(K9<>"",P9<>"Transferencia",P9<>"Pago tarjeta"),"⚠ Destino solo aplica a transferencias",IF(AND(K9<>"",K9=Q9),"⚠ Origen igual a destino",IF(AND(K9<>"",ISNA(MATCH(K9,ctaNombre,0))),"⚠ Destino no registrado",IF(AND(P9="Pago tarjeta",AE9<>"Tarjeta de crédito"),"⚠ El destino debe ser tarjeta de crédito",IF(AND(P9="Gasto",E9="Depósitos y retiros"),"⚠ Usa tipo Transferencia",IF(AND(P9="Resultado trading",AD9<>"Cuenta de trading"),"⚠ Usa una cuenta de trading",IF(AND(G9<=0,P9<>"Ajuste",P9<>"Resultado trading"),"⚠ El monto debe ser positivo","✓"))))))))))))))) | P9: =IF(OR(B9="",G9=""),"",IF(C9="","Gasto",C9)) | Q9: =IF(P9="","",IF(J9<>"",J9,CuentaPred&"")) | R9: =IF(P9="","",IF(ISNUMBER(I9),I9,TasaUSD)) | S9: =IF(P9="","",IF(H9="USD",G9*R9,G9)) | T9: =IF(P9="","",IF(H9="USD",G9,IF(R9>0,G9/R9,0))) | U9: =IF(P9="","",IF(P9="Gasto",S9,IF(P9="Reembolso",-S9,0))) | V9: =IF(P9="","",IF(P9="Ingreso",S9,0)) | W9: =IF(P9="","",IF(P9="Resultado trading",S9,0)) | X9: =IF(OR(P9="Gasto",P9="Reembolso"),IF(M9<>"",M9,IFERROR(INDEX(catClasif,MATCH(D9&"|"&E9,catClave,0))&"","Variable")),"") | Y9: =IF(P9="","",IFERROR(INDEX(catGrupo,MATCH(D9&"|"&E9,catClave,0))&"","")) | Z9: =IF(P9="","",WEEKDAY(B9,2)) | AA9: =IF(P9="","",IF(AND(P9="Gasto",X9="Variable",D9<>catTrading,S9>0,S9<=Umbral),1,0)) | AB9: =IF(OR(P9="",Q9=""),"",IFERROR(IF(INDEX(ctaVinc,MATCH(Q9,ctaNombre,0))&""<>"",INDEX(ctaVinc,MATCH(Q9,ctaNombre,0))&"",Q9),Q9)) | AC9: =IF(OR(K9="",AND(P9<>"Transferencia",P9<>"Pago tarjeta")),"",IFERROR(IF(INDEX(ctaVinc,MATCH(K9,ctaNombre,0))&""<>"",INDEX(ctaVinc,MATCH(K9,ctaNombre,0))&"",K9),K9)) | AD9: =IF(AB9="","",IFERROR(INDEX(ctaTipo,MATCH(AB9,ctaNombre,0))&"","")) | AE9: =IF(AC9="","",IFERROR(INDEX(ctaTipo,MATCH(AC9,ctaNombre,0))&"","")) | AF9: =IF(OR(P9="",AB9=""),"",IF(OR(P9="Gasto",P9="Transferencia",P9="Pago tarjeta"),-1,1)*IF(IFERROR(INDEX(ctaMoneda,MATCH(AB9,ctaNombre,0))&"","DOP")="USD",T9,S9)) | AG9: =IF(AC9="","",IF(IFERROR(INDEX(ctaMoneda,MATCH(AC9,ctaNombre,0))&"","DOP")="USD",T9,S9)) | AH9: =IF(P9="","",IF(AND(AD9<>"",COUNTIFS(tcTipo,AD9,tcLiq,"Sí")>0),IF(OR(P9="Gasto",P9="Transferencia",P9="Pago tarjeta"),-1,1)*S9,0)+IF(AND(AE9<>"",COUNTIFS(tcTipo,AE9,tcLiq,"Sí")>0),S9,0)) | AI9: =IF(OR(L9="",P9=""),"",IF(COUNTIFS(L$6:L9,L9,P$6:P9,"?*")=1,MAX(AI$5:AI8)+1,""))
B10: 46237 | C10: Gasto | D10: Tecnología y suscripciones | E10: Herramientas de inteligencia artificial | F10: DEMO · Suscripción herramienta IA | G10: 20 | H10: USD | J10: Tarjeta de crédito | L10: Herramienta IA | N10: DEMOSTRACIÓN | O10: =IF(AND(B10="",G10="",C10="",D10="",J10=""),"",IF(B10="","⚠ Falta fecha",IF(G10="","⚠ Falta monto",IF(Q10="","⚠ Falta cuenta",IF(ISNA(MATCH(Q10,ctaNombre,0)),"⚠ Cuenta no registrada",IF(AND(OR(P10="Gasto",P10="Reembolso"),D10=""),"⚠ Falta categoría",IF(AND(D10<>"",E10<>"",ISNA(MATCH(D10&"|"&E10,catClave,0))),"⚠ Subcategoría no corresponde",IF(AND(OR(P10="Transferencia",P10="Pago tarjeta"),K10=""),"⚠ Falta cuenta destino",IF(AND(K10<>"",P10<>"Transferencia",P10<>"Pago tarjeta"),"⚠ Destino solo aplica a transferencias",IF(AND(K10<>"",K10=Q10),"⚠ Origen igual a destino",IF(AND(K10<>"",ISNA(MATCH(K10,ctaNombre,0))),"⚠ Destino no registrado",IF(AND(P10="Pago tarjeta",AE10<>"Tarjeta de crédito"),"⚠ El destino debe ser tarjeta de crédito",IF(AND(P10="Gasto",E10="Depósitos y retiros"),"⚠ Usa tipo Transferencia",IF(AND(P10="Resultado trading",AD10<>"Cuenta de trading"),"⚠ Usa una cuenta de trading",IF(AND(G10<=0,P10<>"Ajuste",P10<>"Resultado trading"),"⚠ El monto debe ser positivo","✓"))))))))))))))) | P10: =IF(OR(B10="",G10=""),"",IF(C10="","Gasto",C10)) | Q10: =IF(P10="","",IF(J10<>"",J10,CuentaPred&"")) | R10: =IF(P10="","",IF(ISNUMBER(I10),I10,TasaUSD)) | S10: =IF(P10="","",IF(H10="USD",G10*R10,G10)) | T10: =IF(P10="","",IF(H10="USD",G10,IF(R10>0,G10/R10,0))) | U10: =IF(P10="","",IF(P10="Gasto",S10,IF(P10="Reembolso",-S10,0))) | V10: =IF(P10="","",IF(P10="Ingreso",S10,0)) | W10: =IF(P10="","",IF(P10="Resultado trading",S10,0)) | X10: =IF(OR(P10="Gasto",P10="Reembolso"),IF(M10<>"",M10,IFERROR(INDEX(catClasif,MATCH(D10&"|"&E10,catClave,0))&"","Variable")),"") | Y10: =IF(P10="","",IFERROR(INDEX(catGrupo,MATCH(D10&"|"&E10,catClave,0))&"","")) | Z10: =IF(P10="","",WEEKDAY(B10,2)) | AA10: =IF(P10="","",IF(AND(P10="Gasto",X10="Variable",D10<>catTrading,S10>0,S10<=Umbral),1,0)) | AB10: =IF(OR(P10="",Q10=""),"",IFERROR(IF(INDEX(ctaVinc,MATCH(Q10,ctaNombre,0))&""<>"",INDEX(ctaVinc,MATCH(Q10,ctaNombre,0))&"",Q10),Q10)) | AC10: =IF(OR(K10="",AND(P10<>"Transferencia",P10<>"Pago tarjeta")),"",IFERROR(IF(INDEX(ctaVinc,MATCH(K10,ctaNombre,0))&""<>"",INDEX(ctaVinc,MATCH(K10,ctaNombre,0))&"",K10),K10)) | AD10: =IF(AB10="","",IFERROR(INDEX(ctaTipo,MATCH(AB10,ctaNombre,0))&"","")) | AE10: =IF(AC10="","",IFERROR(INDEX(ctaTipo,MATCH(AC10,ctaNombre,0))&"","")) | AF10: =IF(OR(P10="",AB10=""),"",IF(OR(P10="Gasto",P10="Transferencia",P10="Pago tarjeta"),-1,1)*IF(IFERROR(INDEX(ctaMoneda,MATCH(AB10,ctaNombre,0))&"","DOP")="USD",T10,S10)) | AG10: =IF(AC10="","",IF(IFERROR(INDEX(ctaMoneda,MATCH(AC10,ctaNombre,0))&"","DOP")="USD",T10,S10)) | AH10: =IF(P10="","",IF(AND(AD10<>"",COUNTIFS(tcTipo,AD10,tcLiq,"Sí")>0),IF(OR(P10="Gasto",P10="Transferencia",P10="Pago tarjeta"),-1,1)*S10,0)+IF(AND(AE10<>"",COUNTIFS(tcTipo,AE10,tcLiq,"Sí")>0),S10,0)) | AI10: =IF(OR(L10="",P10=""),"",IF(COUNTIFS(L$6:L10,L10,P$6:P10,"?*")=1,MAX(AI$5:AI9)+1,""))
B11: 46238 | C11: Gasto | D11: Alimentación | E11: Almuerzos laborales | F11: DEMO · Almuerzo laboral | G11: 375 | H11: DOP | J11: Tarjeta de débito | L11: Comedor ejecutivo | N11: DEMOSTRACIÓN | O11: =IF(AND(B11="",G11="",C11="",D11="",J11=""),"",IF(B11="","⚠ Falta fecha",IF(G11="","⚠ Falta monto",IF(Q11="","⚠ Falta cuenta",IF(ISNA(MATCH(Q11,ctaNombre,0)),"⚠ Cuenta no registrada",IF(AND(OR(P11="Gasto",P11="Reembolso"),D11=""),"⚠ Falta categoría",IF(AND(D11<>"",E11<>"",ISNA(MATCH(D11&"|"&E11,catClave,0))),"⚠ Subcategoría no corresponde",IF(AND(OR(P11="Transferencia",P11="Pago tarjeta"),K11=""),"⚠ Falta cuenta destino",IF(AND(K11<>"",P11<>"Transferencia",P11<>"Pago tarjeta"),"⚠ Destino solo aplica a transferencias",IF(AND(K11<>"",K11=Q11),"⚠ Origen igual a destino",IF(AND(K11<>"",ISNA(MATCH(K11,ctaNombre,0))),"⚠ Destino no registrado",IF(AND(P11="Pago tarjeta",AE11<>"Tarjeta de crédito"),"⚠ El destino debe ser tarjeta de crédito",IF(AND(P11="Gasto",E11="Depósitos y retiros"),"⚠ Usa tipo Transferencia",IF(AND(P11="Resultado trading",AD11<>"Cuenta de trading"),"⚠ Usa una cuenta de trading",IF(AND(G11<=0,P11<>"Ajuste",P11<>"Resultado trading"),"⚠ El monto debe ser positivo","✓"))))))))))))))) | P11: =IF(OR(B11="",G11=""),"",IF(C11="","Gasto",C11)) | Q11: =IF(P11="","",IF(J11<>"",J11,CuentaPred&"")) | R11: =IF(P11="","",IF(ISNUMBER(I11),I11,TasaUSD)) | S11: =IF(P11="","",IF(H11="USD",G11*R11,G11)) | T11: =IF(P11="","",IF(H11="USD",G11,IF(R11>0,G11/R11,0))) | U11: =IF(P11="","",IF(P11="Gasto",S11,IF(P11="Reembolso",-S11,0))) | V11: =IF(P11="","",IF(P11="Ingreso",S11,0)) | W11: =IF(P11="","",IF(P11="Resultado trading",S11,0)) | X11: =IF(OR(P11="Gasto",P11="Reembolso"),IF(M11<>"",M11,IFERROR(INDEX(catClasif,MATCH(D11&"|"&E11,catClave,0))&"","Variable")),"") | Y11: =IF(P11="","",IFERROR(INDEX(catGrupo,MATCH(D11&"|"&E11,catClave,0))&"","")) | Z11: =IF(P11="","",WEEKDAY(B11,2)) | AA11: =IF(P11="","",IF(AND(P11="Gasto",X11="Variable",D11<>catTrading,S11>0,S11<=Umbral),1,0)) | AB11: =IF(OR(P11="",Q11=""),"",IFERROR(IF(INDEX(ctaVinc,MATCH(Q11,ctaNombre,0))&""<>"",INDEX(ctaVinc,MATCH(Q11,ctaNombre,0))&"",Q11),Q11)) | AC11: =IF(OR(K11="",AND(P11<>"Transferencia",P11<>"Pago tarjeta")),"",IFERROR(IF(INDEX(ctaVinc,MATCH(K11,ctaNombre,0))&""<>"",INDEX(ctaVinc,MATCH(K11,ctaNombre,0))&"",K11),K11)) | AD11: =IF(AB11="","",IFERROR(INDEX(ctaTipo,MATCH(AB11,ctaNombre,0))&"","")) | AE11: =IF(AC11="","",IFERROR(INDEX(ctaTipo,MATCH(AC11,ctaNombre,0))&"","")) | AF11: =IF(OR(P11="",AB11=""),"",IF(OR(P11="Gasto",P11="Transferencia",P11="Pago tarjeta"),-1,1)*IF(IFERROR(INDEX(ctaMoneda,MATCH(AB11,ctaNombre,0))&"","DOP")="USD",T11,S11)) | AG11: =IF(AC11="","",IF(IFERROR(INDEX(ctaMoneda,MATCH(AC11,ctaNombre,0))&"","DOP")="USD",T11,S11)) | AH11: =IF(P11="","",IF(AND(AD11<>"",COUNTIFS(tcTipo,AD11,tcLiq,"Sí")>0),IF(OR(P11="Gasto",P11="Transferencia",P11="Pago tarjeta"),-1,1)*S11,0)+IF(AND(AE11<>"",COUNTIFS(tcTipo,AE11,tcLiq,"Sí")>0),S11,0)) | AI11: =IF(OR(L11="",P11=""),"",IF(COUNTIFS(L$6:L11,L11,P$6:P11,"?*")=1,MAX(AI$5:AI10)+1,""))
B12: 46238 | C12: Gasto | D12: Alimentación | E12: Bebidas, snacks y otros consumos | F12: DEMO · Café | G12: 160 | H12: DOP | J12: Efectivo | L12: Colmado del barrio | N12: DEMOSTRACIÓN | O12: =IF(AND(B12="",G12="",C12="",D12="",J12=""),"",IF(B12="","⚠ Falta fecha",IF(G12="","⚠ Falta monto",IF(Q12="","⚠ Falta cuenta",IF(ISNA(MATCH(Q12,ctaNombre,0)),"⚠ Cuenta no registrada",IF(AND(OR(P12="Gasto",P12="Reembolso"),D12=""),"⚠ Falta categoría",IF(AND(D12<>"",E12<>"",ISNA(MATCH(D12&"|"&E12,catClave,0))),"⚠ Subcategoría no corresponde",IF(AND(OR(P12="Transferencia",P12="Pago tarjeta"),K12=""),"⚠ Falta cuenta destino",IF(AND(K12<>"",P12<>"Transferencia",P12<>"Pago tarjeta"),"⚠ Destino solo aplica a transferencias",IF(AND(K12<>"",K12=Q12),"⚠ Origen igual a destino",IF(AND(K12<>"",ISNA(MATCH(K12,ctaNombre,0))),"⚠ Destino no registrado",IF(AND(P12="Pago tarjeta",AE12<>"Tarjeta de crédito"),"⚠ El destino debe ser tarjeta de crédito",IF(AND(P12="Gasto",E12="Depósitos y retiros"),"⚠ Usa tipo Transferencia",IF(AND(P12="Resultado trading",AD12<>"Cuenta de trading"),"⚠ Usa una cuenta de trading",IF(AND(G12<=0,P12<>"Ajuste",P12<>"Resultado trading"),"⚠ El monto debe ser positivo","✓"))))))))))))))) | P12: =IF(OR(B12="",G12=""),"",IF(C12="","Gasto",C12)) | Q12: =IF(P12="","",IF(J12<>"",J12,CuentaPred&"")) | R12: =IF(P12="","",IF(ISNUMBER(I12),I12,TasaUSD)) | S12: =IF(P12="","",IF(H12="USD",G12*R12,G12)) | T12: =IF(P12="","",IF(H12="USD",G12,IF(R12>0,G12/R12,0))) | U12: =IF(P12="","",IF(P12="Gasto",S12,IF(P12="Reembolso",-S12,0))) | V12: =IF(P12="","",IF(P12="Ingreso",S12,0)) | W12: =IF(P12="","",IF(P12="Resultado trading",S12,0)) | X12: =IF(OR(P12="Gasto",P12="Reembolso"),IF(M12<>"",M12,IFERROR(INDEX(catClasif,MATCH(D12&"|"&E12,catClave,0))&"","Variable")),"") | Y12: =IF(P12="","",IFERROR(INDEX(catGrupo,MATCH(D12&"|"&E12,catClave,0))&"","")) | Z12: =IF(P12="","",WEEKDAY(B12,2)) | AA12: =IF(P12="","",IF(AND(P12="Gasto",X12="Variable",D12<>catTrading,S12>0,S12<=Umbral),1,0)) | AB12: =IF(OR(P12="",Q12=""),"",IFERROR(IF(INDEX(ctaVinc,MATCH(Q12,ctaNombre,0))&""<>"",INDEX(ctaVinc,MATCH(Q12,ctaNombre,0))&"",Q12),Q12)) | AC12: =IF(OR(K12="",AND(P12<>"Transferencia",P12<>"Pago tarjeta")),"",IFERROR(IF(INDEX(ctaVinc,MATCH(K12,ctaNombre,0))&""<>"",INDEX(ctaVinc,MATCH(K12,ctaNombre,0))&"",K12),K12)) | AD12: =IF(AB12="","",IFERROR(INDEX(ctaTipo,MATCH(AB12,ctaNombre,0))&"","")) | AE12: =IF(AC12="","",IFERROR(INDEX(ctaTipo,MATCH(AC12,ctaNombre,0))&"","")) | AF12: =IF(OR(P12="",AB12=""),"",IF(OR(P12="Gasto",P12="Transferencia",P12="Pago tarjeta"),-1,1)*IF(IFERROR(INDEX(ctaMoneda,MATCH(AB12,ctaNombre,0))&"","DOP")="USD",T12,S12)) | AG12: =IF(AC12="","",IF(IFERROR(INDEX(ctaMoneda,MATCH(AC12,ctaNombre,0))&"","DOP")="USD",T12,S12)) | AH12: =IF(P12="","",IF(AND(AD12<>"",COUNTIFS(tcTipo,AD12,tcLiq,"Sí")>0),IF(OR(P12="Gasto",P12="Transferencia",P12="Pago tarjeta"),-1,1)*S12,0)+IF(AND(AE12<>"",COUNTIFS(tcTipo,AE12,tcLiq,"Sí")>0),S12,0)) | AI12: =IF(OR(L12="",P12=""),"",IF(COUNTIFS(L$6:L12,L12,P$6:P12,"?*")=1,MAX(AI$5:AI11)+1,""))
B13: 46239 | C13: Gasto | D13: Alimentación | E13: Desayunos comprados | F13: DEMO · Desayuno en la oficina | G13: 290 | H13: DOP | J13: Efectivo | L13: Cafetería del trabajo | N13: DEMOSTRACIÓN | O13: =IF(AND(B13="",G13="",C13="",D13="",J13=""),"",IF(B13="","⚠ Falta fecha",IF(G13="","⚠ Falta monto",IF(Q13="","⚠ Falta cuenta",IF(ISNA(MATCH(Q13,ctaNombre,0)),"⚠ Cuenta no registrada",IF(AND(OR(P13="Gasto",P13="Reembolso"),D13=""),"⚠ Falta categoría",IF(AND(D13<>"",E13<>"",ISNA(MATCH(D13&"|"&E13,catClave,0))),"⚠ Subcategoría no corresponde",IF(AND(OR(P13="Transferencia",P13="Pago tarjeta"),K13=""),"⚠ Falta cuenta destino",IF(AND(K13<>"",P13<>"Transferencia",P13<>"Pago tarjeta"),"⚠ Destino solo aplica a transferencias",IF(AND(K13<>"",K13=Q13),"⚠ Origen igual a destino",IF(AND(K13<>"",ISNA(MATCH(K13,ctaNombre,0))),"⚠ Destino no registrado",IF(AND(P13="Pago tarjeta",AE13<>"Tarjeta de crédito"),"⚠ El destino debe ser tarjeta de crédito",IF(AND(P13="Gasto",E13="Depósitos y retiros"),"⚠ Usa tipo Transferencia",IF(AND(P13="Resultado trading",AD13<>"Cuenta de trading"),"⚠ Usa una cuenta de trading",IF(AND(G13<=0,P13<>"Ajuste",P13<>"Resultado trading"),"⚠ El monto debe ser positivo","✓"))))))))))))))) | P13: =IF(OR(B13="",G13=""),"",IF(C13="","Gasto",C13)) | Q13: =IF(P13="","",IF(J13<>"",J13,CuentaPred&"")) | R13: =IF(P13="","",IF(ISNUMBER(I13),I13,TasaUSD)) | S13: =IF(P13="","",IF(H13="USD",G13*R13,G13)) | T13: =IF(P13="","",IF(H13="USD",G13,IF(R13>0,G13/R13,0))) | U13: =IF(P13="","",IF(P13="Gasto",S13,IF(P13="Reembolso",-S13,0))) | V13: =IF(P13="","",IF(P13="Ingreso",S13,0)) | W13: =IF(P13="","",IF(P13="Resultado trading",S13,0)) | X13: =IF(OR(P13="Gasto",P13="Reembolso"),IF(M13<>"",M13,IFERROR(INDEX(catClasif,MATCH(D13&"|"&E13,catClave,0))&"","Variable")),"") | Y13: =IF(P13="","",IFERROR(INDEX(catGrupo,MATCH(D13&"|"&E13,catClave,0))&"","")) | Z13: =IF(P13="","",WEEKDAY(B13,2)) | AA13: =IF(P13="","",IF(AND(P13="Gasto",X13="Variable",D13<>catTrading,S13>0,S13<=Umbral),1,0)) | AB13: =IF(OR(P13="",Q13=""),"",IFERROR(IF(INDEX(ctaVinc,MATCH(Q13,ctaNombre,0))&""<>"",INDEX(ctaVinc,MATCH(Q13,ctaNombre,0))&"",Q13),Q13)) | AC13: =IF(OR(K13="",AND(P13<>"Transferencia",P13<>"Pago tarjeta")),"",IFERROR(IF(INDEX(ctaVinc,MATCH(K13,ctaNombre,0))&""<>"",INDEX(ctaVinc,MATCH(K13,ctaNombre,0))&"",K13),K13)) | AD13: =IF(AB13="","",IFERROR(INDEX(ctaTipo,MATCH(AB13,ctaNombre,0))&"","")) | AE13: =IF(AC13="","",IFERROR(INDEX(ctaTipo,MATCH(AC13,ctaNombre,0))&"","")) | AF13: =IF(OR(P13="",AB13=""),"",IF(OR(P13="Gasto",P13="Transferencia",P13="Pago tarjeta"),-1,1)*IF(IFERROR(INDEX(ctaMoneda,MATCH(AB13,ctaNombre,0))&"","DOP")="USD",T13,S13)) | AG13: =IF(AC13="","",IF(IFERROR(INDEX(ctaMoneda,MATCH(AC13,ctaNombre,0))&"","DOP")="USD",T13,S13)) | AH13: =IF(P13="","",IF(AND(AD13<>"",COUNTIFS(tcTipo,AD13,tcLiq,"Sí")>0),IF(OR(P13="Gasto",P13="Transferencia",P13="Pago tarjeta"),-1,1)*S13,0)+IF(AND(AE13<>"",COUNTIFS(tcTipo,AE13,tcLiq,"Sí")>0),S13,0)) | AI13: =IF(OR(L13="",P13=""),"",IF(COUNTIFS(L$6:L13,L13,P$6:P13,"?*")=1,MAX(AI$5:AI12)+1,""))
B14: 46239 | C14: Gasto | D14: Alimentación | E14: Cenas compradas | F14: DEMO · Cena comprada | G14: 525 | H14: DOP | J14: Tarjeta de crédito | L14: Pizzería del sector | N14: DEMOSTRACIÓN | O14: =IF(AND(B14="",G14="",C14="",D14="",J14=""),"",IF(B14="","⚠ Falta fecha",IF(G14="","⚠ Falta monto",IF(Q14="","⚠ Falta cuenta",IF(ISNA(MATCH(Q14,ctaNombre,0)),"⚠ Cuenta no registrada",IF(AND(OR(P14="Gasto",P14="Reembolso"),D14=""),"⚠ Falta categoría",IF(AND(D14<>"",E14<>"",ISNA(MATCH(D14&"|"&E14,catClave,0))),"⚠ Subcategoría no corresponde",IF(AND(OR(P14="Transferencia",P14="Pago tarjeta"),K14=""),"⚠ Falta cuenta destino",IF(AND(K14<>"",P14<>"Transferencia",P14<>"Pago tarjeta"),"⚠ Destino solo aplica a transferencias",IF(AND(K14<>"",K14=Q14),"⚠ Origen igual a destino",IF(AND(K14<>"",ISNA(MATCH(K14,ctaNombre,0))),"⚠ Destino no registrado",IF(AND(P14="Pago tarjeta",AE14<>"Tarjeta de crédito"),"⚠ El destino debe ser tarjeta de crédito",IF(AND(P14="Gasto",E14="Depósitos y retiros"),"⚠ Usa tipo Transferencia",IF(AND(P14="Resultado trading",AD14<>"Cuenta de trading"),"⚠ Usa una cuenta de trading",IF(AND(G14<=0,P14<>"Ajuste",P14<>"Resultado trading"),"⚠ El monto debe ser positivo","✓"))))))))))))))) | P14: =IF(OR(B14="",G14=""),"",IF(C14="","Gasto",C14)) | Q14: =IF(P14="","",IF(J14<>"",J14,CuentaPred&"")) | R14: =IF(P14="","",IF(ISNUMBER(I14),I14,TasaUSD)) | S14: =IF(P14="","",IF(H14="USD",G14*R14,G14)) | T14: =IF(P14="","",IF(H14="USD",G14,IF(R14>0,G14/R14,0))) | U14: =IF(P14="","",IF(P14="Gasto",S14,IF(P14="Reembolso",-S14,0))) | V14: =IF(P14="","",IF(P14="Ingreso",S14,0)) | W14: =IF(P14="","",IF(P14="Resultado trading",S14,0)) | X14: =IF(OR(P14="Gasto",P14="Reembolso"),IF(M14<>"",M14,IFERROR(INDEX(catClasif,MATCH(D14&"|"&E14,catClave,0))&"","Variable")),"") | Y14: =IF(P14="","",IFERROR(INDEX(catGrupo,MATCH(D14&"|"&E14,catClave,0))&"","")) | Z14: =IF(P14="","",WEEKDAY(B14,2)) | AA14: =IF(P14="","",IF(AND(P14="Gasto",X14="Variable",D14<>catTrading,S14>0,S14<=Umbral),1,0)) | AB14: =IF(OR(P14="",Q14=""),"",IFERROR(IF(INDEX(ctaVinc,MATCH(Q14,ctaNombre,0))&""<>"",INDEX(ctaVinc,MATCH(Q14,ctaNombre,0))&"",Q14),Q14)) | AC14: =IF(OR(K14="",AND(P14<>"Transferencia",P14<>"Pago tarjeta")),"",IFERROR(IF(INDEX(ctaVinc,MATCH(K14,ctaNombre,0))&""<>"",INDEX(ctaVinc,MATCH(K14,ctaNombre,0))&"",K14),K14)) | AD14: =IF(AB14="","",IFERROR(INDEX(ctaTipo,MATCH(AB14,ctaNombre,0))&"","")) | AE14: =IF(AC14="","",IFERROR(INDEX(ctaTipo,MATCH(AC14,ctaNombre,0))&"","")) | AF14: =IF(OR(P14="",AB14=""),"",IF(OR(P14="Gasto",P14="Transferencia",P14="Pago tarjeta"),-1,1)*IF(IFERROR(INDEX(ctaMoneda,MATCH(AB14,ctaNombre,0))&"","DOP")="USD",T14,S14)) | AG14: =IF(AC14="","",IF(IFERROR(INDEX(ctaMoneda,MATCH(AC14,ctaNombre,0))&"","DOP")="USD",T14,S14)) | AH14: =IF(P14="","",IF(AND(AD14<>"",COUNTIFS(tcTipo,AD14,tcLiq,"Sí")>0),IF(OR(P14="Gasto",P14="Transferencia",P14="Pago tarjeta"),-1,1)*S14,0)+IF(AND(AE14<>"",COUNTIFS(tcTipo,AE14,tcLiq,"Sí")>0),S14,0)) | AI14: =IF(OR(L14="",P14=""),"",IF(COUNTIFS(L$6:L14,L14,P$6:P14,"?*")=1,MAX(AI$5:AI13)+1,""))
B15: 46239 | C15: Gasto | D15: Hogar y servicios | E15: Internet | F15: DEMO · Internet del hogar | G15: 2050 | H15: DOP | J15: Banco principal | L15: Proveedor de internet | N15: DEMOSTRACIÓN | O15: =IF(AND(B15="",G15="",C15="",D15="",J15=""),"",IF(B15="","⚠ Falta fecha",IF(G15="","⚠ Falta monto",IF(Q15="","⚠ Falta cuenta",IF(ISNA(MATCH(Q15,ctaNombre,0)),"⚠ Cuenta no registrada",IF(AND(OR(P15="Gasto",P15="Reembolso"),D15=""),"⚠ Falta categoría",IF(AND(D15<>"",E15<>"",ISNA(MATCH(D15&"|"&E15,catClave,0))),"⚠ Subcategoría no corresponde",IF(AND(OR(P15="Transferencia",P15="Pago tarjeta"),K15=""),"⚠ Falta cuenta destino",IF(AND(K15<>"",P15<>"Transferencia",P15<>"Pago tarjeta"),"⚠ Destino solo aplica a transferencias",IF(AND(K15<>"",K15=Q15),"⚠ Origen igual a destino",IF(AND(K15<>"",ISNA(MATCH(K15,ctaNombre,0))),"⚠ Destino no registrado",IF(AND(P15="Pago tarjeta",AE15<>"Tarjeta de crédito"),"⚠ El destino debe ser tarjeta de crédito",IF(AND(P15="Gasto",E15="Depósitos y retiros"),"⚠ Usa tipo Transferencia",IF(AND(P15="Resultado trading",AD15<>"Cuenta de trading"),"⚠ Usa una cuenta de trading",IF(AND(G15<=0,P15<>"Ajuste",P15<>"Resultado trading"),"⚠ El monto debe ser positivo","✓"))))))))))))))) | P15: =IF(OR(B15="",G15=""),"",IF(C15="","Gasto",C15)) | Q15: =IF(P15="","",IF(J15<>"",J15,CuentaPred&"")) | R15: =IF(P15="","",IF(ISNUMBER(I15),I15,TasaUSD)) | S15: =IF(P15="","",IF(H15="USD",G15*R15,G15)) | T15: =IF(P15="","",IF(H15="USD",G15,IF(R15>0,G15/R15,0))) | U15: =IF(P15="","",IF(P15="Gasto",S15,IF(P15="Reembolso",-S15,0))) | V15: =IF(P15="","",IF(P15="Ingreso",S15,0)) | W15: =IF(P15="","",IF(P15="Resultado trading",S15,0)) | X15: =IF(OR(P15="Gasto",P15="Reembolso"),IF(M15<>"",M15,IFERROR(INDEX(catClasif,MATCH(D15&"|"&E15,catClave,0))&"","Variable")),"") | Y15: =IF(P15="","",IFERROR(INDEX(catGrupo,MATCH(D15&"|"&E15,catClave,0))&"","")) | Z15: =IF(P15="","",WEEKDAY(B15,2)) | AA15: =IF(P15="","",IF(AND(P15="Gasto",X15="Variable",D15<>catTrading,S15>0,S15<=Umbral),1,0)) | AB15: =IF(OR(P15="",Q15=""),"",IFERROR(IF(INDEX(ctaVinc,MATCH(Q15,ctaNombre,0))&""<>"",INDEX(ctaVinc,MATCH(Q15,ctaNombre,0))&"",Q15),Q15)) | AC15: =IF(OR(K15="",AND(P15<>"Transferencia",P15<>"Pago tarjeta")),"",IFERROR(IF(INDEX(ctaVinc,MATCH(K15,ctaNombre,0))&""<>"",INDEX(ctaVinc,MATCH(K15,ctaNombre,0))&"",K15),K15)) | AD15: =IF(AB15="","",IFERROR(INDEX(ctaTipo,MATCH(AB15,ctaNombre,0))&"","")) | AE15: =IF(AC15="","",IFERROR(INDEX(ctaTipo,MATCH(AC15,ctaNombre,0))&"","")) | AF15: =IF(OR(P15="",AB15=""),"",IF(OR(P15="Gasto",P15="Transferencia",P15="Pago tarjeta"),-1,1)*IF(IFERROR(INDEX(ctaMoneda,MATCH(AB15,ctaNombre,0))&"","DOP")="USD",T15,S15)) | AG15: =IF(AC15="","",IF(IFERROR(INDEX(ctaMoneda,MATCH(AC15,ctaNombre,0))&"","DOP")="USD",T15,S15)) | AH15: =IF(P15="","",IF(AND(AD15<>"",COUNTIFS(tcTipo,AD15,tcLiq,"Sí")>0),IF(OR(P15="Gasto",P15="Transferencia",P15="Pago tarjeta"),-1,1)*S15,0)+IF(AND(AE15<>"",COUNTIFS(tcTipo,AE15,tcLiq,"Sí")>0),S15,0)) | AI15: =IF(OR(L15="",P15=""),"",IF(COUNTIFS(L$6:L15,L15,P$6:P15,"?*")=1,MAX(AI$5:AI14)+1,""))
B16: 46240 | C16: Gasto | D16: Alimentación | E16: Desayunos comprados | F16: DEMO · Desayuno en la oficina | G16: 220 | H16: DOP | J16: Efectivo | L16: Cafetería del trabajo | N16: DEMOSTRACIÓN | O16: =IF(AND(B16="",G16="",C16="",D16="",J16=""),"",IF(B16="","⚠ Falta fecha",IF(G16="","⚠ Falta monto",IF(Q16="","⚠ Falta cuenta",IF(ISNA(MATCH(Q16,ctaNombre,0)),"⚠ Cuenta no registrada",IF(AND(OR(P16="Gasto",P16="Reembolso"),D16=""),"⚠ Falta categoría",IF(AND(D16<>"",E16<>"",ISNA(MATCH(D16&"|"&E16,catClave,0))),"⚠ Subcategoría no corresponde",IF(AND(OR(P16="Transferencia",P16="Pago tarjeta"),K16=""),"⚠ Falta cuenta destino",IF(AND(K16<>"",P16<>"Transferencia",P16<>"Pago tarjeta"),"⚠ Destino solo aplica a transferencias",IF(AND(K16<>"",K16=Q16),"⚠ Origen igual a destino",IF(AND(K16<>"",ISNA(MATCH(K16,ctaNombre,0))),"⚠ Destino no registrado",IF(AND(P16="Pago tarjeta",AE16<>"Tarjeta de crédito"),"⚠ El destino debe ser tarjeta de crédito",IF(AND(P16="Gasto",E16="Depósitos y retiros"),"⚠ Usa tipo Transferencia",IF(AND(P16="Resultado trading",AD16<>"Cuenta de trading"),"⚠ Usa una cuenta de trading",IF(AND(G16<=0,P16<>"Ajuste",P16<>"Resultado trading"),"⚠ El monto debe ser positivo","✓"))))))))))))))) | P16: =IF(OR(B16="",G16=""),"",IF(C16="","Gasto",C16)) | Q16: =IF(P16="","",IF(J16<>"",J16,CuentaPred&"")) | R16: =IF(P16="","",IF(ISNUMBER(I16),I16,TasaUSD)) | S16: =IF(P16="","",IF(H16="USD",G16*R16,G16)) | T16: =IF(P16="","",IF(H16="USD",G16,IF(R16>0,G16/R16,0))) | U16: =IF(P16="","",IF(P16="Gasto",S16,IF(P16="Reembolso",-S16,0))) | V16: =IF(P16="","",IF(P16="Ingreso",S16,0)) | W16: =IF(P16="","",IF(P16="Resultado trading",S16,0)) | X16: =IF(OR(P16="Gasto",P16="Reembolso"),IF(M16<>"",M16,IFERROR(INDEX(catClasif,MATCH(D16&"|"&E16,catClave,0))&"","Variable")),"") | Y16: =IF(P16="","",IFERROR(INDEX(catGrupo,MATCH(D16&"|"&E16,catClave,0))&"","")) | Z16: =IF(P16="","",WEEKDAY(B16,2)) | AA16: =IF(P16="","",IF(AND(P16="Gasto",X16="Variable",D16<>catTrading,S16>0,S16<=Umbral),1,0)) | AB16: =IF(OR(P16="",Q16=""),"",IFERROR(IF(INDEX(ctaVinc,MATCH(Q16,ctaNombre,0))&""<>"",INDEX(ctaVinc,MATCH(Q16,ctaNombre,0))&"",Q16),Q16)) | AC16: =IF(OR(K16="",AND(P16<>"Transferencia",P16<>"Pago tarjeta")),"",IFERROR(IF(INDEX(ctaVinc,MATCH(K16,ctaNombre,0))&""<>"",INDEX(ctaVinc,MATCH(K16,ctaNombre,0))&"",K16),K16)) | AD16: =IF(AB16="","",IFERROR(INDEX(ctaTipo,MATCH(AB16,ctaNombre,0))&"","")) | AE16: =IF(AC16="","",IFERROR(INDEX(ctaTipo,MATCH(AC16,ctaNombre,0))&"","")) | AF16: =IF(OR(P16="",AB16=""),"",IF(OR(P16="Gasto",P16="Transferencia",P16="Pago tarjeta"),-1,1)*IF(IFERROR(INDEX(ctaMoneda,MATCH(AB16,ctaNombre,0))&"","DOP")="USD",T16,S16)) | AG16: =IF(AC16="","",IF(IFERROR(INDEX(ctaMoneda,MATCH(AC16,ctaNombre,0))&"","DOP")="USD",T16,S16)) | AH16: =IF(P16="","",IF(AND(AD16<>"",COUNTIFS(tcTipo,AD16,tcLiq,"Sí")>0),IF(OR(P16="Gasto",P16="Transferencia",P16="Pago tarjeta"),-1,1)*S16,0)+IF(AND(AE16<>"",COUNTIFS(tcTipo,AE16,tcLiq,"Sí")>0),S16,0)) | AI16: =IF(OR(L16="",P16=""),"",IF(COUNTIFS(L$6:L16,L16,P$6:P16,"?*")=1,MAX(AI$5:AI15)+1,""))
B17: 46240 | C17: Gasto | D17: Alimentación | E17: Almuerzos laborales | F17: DEMO · Almuerzo laboral | G17: 475 | H17: DOP | J17: Billetera digital | L17: Comedor ejecutivo | N17: DEMOSTRACIÓN | O17: =IF(AND(B17="",G17="",C17="",D17="",J17=""),"",IF(B17="","⚠ Falta fecha",IF(G17="","⚠ Falta monto",IF(Q17="","⚠ Falta cuenta",IF(ISNA(MATCH(Q17,ctaNombre,0)),"⚠ Cuenta no registrada",IF(AND(OR(P17="Gasto",P17="Reembolso"),D17=""),"⚠ Falta categoría",IF(AND(D17<>"",E17<>"",ISNA(MATCH(D17&"|"&E17,catClave,0))),"⚠ Subcategoría no corresponde",IF(AND(OR(P17="Transferencia",P17="Pago tarjeta"),K17=""),"⚠ Falta cuenta destino",IF(AND(K17<>"",P17<>"Transferencia",P17<>"Pago tarjeta"),"⚠ Destino solo aplica a transferencias",IF(AND(K17<>"",K17=Q17),"⚠ Origen igual a destino",IF(AND(K17<>"",ISNA(MATCH(K17,ctaNombre,0))),"⚠ Destino no registrado",IF(AND(P17="Pago tarjeta",AE17<>"Tarjeta de crédito"),"⚠ El destino debe ser tarjeta de crédito",IF(AND(P17="Gasto",E17="Depósitos y retiros"),"⚠ Usa tipo Transferencia",IF(AND(P17="Resultado trading",AD17<>"Cuenta de trading"),"⚠ Usa una cuenta de trading",IF(AND(G17<=0,P17<>"Ajuste",P17<>"Resultado trading"),"⚠ El monto debe ser positivo","✓"))))))))))))))) | P17: =IF(OR(B17="",G17=""),"",IF(C17="","Gasto",C17)) | Q17: =IF(P17="","",IF(J17<>"",J17,CuentaPred&"")) | R17: =IF(P17="","",IF(ISNUMBER(I17),I17,TasaUSD)) | S17: =IF(P17="","",IF(H17="USD",G17*R17,G17)) | T17: =IF(P17="","",IF(H17="USD",G17,IF(R17>0,G17/R17,0))) | U17: =IF(P17="","",IF(P17="Gasto",S17,IF(P17="Reembolso",-S17,0))) | V17: =IF(P17="","",IF(P17="Ingreso",S17,0)) | W17: =IF(P17="","",IF(P17="Resultado trading",S17,0)) | X17: =IF(OR(P17="Gasto",P17="Reembolso"),IF(M17<>"",M17,IFERROR(INDEX(catClasif,MATCH(D17&"|"&E17,catClave,0))&"","Variable")),"") | Y17: =IF(P17="","",IFERROR(INDEX(catGrupo,MATCH(D17&"|"&E17,catClave,0))&"","")) | Z17: =IF(P17="","",WEEKDAY(B17,2)) | AA17: =IF(P17="","",IF(AND(P17="Gasto",X17="Variable",D17<>catTrading,S17>0,S17<=Umbral),1,0)) | AB17: =IF(OR(P17="",Q17=""),"",IFERROR(IF(INDEX(ctaVinc,MATCH(Q17,ctaNombre,0))&""<>"",INDEX(ctaVinc,MATCH(Q17,ctaNombre,0))&"",Q17),Q17)) | AC17: =IF(OR(K17="",AND(P17<>"Transferencia",P17<>"Pago tarjeta")),"",IFERROR(IF(INDEX(ctaVinc,MATCH(K17,ctaNombre,0))&""<>"",INDEX(ctaVinc,MATCH(K17,ctaNombre,0))&"",K17),K17)) | AD17: =IF(AB17="","",IFERROR(INDEX(ctaTipo,MATCH(AB17,ctaNombre,0))&"","")) | AE17: =IF(AC17="","",IFERROR(INDEX(ctaTipo,MATCH(AC17,ctaNombre,0))&"","")) | AF17: =IF(OR(P17="",AB17=""),"",IF(OR(P17="Gasto",P17="Transferencia",P17="Pago tarjeta"),-1,1)*IF(IFERROR(INDEX(ctaMoneda,MATCH(AB17,ctaNombre,0))&"","DOP")="USD",T17,S17)) | AG17: =IF(AC17="","",IF(IFERROR(INDEX(ctaMoneda,MATCH(AC17,ctaNombre,0))&"","DOP")="USD",T17,S17)) | AH17: =IF(P17="","",IF(AND(AD17<>"",COUNTIFS(tcTipo,AD17,tcLiq,"Sí")>0),IF(OR(P17="Gasto",P17="Transferencia",P17="Pago tarjeta"),-1,1)*S17,0)+IF(AND(AE17<>"",COUNTIFS(tcTipo,AE17,tcLiq,"Sí")>0),S17,0)) | AI17: =IF(OR(L17="",P17=""),"",IF(COUNTIFS(L$6:L17,L17,P$6:P17,"?*")=1,MAX(AI$5:AI16)+1,""))
B18: 46240 | C18: Gasto | D18: Transporte y vehículo | E18: Parqueos y peajes | F18: DEMO · Parqueo | G18: 100 | H18: DOP | J18: Efectivo | L18: Parqueo centro | N18: DEMOSTRACIÓN | O18: =IF(AND(B18="",G18="",C18="",D18="",J18=""),"",IF(B18="","⚠ Falta fecha",IF(G18="","⚠ Falta monto",IF(Q18="","⚠ Falta cuenta",IF(ISNA(MATCH(Q18,ctaNombre,0)),"⚠ Cuenta no registrada",IF(AND(OR(P18="Gasto",P18="Reembolso"),D18=""),"⚠ Falta categoría",IF(AND(D18<>"",E18<>"",ISNA(MATCH(D18&"|"&E18,catClave,0))),"⚠ Subcategoría no corresponde",IF(AND(OR(P18="Transferencia",P18="Pago tarjeta"),K18=""),"⚠ Falta cuenta destino",IF(AND(K18<>"",P18<>"Transferencia",P18<>"Pago tarjeta"),"⚠ Destino solo aplica a transferencias",IF(AND(K18<>"",K18=Q18),"⚠ Origen igual a destino",IF(AND(K18<>"",ISNA(MATCH(K18,ctaNombre,0))),"⚠ Destino no registrado",IF(AND(P18="Pago tarjeta",AE18<>"Tarjeta de crédito"),"⚠ El destino debe ser tarjeta de crédito",IF(AND(P18="Gasto",E18="Depósitos y retiros"),"⚠ Usa tipo Transferencia",IF(AND(P18="Resultado trading",AD18<>"Cuenta de trading"),"⚠ Usa una cuenta de trading",IF(AND(G18<=0,P18<>"Ajuste",P18<>"Resultado trading"),"⚠ El monto debe ser positivo","✓"))))))))))))))) | P18: =IF(OR(B18="",G18=""),"",IF(C18="","Gasto",C18)) | Q18: =IF(P18="","",IF(J18<>"",J18,CuentaPred&"")) | R18: =IF(P18="","",IF(ISNUMBER(I18),I18,TasaUSD)) | S18: =IF(P18="","",IF(H18="USD",G18*R18,G18)) | T18: =IF(P18="","",IF(H18="USD",G18,IF(R18>0,G18/R18,0))) | U18: =IF(P18="","",IF(P18="Gasto",S18,IF(P18="Reembolso",-S18,0))) | V18: =IF(P18="","",IF(P18="Ingreso",S18,0)) | W18: =IF(P18="","",IF(P18="Resultado trading",S18,0)) | X18: =IF(OR(P18="Gasto",P18="Reembolso"),IF(M18<>"",M18,IFERROR(INDEX(catClasif,MATCH(D18&"|"&E18,catClave,0))&"","Variable")),"") | Y18: =IF(P18="","",IFERROR(INDEX(catGrupo,MATCH(D18&"|"&E18,catClave,0))&"","")) | Z18: =IF(P18="","",WEEKDAY(B18,2)) | AA18: =IF(P18="","",IF(AND(P18="Gasto",X18="Variable",D18<>catTrading,S18>0,S18<=Umbral),1,0)) | AB18: =IF(OR(P18="",Q18=""),"",IFERROR(IF(INDEX(ctaVinc,MATCH(Q18,ctaNombre,0))&""<>"",INDEX(ctaVinc,MATCH(Q18,ctaNombre,0))&"",Q18),Q18)) | AC18: =IF(OR(K18="",AND(P18<>"Transferencia",P18<>"Pago tarjeta")),"",IFERROR(IF(INDEX(ctaVinc,MATCH(K18,ctaNombre,0))&""<>"",INDEX(ctaVinc,MATCH(K18,ctaNombre,0))&"",K18),K18)) | AD18: =IF(AB18="","",IFERROR(INDEX(ctaTipo,MATCH(AB18,ctaNombre,0))&"","")) | AE18: =IF(AC18="","",IFERROR(INDEX(ctaTipo,MATCH(AC18,ctaNombre,0))&"","")) | AF18: =IF(OR(P18="",AB18=""),"",IF(OR(P18="Gasto",P18="Transferencia",P18="Pago tarjeta"),-1,1)*IF(IFERROR(INDEX(ctaMoneda,MATCH(AB18,ctaNombre,0))&"","DOP")="USD",T18,S18)) | AG18: =IF(AC18="","",IF(IFERROR(INDEX(ctaMoneda,MATCH(AC18,ctaNombre,0))&"","DOP")="USD",T18,S18)) | AH18: =IF(P18="","",IF(AND(AD18<>"",COUNTIFS(tcTipo,AD18,tcLiq,"Sí")>0),IF(OR(P18="Gasto",P18="Transferencia",P18="Pago tarjeta"),-1,1)*S18,0)+IF(AND(AE18<>"",COUNTIFS(tcTipo,AE18,tcLiq,"Sí")>0),S18,0)) | AI18: =IF(OR(L18="",P18=""),"",IF(COUNTIFS(L$6:L18,L18,P$6:P18,"?*")=1,MAX(AI$5:AI17)+1,""))
B19: 46240 | C19: Transferencia | D19: Trading y actividades financieras | E19: Depósitos y retiros | F19: DEMO · Depósito a cuenta de trading | G19: 15750 | H19: DOP | I19: 63 | J19: Banco principal | K19: Cuenta de trading | N19: DEMOSTRACIÓN | O19: =IF(AND(B19="",G19="",C19="",D19="",J19=""),"",IF(B19="","⚠ Falta fecha",IF(G19="","⚠ Falta monto",IF(Q19="","⚠ Falta cuenta",IF(ISNA(MATCH(Q19,ctaNombre,0)),"⚠ Cuenta no registrada",IF(AND(OR(P19="Gasto",P19="Reembolso"),D19=""),"⚠ Falta categoría",IF(AND(D19<>"",E19<>"",ISNA(MATCH(D19&"|"&E19,catClave,0))),"⚠ Subcategoría no corresponde",IF(AND(OR(P19="Transferencia",P19="Pago tarjeta"),K19=""),"⚠ Falta cuenta destino",IF(AND(K19<>"",P19<>"Transferencia",P19<>"Pago tarjeta"),"⚠ Destino solo aplica a transferencias",IF(AND(K19<>"",K19=Q19),"⚠ Origen igual a destino",IF(AND(K19<>"",ISNA(MATCH(K19,ctaNombre,0))),"⚠ Destino no registrado",IF(AND(P19="Pago tarjeta",AE19<>"Tarjeta de crédito"),"⚠ El destino debe ser tarjeta de crédito",IF(AND(P19="Gasto",E19="Depósitos y retiros"),"⚠ Usa tipo Transferencia",IF(AND(P19="Resultado trading",AD19<>"Cuenta de trading"),"⚠ Usa una cuenta de trading",IF(AND(G19<=0,P19<>"Ajuste",P19<>"Resultado trading"),"⚠ El monto debe ser positivo","✓"))))))))))))))) | P19: =IF(OR(B19="",G19=""),"",IF(C19="","Gasto",C19)) | Q19: =IF(P19="","",IF(J19<>"",J19,CuentaPred&"")) | R19: =IF(P19="","",IF(ISNUMBER(I19),I19,TasaUSD)) | S19: =IF(P19="","",IF(H19="USD",G19*R19,G19)) | T19: =IF(P19="","",IF(H19="USD",G19,IF(R19>0,G19/R19,0))) | U19: =IF(P19="","",IF(P19="Gasto",S19,IF(P19="Reembolso",-S19,0))) | V19: =IF(P19="","",IF(P19="Ingreso",S19,0)) | W19: =IF(P19="","",IF(P19="Resultado trading",S19,0)) | X19: =IF(OR(P19="Gasto",P19="Reembolso"),IF(M19<>"",M19,IFERROR(INDEX(catClasif,MATCH(D19&"|"&E19,catClave,0))&"","Variable")),"") | Y19: =IF(P19="","",IFERROR(INDEX(catGrupo,MATCH(D19&"|"&E19,catClave,0))&"","")) | Z19: =IF(P19="","",WEEKDAY(B19,2)) | AA19: =IF(P19="","",IF(AND(P19="Gasto",X19="Variable",D19<>catTrading,S19>0,S19<=Umbral),1,0)) | AB19: =IF(OR(P19="",Q19=""),"",IFERROR(IF(INDEX(ctaVinc,MATCH(Q19,ctaNombre,0))&""<>"",INDEX(ctaVinc,MATCH(Q19,ctaNombre,0))&"",Q19),Q19)) | AC19: =IF(OR(K19="",AND(P19<>"Transferencia",P19<>"Pago tarjeta")),"",IFERROR(IF(INDEX(ctaVinc,MATCH(K19,ctaNombre,0))&""<>"",INDEX(ctaVinc,MATCH(K19,ctaNombre,0))&"",K19),K19)) | AD19: =IF(AB19="","",IFERROR(INDEX(ctaTipo,MATCH(AB19,ctaNombre,0))&"","")) | AE19: =IF(AC19="","",IFERROR(INDEX(ctaTipo,MATCH(AC19,ctaNombre,0))&"","")) | AF19: =IF(OR(P19="",AB19=""),"",IF(OR(P19="Gasto",P19="Transferencia",P19="Pago tarjeta"),-1,1)*IF(IFERROR(INDEX(ctaMoneda,MATCH(AB19,ctaNombre,0))&"","DOP")="USD",T19,S19)) | AG19: =IF(AC19="","",IF(IFERROR(INDEX(ctaMoneda,MATCH(AC19,ctaNombre,0))&"","DOP")="USD",T19,S19)) | AH19: =IF(P19="","",IF(AND(AD19<>"",COUNTIFS(tcTipo,AD19,tcLiq,"Sí")>0),IF(OR(P19="Gasto",P19="Transferencia",P19="Pago tarjeta"),-1,1)*S19,0)+IF(AND(AE19<>"",COUNTIFS(tcTipo,AE19,tcLiq,"Sí")>0),S19,0)) | AI19: =IF(OR(L19="",P19=""),"",IF(COUNTIFS(L$6:L19,L19,P$6:P19,"?*")=1,MAX(AI$5:AI18)+1,""))
B20: 46241 | C20: Gasto | D20: Alimentación | E20: Almuerzos laborales | F20: DEMO · Almuerzo laboral | G20: 575 | H20: DOP | J20: Billetera digital | L20: Comedor ejecutivo | N20: DEMOSTRACIÓN | O20: =IF(AND(B20="",G20="",C20="",D20="",J20=""),"",IF(B20="","⚠ Falta fecha",IF(G20="","⚠ Falta monto",IF(Q20="","⚠ Falta cuenta",IF(ISNA(MATCH(Q20,ctaNombre,0)),"⚠ Cuenta no registrada",IF(AND(OR(P20="Gasto",P20="Reembolso"),D20=""),"⚠ Falta categoría",IF(AND(D20<>"",E20<>"",ISNA(MATCH(D20&"|"&E20,catClave,0))),"⚠ Subcategoría no corresponde",IF(AND(OR(P20="Transferencia",P20="Pago tarjeta"),K20=""),"⚠ Falta cuenta destino",IF(AND(K20<>"",P20<>"Transferencia",P20<>"Pago tarjeta"),"⚠ Destino solo aplica a transferencias",IF(AND(K20<>"",K20=Q20),"⚠ Origen igual a destino",IF(AND(K20<>"",ISNA(MATCH(K20,ctaNombre,0))),"⚠ Destino no registrado",IF(AND(P20="Pago tarjeta",AE20<>"Tarjeta de crédito"),"⚠ El destino debe ser tarjeta de crédito",IF(AND(P20="Gasto",E20="Depósitos y retiros"),"⚠ Usa tipo Transferencia",IF(AND(P20="Resultado trading",AD20<>"Cuenta de trading"),"⚠ Usa una cuenta de trading",IF(AND(G20<=0,P20<>"Ajuste",P20<>"Resultado trading"),"⚠ El monto debe ser positivo","✓"))))))))))))))) | P20: =IF(OR(B20="",G20=""),"",IF(C20="","Gasto",C20)) | Q20: =IF(P20="","",IF(J20<>"",J20,CuentaPred&"")) | R20: =IF(P20="","",IF(ISNUMBER(I20),I20,TasaUSD)) | S20: =IF(P20="","",IF(H20="USD",G20*R20,G20)) | T20: =IF(P20="","",IF(H20="USD",G20,IF(R20>0,G20/R20,0))) | U20: =IF(P20="","",IF(P20="Gasto",S20,IF(P20="Reembolso",-S20,0))) | V20: =IF(P20="","",IF(P20="Ingreso",S20,0)) | W20: =IF(P20="","",IF(P20="Resultado trading",S20,0)) | X20: =IF(OR(P20="Gasto",P20="Reembolso"),IF(M20<>"",M20,IFERROR(INDEX(catClasif,MATCH(D20&"|"&E20,catClave,0))&"","Variable")),"") | Y20: =IF(P20="","",IFERROR(INDEX(catGrupo,MATCH(D20&"|"&E20,catClave,0))&"","")) | Z20: =IF(P20="","",WEEKDAY(B20,2)) | AA20: =IF(P20="","",IF(AND(P20="Gasto",X20="Variable",D20<>catTrading,S20>0,S20<=Umbral),1,0)) | AB20: =IF(OR(P20="",Q20=""),"",IFERROR(IF(INDEX(ctaVinc,MATCH(Q20,ctaNombre,0))&""<>"",INDEX(ctaVinc,MATCH(Q20,ctaNombre,0))&"",Q20),Q20)) | AC20: =IF(OR(K20="",AND(P20<>"Transferencia",P20<>"Pago tarjeta")),"",IFERROR(IF(INDEX(ctaVinc,MATCH(K20,ctaNombre,0))&""<>"",INDEX(ctaVinc,MATCH(K20,ctaNombre,0))&"",K20),K20)) | AD20: =IF(AB20="","",IFERROR(INDEX(ctaTipo,MATCH(AB20,ctaNombre,0))&"","")) | AE20: =IF(AC20="","",IFERROR(INDEX(ctaTipo,MATCH(AC20,ctaNombre,0))&"","")) | AF20: =IF(OR(P20="",AB20=""),"",IF(OR(P20="Gasto",P20="Transferencia",P20="Pago tarjeta"),-1,1)*IF(IFERROR(INDEX(ctaMoneda,MATCH(AB20,ctaNombre,0))&"","DOP")="USD",T20,S20)) | AG20: =IF(AC20="","",IF(IFERROR(INDEX(ctaMoneda,MATCH(AC20,ctaNombre,0))&"","DOP")="USD",T20,S20)) | AH20: =IF(P20="","",IF(AND(AD20<>"",COUNTIFS(tcTipo,AD20,tcLiq,"Sí")>0),IF(OR(P20="Gasto",P20="Transferencia",P20="Pago tarjeta"),-1,1)*S20,0)+IF(AND(AE20<>"",COUNTIFS(tcTipo,AE20,tcLiq,"Sí")>0),S20,0)) | AI20: =IF(OR(L20="",P20=""),"",IF(COUNTIFS(L$6:L20,L20,P$6:P20,"?*")=1,MAX(AI$5:AI19)+1,""))
B21: 46241 | C21: Gasto | D21: Alimentación | E21: Bebidas, snacks y otros consumos | F21: DEMO · Jugo y galletas | G21: 130 | H21: DOP | J21: Billetera digital | L21: Colmado del barrio | N21: DEMOSTRACIÓN | O21: =IF(AND(B21="",G21="",C21="",D21="",J21=""),"",IF(B21="","⚠ Falta fecha",IF(G21="","⚠ Falta monto",IF(Q21="","⚠ Falta cuenta",IF(ISNA(MATCH(Q21,ctaNombre,0)),"⚠ Cuenta no registrada",IF(AND(OR(P21="Gasto",P21="Reembolso"),D21=""),"⚠ Falta categoría",IF(AND(D21<>"",E21<>"",ISNA(MATCH(D21&"|"&E21,catClave,0))),"⚠ Subcategoría no corresponde",IF(AND(OR(P21="Transferencia",P21="Pago tarjeta"),K21=""),"⚠ Falta cuenta destino",IF(AND(K21<>"",P21<>"Transferencia",P21<>"Pago tarjeta"),"⚠ Destino solo aplica a transferencias",IF(AND(K21<>"",K21=Q21),"⚠ Origen igual a destino",IF(AND(K21<>"",ISNA(MATCH(K21,ctaNombre,0))),"⚠ Destino no registrado",IF(AND(P21="Pago tarjeta",AE21<>"Tarjeta de crédito"),"⚠ El destino debe ser tarjeta de crédito",IF(AND(P21="Gasto",E21="Depósitos y retiros"),"⚠ Usa tipo Transferencia",IF(AND(P21="Resultado trading",AD21<>"Cuenta de trading"),"⚠ Usa una cuenta de trading",IF(AND(G21<=0,P21<>"Ajuste",P21<>"Resultado trading"),"⚠ El monto debe ser positivo","✓"))))))))))))))) | P21: =IF(OR(B21="",G21=""),"",IF(C21="","Gasto",C21)) | Q21: =IF(P21="","",IF(J21<>"",J21,CuentaPred&"")) | R21: =IF(P21="","",IF(ISNUMBER(I21),I21,TasaUSD)) | S21: =IF(P21="","",IF(H21="USD",G21*R21,G21)) | T21: =IF(P21="","",IF(H21="USD",G21,IF(R21>0,G21/R21,0))) | U21: =IF(P21="","",IF(P21="Gasto",S21,IF(P21="Reembolso",-S21,0))) | V21: =IF(P21="","",IF(P21="Ingreso",S21,0)) | W21: =IF(P21="","",IF(P21="Resultado trading",S21,0)) | X21: =IF(OR(P21="Gasto",P21="Reembolso"),IF(M21<>"",M21,IFERROR(INDEX(catClasif,MATCH(D21&"|"&E21,catClave,0))&"","Variable")),"") | Y21: =IF(P21="","",IFERROR(INDEX(catGrupo,MATCH(D21&"|"&E21,catClave,0))&"","")) | Z21: =IF(P21="","",WEEKDAY(B21,2)) | AA21: =IF(P21="","",IF(AND(P21="Gasto",X21="Variable",D21<>catTrading,S21>0,S21<=Umbral),1,0)) | AB21: =IF(OR(P21="",Q21=""),"",IFERROR(IF(INDEX(ctaVinc,MATCH(Q21,ctaNombre,0))&""<>"",INDEX(ctaVinc,MATCH(Q21,ctaNombre,0))&"",Q21),Q21)) | AC21: =IF(OR(K21="",AND(P21<>"Transferencia",P21<>"Pago tarjeta")),"",IFERROR(IF(INDEX(ctaVinc,MATCH(K21,ctaNombre,0))&""<>"",INDEX(ctaVinc,MATCH(K21,ctaNombre,0))&"",K21),K21)) | AD21: =IF(AB21="","",IFERROR(INDEX(ctaTipo,MATCH(AB21,ctaNombre,0))&"","")) | AE21: =IF(AC21="","",IFERROR(INDEX(ctaTipo,MATCH(AC21,ctaNombre,0))&"","")) | AF21: =IF(OR(P21="",AB21=""),"",IF(OR(P21="Gasto",P21="Transferencia",P21="Pago tarjeta"),-1,1)*IF(IFERROR(INDEX(ctaMoneda,MATCH(AB21,ctaNombre,0))&"","DOP")="USD",T21,S21)) | AG21: =IF(AC21="","",IF(IFERROR(INDEX(ctaMoneda,MATCH(AC21,ctaNombre,0))&"","DOP")="USD",T21,S21)) | AH21: =IF(P21="","",IF(AND(AD21<>"",COUNTIFS(tcTipo,AD21,tcLiq,"Sí")>0),IF(OR(P21="Gasto",P21="Transferencia",P21="Pago tarjeta"),-1,1)*S21,0)+IF(AND(AE21<>"",COUNTIFS(tcTipo,AE21,tcLiq,"Sí")>0),S21,0)) | AI21: =IF(OR(L21="",P21=""),"",IF(COUNTIFS(L$6:L21,L21,P$6:P21,"?*")=1,MAX(AI$5:AI20)+1,""))
B22: 46241 | C22: Gasto | D22: Trading y actividades financieras | E22: Evaluaciones y cuentas de trading | F22: DEMO · Evaluación de cuenta fondeada | G22: 150 | H22: USD | J22: Tarjeta de crédito | L22: Firma de evaluación | N22: DEMOSTRACIÓN | O22: =IF(AND(B22="",G22="",C22="",D22="",J22=""),"",IF(B22="","⚠ Falta fecha",IF(G22="","⚠ Falta monto",IF(Q22="","⚠ Falta cuenta",IF(ISNA(MATCH(Q22,ctaNombre,0)),"⚠ Cuenta no registrada",IF(AND(OR(P22="Gasto",P22="Reembolso"),D22=""),"⚠ Falta categoría",IF(AND(D22<>"",E22<>"",ISNA(MATCH(D22&"|"&E22,catClave,0))),"⚠ Subcategoría no corresponde",IF(AND(OR(P22="Transferencia",P22="Pago tarjeta"),K22=""),"⚠ Falta cuenta destino",IF(AND(K22<>"",P22<>"Transferencia",P22<>"Pago tarjeta"),"⚠ Destino solo aplica a transferencias",IF(AND(K22<>"",K22=Q22),"⚠ Origen igual a destino",IF(AND(K22<>"",ISNA(MATCH(K22,ctaNombre,0))),"⚠ Destino no registrado",IF(AND(P22="Pago tarjeta",AE22<>"Tarjeta de crédito"),"⚠ El destino debe ser tarjeta de crédito",IF(AND(P22="Gasto",E22="Depósitos y retiros"),"⚠ Usa tipo Transferencia",IF(AND(P22="Resultado trading",AD22<>"Cuenta de trading"),"⚠ Usa una cuenta de trading",IF(AND(G22<=0,P22<>"Ajuste",P22<>"Resultado trading"),"⚠ El monto debe ser positivo","✓"))))))))))))))) | P22: =IF(OR(B22="",G22=""),"",IF(C22="","Gasto",C22)) | Q22: =IF(P22="","",IF(J22<>"",J22,CuentaPred&"")) | R22: =IF(P22="","",IF(ISNUMBER(I22),I22,TasaUSD)) | S22: =IF(P22="","",IF(H22="USD",G22*R22,G22)) | T22: =IF(P22="","",IF(H22="USD",G22,IF(R22>0,G22/R22,0))) | U22: =IF(P22="","",IF(P22="Gasto",S22,IF(P22="Reembolso",-S22,0))) | V22: =IF(P22="","",IF(P22="Ingreso",S22,0)) | W22: =IF(P22="","",IF(P22="Resultado trading",S22,0)) | X22: =IF(OR(P22="Gasto",P22="Reembolso"),IF(M22<>"",M22,IFERROR(INDEX(catClasif,MATCH(D22&"|"&E22,catClave,0))&"","Variable")),"") | Y22: =IF(P22="","",IFERROR(INDEX(catGrupo,MATCH(D22&"|"&E22,catClave,0))&"","")) | Z22: =IF(P22="","",WEEKDAY(B22,2)) | AA22: =IF(P22="","",IF(AND(P22="Gasto",X22="Variable",D22<>catTrading,S22>0,S22<=Umbral),1,0)) | AB22: =IF(OR(P22="",Q22=""),"",IFERROR(IF(INDEX(ctaVinc,MATCH(Q22,ctaNombre,0))&""<>"",INDEX(ctaVinc,MATCH(Q22,ctaNombre,0))&"",Q22),Q22)) | AC22: =IF(OR(K22="",AND(P22<>"Transferencia",P22<>"Pago tarjeta")),"",IFERROR(IF(INDEX(ctaVinc,MATCH(K22,ctaNombre,0))&""<>"",INDEX(ctaVinc,MATCH(K22,ctaNombre,0))&"",K22),K22)) | AD22: =IF(AB22="","",IFERROR(INDEX(ctaTipo,MATCH(AB22,ctaNombre,0))&"","")) | AE22: =IF(AC22="","",IFERROR(INDEX(ctaTipo,MATCH(AC22,ctaNombre,0))&"","")) | AF22: =IF(OR(P22="",AB22=""),"",IF(OR(P22="Gasto",P22="Transferencia",P22="Pago tarjeta"),-1,1)*IF(IFERROR(INDEX(ctaMoneda,MATCH(AB22,ctaNombre,0))&"","DOP")="USD",T22,S22)) | AG22: =IF(AC22="","",IF(IFERROR(INDEX(ctaMoneda,MATCH(AC22,ctaNombre,0))&"","DOP")="USD",T22,S22)) | AH22: =IF(P22="","",IF(AND(AD22<>"",COUNTIFS(tcTipo,AD22,tcLiq,"Sí")>0),IF(OR(P22="Gasto",P22="Transferencia",P22="Pago tarjeta"),-1,1)*S22,0)+IF(AND(AE22<>"",COUNTIFS(tcTipo,AE22,tcLiq,"Sí")>0),S22,0)) | AI22: =IF(OR(L22="",P22=""),"",IF(COUNTIFS(L$6:L22,L22,P$6:P22,"?*")=1,MAX(AI$5:AI21)+1,""))
B23: 46242 | C23: Gasto | D23: Alimentación | E23: Restaurantes | F23: DEMO · Almuerzo de fin de semana | G23: 2200 | H23: DOP | J23: Tarjeta de crédito | L23: Restaurante del malecón | N23: DEMOSTRACIÓN | O23: =IF(AND(B23="",G23="",C23="",D23="",J23=""),"",IF(B23="","⚠ Falta fecha",IF(G23="","⚠ Falta monto",IF(Q23="","⚠ Falta cuenta",IF(ISNA(MATCH(Q23,ctaNombre,0)),"⚠ Cuenta no registrada",IF(AND(OR(P23="Gasto",P23="Reembolso"),D23=""),"⚠ Falta categoría",IF(AND(D23<>"",E23<>"",ISNA(MATCH(D23&"|"&E23,catClave,0))),"⚠ Subcategoría no corresponde",IF(AND(OR(P23="Transferencia",P23="Pago tarjeta"),K23=""),"⚠ Falta cuenta destino",IF(AND(K23<>"",P23<>"Transferencia",P23<>"Pago tarjeta"),"⚠ Destino solo aplica a transferencias",IF(AND(K23<>"",K23=Q23),"⚠ Origen igual a destino",IF(AND(K23<>"",ISNA(MATCH(K23,ctaNombre,0))),"⚠ Destino no registrado",IF(AND(P23="Pago tarjeta",AE23<>"Tarjeta de crédito"),"⚠ El destino debe ser tarjeta de crédito",IF(AND(P23="Gasto",E23="Depósitos y retiros"),"⚠ Usa tipo Transferencia",IF(AND(P23="Resultado trading",AD23<>"Cuenta de trading"),"⚠ Usa una cuenta de trading",IF(AND(G23<=0,P23<>"Ajuste",P23<>"Resultado trading"),"⚠ El monto debe ser positivo","✓"))))))))))))))) | P23: =IF(OR(B23="",G23=""),"",IF(C23="","Gasto",C23)) | Q23: =IF(P23="","",IF(J23<>"",J23,CuentaPred&"")) | R23: =IF(P23="","",IF(ISNUMBER(I23),I23,TasaUSD)) | S23: =IF(P23="","",IF(H23="USD",G23*R23,G23)) | T23: =IF(P23="","",IF(H23="USD",G23,IF(R23>0,G23/R23,0))) | U23: =IF(P23="","",IF(P23="Gasto",S23,IF(P23="Reembolso",-S23,0))) | V23: =IF(P23="","",IF(P23="Ingreso",S23,0)) | W23: =IF(P23="","",IF(P23="Resultado trading",S23,0)) | X23: =IF(OR(P23="Gasto",P23="Reembolso"),IF(M23<>"",M23,IFERROR(INDEX(catClasif,MATCH(D23&"|"&E23,catClave,0))&"","Variable")),"") | Y23: =IF(P23="","",IFERROR(INDEX(catGrupo,MATCH(D23&"|"&E23,catClave,0))&"","")) | Z23: =IF(P23="","",WEEKDAY(B23,2)) | AA23: =IF(P23="","",IF(AND(P23="Gasto",X23="Variable",D23<>catTrading,S23>0,S23<=Umbral),1,0)) | AB23: =IF(OR(P23="",Q23=""),"",IFERROR(IF(INDEX(ctaVinc,MATCH(Q23,ctaNombre,0))&""<>"",INDEX(ctaVinc,MATCH(Q23,ctaNombre,0))&"",Q23),Q23)) | AC23: =IF(OR(K23="",AND(P23<>"Transferencia",P23<>"Pago tarjeta")),"",IFERROR(IF(INDEX(ctaVinc,MATCH(K23,ctaNombre,0))&""<>"",INDEX(ctaVinc,MATCH(K23,ctaNombre,0))&"",K23),K23)) | AD23: =IF(AB23="","",IFERROR(INDEX(ctaTipo,MATCH(AB23,ctaNombre,0))&"","")) | AE23: =IF(AC23="","",IFERROR(INDEX(ctaTipo,MATCH(AC23,ctaNombre,0))&"","")) | AF23: =IF(OR(P23="",AB23=""),"",IF(OR(P23="Gasto",P23="Transferencia",P23="Pago tarjeta"),-1,1)*IF(IFERROR(INDEX(ctaMoneda,MATCH(AB23,ctaNombre,0))&"","DOP")="USD",T23,S23)) | AG23: =IF(AC23="","",IF(IFERROR(INDEX(ctaMoneda,MATCH(AC23,ctaNombre,0))&"","DOP")="USD",T23,S23)) | AH23: =IF(P23="","",IF(AND(AD23<>"",COUNTIFS(tcTipo,AD23,tcLiq,"Sí")>0),IF(OR(P23="Gasto",P23="Transferencia",P23="Pago tarjeta"),-1,1)*S23,0)+IF(AND(AE23<>"",COUNTIFS(tcTipo,AE23,tcLiq,"Sí")>0),S23,0)) | AI23: =IF(OR(L23="",P23=""),"",IF(COUNTIFS(L$6:L23,L23,P$6:P23,"?*")=1,MAX(AI$5:AI22)+1,""))
B24: 46242 | C24: Gasto | D24: Salud | E24: Gimnasio y bienestar | F24: DEMO · Mensualidad gimnasio | G24: 2500 | H24: DOP | J24: Tarjeta de crédito | L24: Gimnasio | N24: DEMOSTRACIÓN | O24: =IF(AND(B24="",G24="",C24="",D24="",J24=""),"",IF(B24="","⚠ Falta fecha",IF(G24="","⚠ Falta monto",IF(Q24="","⚠ Falta cuenta",IF(ISNA(MATCH(Q24,ctaNombre,0)),"⚠ Cuenta no registrada",IF(AND(OR(P24="Gasto",P24="Reembolso"),D24=""),"⚠ Falta categoría",IF(AND(D24<>"",E24<>"",ISNA(MATCH(D24&"|"&E24,catClave,0))),"⚠ Subcategoría no corresponde",IF(AND(OR(P24="Transferencia",P24="Pago tarjeta"),K24=""),"⚠ Falta cuenta destino",IF(AND(K24<>"",P24<>"Transferencia",P24<>"Pago tarjeta"),"⚠ Destino solo aplica a transferencias",IF(AND(K24<>"",K24=Q24),"⚠ Origen igual a destino",IF(AND(K24<>"",ISNA(MATCH(K24,ctaNombre,0))),"⚠ Destino no registrado",IF(AND(P24="Pago tarjeta",AE24<>"Tarjeta de crédito"),"⚠ El destino debe ser tarjeta de crédito",IF(AND(P24="Gasto",E24="Depósitos y retiros"),"⚠ Usa tipo Transferencia",IF(AND(P24="Resultado trading",AD24<>"Cuenta de trading"),"⚠ Usa una cuenta de trading",IF(AND(G24<=0,P24<>"Ajuste",P24<>"Resultado trading"),"⚠ El monto debe ser positivo","✓"))))))))))))))) | P24: =IF(OR(B24="",G24=""),"",IF(C24="","Gasto",C24)) | Q24: =IF(P24="","",IF(J24<>"",J24,CuentaPred&"")) | R24: =IF(P24="","",IF(ISNUMBER(I24),I24,TasaUSD)) | S24: =IF(P24="","",IF(H24="USD",G24*R24,G24)) | T24: =IF(P24="","",IF(H24="USD",G24,IF(R24>0,G24/R24,0))) | U24: =IF(P24="","",IF(P24="Gasto",S24,IF(P24="Reembolso",-S24,0))) | V24: =IF(P24="","",IF(P24="Ingreso",S24,0)) | W24: =IF(P24="","",IF(P24="Resultado trading",S24,0)) | X24: =IF(OR(P24="Gasto",P24="Reembolso"),IF(M24<>"",M24,IFERROR(INDEX(catClasif,MATCH(D24&"|"&E24,catClave,0))&"","Variable")),"") | Y24: =IF(P24="","",IFERROR(INDEX(catGrupo,MATCH(D24&"|"&E24,catClave,0))&"","")) | Z24: =IF(P24="","",WEEKDAY(B24,2)) | AA24: =IF(P24="","",IF(AND(P24="Gasto",X24="Variable",D24<>catTrading,S24>0,S24<=Umbral),1,0)) | AB24: =IF(OR(P24="",Q24=""),"",IFERROR(IF(INDEX(ctaVinc,MATCH(Q24,ctaNombre,0))&""<>"",INDEX(ctaVinc,MATCH(Q24,ctaNombre,0))&"",Q24),Q24)) | AC24: =IF(OR(K24="",AND(P24<>"Transferencia",P24<>"Pago tarjeta")),"",IFERROR(IF(INDEX(ctaVinc,MATCH(K24,ctaNombre,0))&""<>"",INDEX(ctaVinc,MATCH(K24,ctaNombre,0))&"",K24),K24)) | AD24: =IF(AB24="","",IFERROR(INDEX(ctaTipo,MATCH(AB24,ctaNombre,0))&"","")) | AE24: =IF(AC24="","",IFERROR(INDEX(ctaTipo,MATCH(AC24,ctaNombre,0))&"","")) | AF24: =IF(OR(P24="",AB24=""),"",IF(OR(P24="Gasto",P24="Transferencia",P24="Pago tarjeta"),-1,1)*IF(IFERROR(INDEX(ctaMoneda,MATCH(AB24,ctaNombre,0))&"","DOP")="USD",T24,S24)) | AG24: =IF(AC24="","",IF(IFERROR(INDEX(ctaMoneda,MATCH(AC24,ctaNombre,0))&"","DOP")="USD",T24,S24)) | AH24: =IF(P24="","",IF(AND(AD24<>"",COUNTIFS(tcTipo,AD24,tcLiq,"Sí")>0),IF(OR(P24="Gasto",P24="Transferencia",P24="Pago tarjeta"),-1,1)*S24,0)+IF(AND(AE24<>"",COUNTIFS(tcTipo,AE24,tcLiq,"Sí")>0),S24,0)) | AI24: =IF(OR(L24="",P24=""),"",IF(COUNTIFS(L$6:L24,L24,P$6:P24,"?*")=1,MAX(AI$5:AI23)+1,""))
B25: 46244 | C25: Gasto | D25: Alimentación | E25: Almuerzos laborales | F25: DEMO · Almuerzo laboral | G25: 575 | H25: DOP | J25: Billetera digital | L25: Comedor ejecutivo | N25: DEMOSTRACIÓN | O25: =IF(AND(B25="",G25="",C25="",D25="",J25=""),"",IF(B25="","⚠ Falta fecha",IF(G25="","⚠ Falta monto",IF(Q25="","⚠ Falta cuenta",IF(ISNA(MATCH(Q25,ctaNombre,0)),"⚠ Cuenta no registrada",IF(AND(OR(P25="Gasto",P25="Reembolso"),D25=""),"⚠ Falta categoría",IF(AND(D25<>"",E25<>"",ISNA(MATCH(D25&"|"&E25,catClave,0))),"⚠ Subcategoría no corresponde",IF(AND(OR(P25="Transferencia",P25="Pago tarjeta"),K25=""),"⚠ Falta cuenta destino",IF(AND(K25<>"",P25<>"Transferencia",P25<>"Pago tarjeta"),"⚠ Destino solo aplica a transferencias",IF(AND(K25<>"",K25=Q25),"⚠ Origen igual a destino",IF(AND(K25<>"",ISNA(MATCH(K25,ctaNombre,0))),"⚠ Destino no registrado",IF(AND(P25="Pago tarjeta",AE25<>"Tarjeta de crédito"),"⚠ El destino debe ser tarjeta de crédito",IF(AND(P25="Gasto",E25="Depósitos y retiros"),"⚠ Usa tipo Transferencia",IF(AND(P25="Resultado trading",AD25<>"Cuenta de trading"),"⚠ Usa una cuenta de trading",IF(AND(G25<=0,P25<>"Ajuste",P25<>"Resultado trading"),"⚠ El monto debe ser positivo","✓"))))))))))))))) | P25: =IF(OR(B25="",G25=""),"",IF(C25="","Gasto",C25)) | Q25: =IF(P25="","",IF(J25<>"",J25,CuentaPred&"")) | R25: =IF(P25="","",IF(ISNUMBER(I25),I25,TasaUSD)) | S25: =IF(P25="","",IF(H25="USD",G25*R25,G25)) | T25: =IF(P25="","",IF(H25="USD",G25,IF(R25>0,G25/R25,0))) | U25: =IF(P25="","",IF(P25="Gasto",S25,IF(P25="Reembolso",-S25,0))) | V25: =IF(P25="","",IF(P25="Ingreso",S25,0)) | W25: =IF(P25="","",IF(P25="Resultado trading",S25,0)) | X25: =IF(OR(P25="Gasto",P25="Reembolso"),IF(M25<>"",M25,IFERROR(INDEX(catClasif,MATCH(D25&"|"&E25,catClave,0))&"","Variable")),"") | Y25: =IF(P25="","",IFERROR(INDEX(catGrupo,MATCH(D25&"|"&E25,catClave,0))&"","")) | Z25: =IF(P25="","",WEEKDAY(B25,2)) | AA25: =IF(P25="","",IF(AND(P25="Gasto",X25="Variable",D25<>catTrading,S25>0,S25<=Umbral),1,0)) | AB25: =IF(OR(P25="",Q25=""),"",IFERROR(IF(INDEX(ctaVinc,MATCH(Q25,ctaNombre,0))&""<>"",INDEX(ctaVinc,MATCH(Q25,ctaNombre,0))&"",Q25),Q25)) | AC25: =IF(OR(K25="",AND(P25<>"Transferencia",P25<>"Pago tarjeta")),"",IFERROR(IF(INDEX(ctaVinc,MATCH(K25,ctaNombre,0))&""<>"",INDEX(ctaVinc,MATCH(K25,ctaNombre,0))&"",K25),K25)) | AD25: =IF(AB25="","",IFERROR(INDEX(ctaTipo,MATCH(AB25,ctaNombre,0))&"","")) | AE25: =IF(AC25="","",IFERROR(INDEX(ctaTipo,MATCH(AC25,ctaNombre,0))&"","")) | AF25: =IF(OR(P25="",AB25=""),"",IF(OR(P25="Gasto",P25="Transferencia",P25="Pago tarjeta"),-1,1)*IF(IFERROR(INDEX(ctaMoneda,MATCH(AB25,ctaNombre,0))&"","DOP")="USD",T25,S25)) | AG25: =IF(AC25="","",IF(IFERROR(INDEX(ctaMoneda,MATCH(AC25,ctaNombre,0))&"","DOP")="USD",T25,S25)) | AH25: =IF(P25="","",IF(AND(AD25<>"",COUNTIFS(tcTipo,AD25,tcLiq,"Sí")>0),IF(OR(P25="Gasto",P25="Transferencia",P25="Pago tarjeta"),-1,1)*S25,0)+IF(AND(AE25<>"",COUNTIFS(tcTipo,AE25,tcLiq,"Sí")>0),S25,0)) | AI25: =IF(OR(L25="",P25=""),"",IF(COUNTIFS(L$6:L25,L25,P$6:P25,"?*")=1,MAX(AI$5:AI24)+1,""))
B26: 46244 | C26: Gasto | D26: Transporte y vehículo | E26: Combustible | F26: DEMO · Combustible | G26: 2350 | H26: DOP | J26: Tarjeta de crédito | L26: Estación de combustible | N26: DEMOSTRACIÓN | O26: =IF(AND(B26="",G26="",C26="",D26="",J26=""),"",IF(B26="","⚠ Falta fecha",IF(G26="","⚠ Falta monto",IF(Q26="","⚠ Falta cuenta",IF(ISNA(MATCH(Q26,ctaNombre,0)),"⚠ Cuenta no registrada",IF(AND(OR(P26="Gasto",P26="Reembolso"),D26=""),"⚠ Falta categoría",IF(AND(D26<>"",E26<>"",ISNA(MATCH(D26&"|"&E26,catClave,0))),"⚠ Subcategoría no corresponde",IF(AND(OR(P26="Transferencia",P26="Pago tarjeta"),K26=""),"⚠ Falta cuenta destino",IF(AND(K26<>"",P26<>"Transferencia",P26<>"Pago tarjeta"),"⚠ Destino solo aplica a transferencias",IF(AND(K26<>"",K26=Q26),"⚠ Origen igual a destino",IF(AND(K26<>"",ISNA(MATCH(K26,ctaNombre,0))),"⚠ Destino no registrado",IF(AND(P26="Pago tarjeta",AE26<>"Tarjeta de crédito"),"⚠ El destino debe ser tarjeta de crédito",IF(AND(P26="Gasto",E26="Depósitos y retiros"),"⚠ Usa tipo Transferencia",IF(AND(P26="Resultado trading",AD26<>"Cuenta de trading"),"⚠ Usa una cuenta de trading",IF(AND(G26<=0,P26<>"Ajuste",P26<>"Resultado trading"),"⚠ El monto debe ser positivo","✓"))))))))))))))) | P26: =IF(OR(B26="",G26=""),"",IF(C26="","Gasto",C26)) | Q26: =IF(P26="","",IF(J26<>"",J26,CuentaPred&"")) | R26: =IF(P26="","",IF(ISNUMBER(I26),I26,TasaUSD)) | S26: =IF(P26="","",IF(H26="USD",G26*R26,G26)) | T26: =IF(P26="","",IF(H26="USD",G26,IF(R26>0,G26/R26,0))) | U26: =IF(P26="","",IF(P26="Gasto",S26,IF(P26="Reembolso",-S26,0))) | V26: =IF(P26="","",IF(P26="Ingreso",S26,0)) | W26: =IF(P26="","",IF(P26="Resultado trading",S26,0)) | X26: =IF(OR(P26="Gasto",P26="Reembolso"),IF(M26<>"",M26,IFERROR(INDEX(catClasif,MATCH(D26&"|"&E26,catClave,0))&"","Variable")),"") | Y26: =IF(P26="","",IFERROR(INDEX(catGrupo,MATCH(D26&"|"&E26,catClave,0))&"","")) | Z26: =IF(P26="","",WEEKDAY(B26,2)) | AA26: =IF(P26="","",IF(AND(P26="Gasto",X26="Variable",D26<>catTrading,S26>0,S26<=Umbral),1,0)) | AB26: =IF(OR(P26="",Q26=""),"",IFERROR(IF(INDEX(ctaVinc,MATCH(Q26,ctaNombre,0))&""<>"",INDEX(ctaVinc,MATCH(Q26,ctaNombre,0))&"",Q26),Q26)) | AC26: =IF(OR(K26="",AND(P26<>"Transferencia",P26<>"Pago tarjeta")),"",IFERROR(IF(INDEX(ctaVinc,MATCH(K26,ctaNombre,0))&""<>"",INDEX(ctaVinc,MATCH(K26,ctaNombre,0))&"",K26),K26)) | AD26: =IF(AB26="","",IFERROR(INDEX(ctaTipo,MATCH(AB26,ctaNombre,0))&"","")) | AE26: =IF(AC26="","",IFERROR(INDEX(ctaTipo,MATCH(AC26,ctaNombre,0))&"","")) | AF26: =IF(OR(P26="",AB26=""),"",IF(OR(P26="Gasto",P26="Transferencia",P26="Pago tarjeta"),-1,1)*IF(IFERROR(INDEX(ctaMoneda,MATCH(AB26,ctaNombre,0))&"","DOP")="USD",T26,S26)) | AG26: =IF(AC26="","",IF(IFERROR(INDEX(ctaMoneda,MATCH(AC26,ctaNombre,0))&"","DOP")="USD",T26,S26)) | AH26: =IF(P26="","",IF(AND(AD26<>"",COUNTIFS(tcTipo,AD26,tcLiq,"Sí")>0),IF(OR(P26="Gasto",P26="Transferencia",P26="Pago tarjeta"),-1,1)*S26,0)+IF(AND(AE26<>"",COUNTIFS(tcTipo,AE26,tcLiq,"Sí")>0),S26,0)) | AI26: =IF(OR(L26="",P26=""),"",IF(COUNTIFS(L$6:L26,L26,P$6:P26,"?*")=1,MAX(AI$5:AI25)+1,""))
B27: 46244 | C27: Gasto | D27: Pareja y actividades sociales | E27: Salidas y citas | F27: DEMO · Salida con pareja | G27: 1900 | H27: DOP | J27: Tarjeta de crédito | L27: Cine y cena | N27: DEMOSTRACIÓN | O27: =IF(AND(B27="",G27="",C27="",D27="",J27=""),"",IF(B27="","⚠ Falta fecha",IF(G27="","⚠ Falta monto",IF(Q27="","⚠ Falta cuenta",IF(ISNA(MATCH(Q27,ctaNombre,0)),"⚠ Cuenta no registrada",IF(AND(OR(P27="Gasto",P27="Reembolso"),D27=""),"⚠ Falta categoría",IF(AND(D27<>"",E27<>"",ISNA(MATCH(D27&"|"&E27,catClave,0))),"⚠ Subcategoría no corresponde",IF(AND(OR(P27="Transferencia",P27="Pago tarjeta"),K27=""),"⚠ Falta cuenta destino",IF(AND(K27<>"",P27<>"Transferencia",P27<>"Pago tarjeta"),"⚠ Destino solo aplica a transferencias",IF(AND(K27<>"",K27=Q27),"⚠ Origen igual a destino",IF(AND(K27<>"",ISNA(MATCH(K27,ctaNombre,0))),"⚠ Destino no registrado",IF(AND(P27="Pago tarjeta",AE27<>"Tarjeta de crédito"),"⚠ El destino debe ser tarjeta de crédito",IF(AND(P27="Gasto",E27="Depósitos y retiros"),"⚠ Usa tipo Transferencia",IF(AND(P27="Resultado trading",AD27<>"Cuenta de trading"),"⚠ Usa una cuenta de trading",IF(AND(G27<=0,P27<>"Ajuste",P27<>"Resultado trading"),"⚠ El monto debe ser positivo","✓"))))))))))))))) | P27: =IF(OR(B27="",G27=""),"",IF(C27="","Gasto",C27)) | Q27: =IF(P27="","",IF(J27<>"",J27,CuentaPred&"")) | R27: =IF(P27="","",IF(ISNUMBER(I27),I27,TasaUSD)) | S27: =IF(P27="","",IF(H27="USD",G27*R27,G27)) | T27: =IF(P27="","",IF(H27="USD",G27,IF(R27>0,G27/R27,0))) | U27: =IF(P27="","",IF(P27="Gasto",S27,IF(P27="Reembolso",-S27,0))) | V27: =IF(P27="","",IF(P27="Ingreso",S27,0)) | W27: =IF(P27="","",IF(P27="Resultado trading",S27,0)) | X27: =IF(OR(P27="Gasto",P27="Reembolso"),IF(M27<>"",M27,IFERROR(INDEX(catClasif,MATCH(D27&"|"&E27,catClave,0))&"","Variable")),"") | Y27: =IF(P27="","",IFERROR(INDEX(catGrupo,MATCH(D27&"|"&E27,catClave,0))&"","")) | Z27: =IF(P27="","",WEEKDAY(B27,2)) | AA27: =IF(P27="","",IF(AND(P27="Gasto",X27="Variable",D27<>catTrading,S27>0,S27<=Umbral),1,0)) | AB27: =IF(OR(P27="",Q27=""),"",IFERROR(IF(INDEX(ctaVinc,MATCH(Q27,ctaNombre,0))&""<>"",INDEX(ctaVinc,MATCH(Q27,ctaNombre,0))&"",Q27),Q27)) | AC27: =IF(OR(K27="",AND(P27<>"Transferencia",P27<>"Pago tarjeta")),"",IFERROR(IF(INDEX(ctaVinc,MATCH(K27,ctaNombre,0))&""<>"",INDEX(ctaVinc,MATCH(K27,ctaNombre,0))&"",K27),K27)) | AD27: =IF(AB27="","",IFERROR(INDEX(ctaTipo,MATCH(AB27,ctaNombre,0))&"","")) | AE27: =IF(AC27="","",IFERROR(INDEX(ctaTipo,MATCH(AC27,ctaNombre,0))&"","")) | AF27: =IF(OR(P27="",AB27=""),"",IF(OR(P27="Gasto",P27="Transferencia",P27="Pago tarjeta"),-1,1)*IF(IFERROR(INDEX(ctaMoneda,MATCH(AB27,ctaNombre,0))&"","DOP")="USD",T27,S27)) | AG27: =IF(AC27="","",IF(IFERROR(INDEX(ctaMoneda,MATCH(AC27,ctaNombre,0))&"","DOP")="USD",T27,S27)) | AH27: =IF(P27="","",IF(AND(AD27<>"",COUNTIFS(tcTipo,AD27,tcLiq,"Sí")>0),IF(OR(P27="Gasto",P27="Transferencia",P27="Pago tarjeta"),-1,1)*S27,0)+IF(AND(AE27<>"",COUNTIFS(tcTipo,AE27,tcLiq,"Sí")>0),S27,0)) | AI27: =IF(OR(L27="",P27=""),"",IF(COUNTIFS(L$6:L27,L27,P$6:P27,"?*")=1,MAX(AI$5:AI26)+1,""))
B28: 46245 | C28: Gasto | D28: Alimentación | E28: Almuerzos laborales | F28: DEMO · Almuerzo laboral | G28: 525 | H28: DOP | J28: Tarjeta de débito | L28: Comedor ejecutivo | N28: DEMOSTRACIÓN | O28: =IF(AND(B28="",G28="",C28="",D28="",J28=""),"",IF(B28="","⚠ Falta fecha",IF(G28="","⚠ Falta monto",IF(Q28="","⚠ Falta cuenta",IF(ISNA(MATCH(Q28,ctaNombre,0)),"⚠ Cuenta no registrada",IF(AND(OR(P28="Gasto",P28="Reembolso"),D28=""),"⚠ Falta categoría",IF(AND(D28<>"",E28<>"",ISNA(MATCH(D28&"|"&E28,catClave,0))),"⚠ Subcategoría no corresponde",IF(AND(OR(P28="Transferencia",P28="Pago tarjeta"),K28=""),"⚠ Falta cuenta destino",IF(AND(K28<>"",P28<>"Transferencia",P28<>"Pago tarjeta"),"⚠ Destino solo aplica a transferencias",IF(AND(K28<>"",K28=Q28),"⚠ Origen igual a destino",IF(AND(K28<>"",ISNA(MATCH(K28,ctaNombre,0))),"⚠ Destino no registrado",IF(AND(P28="Pago tarjeta",AE28<>"Tarjeta de crédito"),"⚠ El destino debe ser tarjeta de crédito",IF(AND(P28="Gasto",E28="Depósitos y retiros"),"⚠ Usa tipo Transferencia",IF(AND(P28="Resultado trading",AD28<>"Cuenta de trading"),"⚠ Usa una cuenta de trading",IF(AND(G28<=0,P28<>"Ajuste",P28<>"Resultado trading"),"⚠ El monto debe ser positivo","✓"))))))))))))))) | P28: =IF(OR(B28="",G28=""),"",IF(C28="","Gasto",C28)) | Q28: =IF(P28="","",IF(J28<>"",J28,CuentaPred&"")) | R28: =IF(P28="","",IF(ISNUMBER(I28),I28,TasaUSD)) | S28: =IF(P28="","",IF(H28="USD",G28*R28,G28)) | T28: =IF(P28="","",IF(H28="USD",G28,IF(R28>0,G28/R28,0))) | U28: =IF(P28="","",IF(P28="Gasto",S28,IF(P28="Reembolso",-S28,0))) | V28: =IF(P28="","",IF(P28="Ingreso",S28,0)) | W28: =IF(P28="","",IF(P28="Resultado trading",S28,0)) | X28: =IF(OR(P28="Gasto",P28="Reembolso"),IF(M28<>"",M28,IFERROR(INDEX(catClasif,MATCH(D28&"|"&E28,catClave,0))&"","Variable")),"") | Y28: =IF(P28="","",IFERROR(INDEX(catGrupo,MATCH(D28&"|"&E28,catClave,0))&"","")) | Z28: =IF(P28="","",WEEKDAY(B28,2)) | AA28: =IF(P28="","",IF(AND(P28="Gasto",X28="Variable",D28<>catTrading,S28>0,S28<=Umbral),1,0)) | AB28: =IF(OR(P28="",Q28=""),"",IFERROR(IF(INDEX(ctaVinc,MATCH(Q28,ctaNombre,0))&""<>"",INDEX(ctaVinc,MATCH(Q28,ctaNombre,0))&"",Q28),Q28)) | AC28: =IF(OR(K28="",AND(P28<>"Transferencia",P28<>"Pago tarjeta")),"",IFERROR(IF(INDEX(ctaVinc,MATCH(K28,ctaNombre,0))&""<>"",INDEX(ctaVinc,MATCH(K28,ctaNombre,0))&"",K28),K28)) | AD28: =IF(AB28="","",IFERROR(INDEX(ctaTipo,MATCH(AB28,ctaNombre,0))&"","")) | AE28: =IF(AC28="","",IFERROR(INDEX(ctaTipo,MATCH(AC28,ctaNombre,0))&"","")) | AF28: =IF(OR(P28="",AB28=""),"",IF(OR(P28="Gasto",P28="Transferencia",P28="Pago tarjeta"),-1,1)*IF(IFERROR(INDEX(ctaMoneda,MATCH(AB28,ctaNombre,0))&"","DOP")="USD",T28,S28)) | AG28: =IF(AC28="","",IF(IFERROR(INDEX(ctaMoneda,MATCH(AC28,ctaNombre,0))&"","DOP")="USD",T28,S28)) | AH28: =IF(P28="","",IF(AND(AD28<>"",COUNTIFS(tcTipo,AD28,tcLiq,"Sí")>0),IF(OR(P28="Gasto",P28="Transferencia",P28="Pago tarjeta"),-1,1)*S28,0)+IF(AND(AE28<>"",COUNTIFS(tcTipo,AE28,tcLiq,"Sí")>0),S28,0)) | AI28: =IF(OR(L28="",P28=""),"",IF(COUNTIFS(L$6:L28,L28,P$6:P28,"?*")=1,MAX(AI$5:AI27)+1,""))
B29: 46246 | C29: Gasto | D29: Alimentación | E29: Almuerzos laborales | F29: DEMO · Almuerzo laboral | G29: 450 | H29: DOP | J29: Tarjeta de débito | L29: Comedor ejecutivo | N29: DEMOSTRACIÓN | O29: =IF(AND(B29="",G29="",C29="",D29="",J29=""),"",IF(B29="","⚠ Falta fecha",IF(G29="","⚠ Falta monto",IF(Q29="","⚠ Falta cuenta",IF(ISNA(MATCH(Q29,ctaNombre,0)),"⚠ Cuenta no registrada",IF(AND(OR(P29="Gasto",P29="Reembolso"),D29=""),"⚠ Falta categoría",IF(AND(D29<>"",E29<>"",ISNA(MATCH(D29&"|"&E29,catClave,0))),"⚠ Subcategoría no corresponde",IF(AND(OR(P29="Transferencia",P29="Pago tarjeta"),K29=""),"⚠ Falta cuenta destino",IF(AND(K29<>"",P29<>"Transferencia",P29<>"Pago tarjeta"),"⚠ Destino solo aplica a transferencias",IF(AND(K29<>"",K29=Q29),"⚠ Origen igual a destino",IF(AND(K29<>"",ISNA(MATCH(K29,ctaNombre,0))),"⚠ Destino no registrado",IF(AND(P29="Pago tarjeta",AE29<>"Tarjeta de crédito"),"⚠ El destino debe ser tarjeta de crédito",IF(AND(P29="Gasto",E29="Depósitos y retiros"),"⚠ Usa tipo Transferencia",IF(AND(P29="Resultado trading",AD29<>"Cuenta de trading"),"⚠ Usa una cuenta de trading",IF(AND(G29<=0,P29<>"Ajuste",P29<>"Resultado trading"),"⚠ El monto debe ser positivo","✓"))))))))))))))) | P29: =IF(OR(B29="",G29=""),"",IF(C29="","Gasto",C29)) | Q29: =IF(P29="","",IF(J29<>"",J29,CuentaPred&"")) | R29: =IF(P29="","",IF(ISNUMBER(I29),I29,TasaUSD)) | S29: =IF(P29="","",IF(H29="USD",G29*R29,G29)) | T29: =IF(P29="","",IF(H29="USD",G29,IF(R29>0,G29/R29,0))) | U29: =IF(P29="","",IF(P29="Gasto",S29,IF(P29="Reembolso",-S29,0))) | V29: =IF(P29="","",IF(P29="Ingreso",S29,0)) | W29: =IF(P29="","",IF(P29="Resultado trading",S29,0)) | X29: =IF(OR(P29="Gasto",P29="Reembolso"),IF(M29<>"",M29,IFERROR(INDEX(catClasif,MATCH(D29&"|"&E29,catClave,0))&"","Variable")),"") | Y29: =IF(P29="","",IFERROR(INDEX(catGrupo,MATCH(D29&"|"&E29,catClave,0))&"","")) | Z29: =IF(P29="","",WEEKDAY(B29,2)) | AA29: =IF(P29="","",IF(AND(P29="Gasto",X29="Variable",D29<>catTrading,S29>0,S29<=Umbral),1,0)) | AB29: =IF(OR(P29="",Q29=""),"",IFERROR(IF(INDEX(ctaVinc,MATCH(Q29,ctaNombre,0))&""<>"",INDEX(ctaVinc,MATCH(Q29,ctaNombre,0))&"",Q29),Q29)) | AC29: =IF(OR(K29="",AND(P29<>"Transferencia",P29<>"Pago tarjeta")),"",IFERROR(IF(INDEX(ctaVinc,MATCH(K29,ctaNombre,0))&""<>"",INDEX(ctaVinc,MATCH(K29,ctaNombre,0))&"",K29),K29)) | AD29: =IF(AB29="","",IFERROR(INDEX(ctaTipo,MATCH(AB29,ctaNombre,0))&"","")) | AE29: =IF(AC29="","",IFERROR(INDEX(ctaTipo,MATCH(AC29,ctaNombre,0))&"","")) | AF29: =IF(OR(P29="",AB29=""),"",IF(OR(P29="Gasto",P29="Transferencia",P29="Pago tarjeta"),-1,1)*IF(IFERROR(INDEX(ctaMoneda,MATCH(AB29,ctaNombre,0))&"","DOP")="USD",T29,S29)) | AG29: =IF(AC29="","",IF(IFERROR(INDEX(ctaMoneda,MATCH(AC29,ctaNombre,0))&"","DOP")="USD",T29,S29)) | AH29: =IF(P29="","",IF(AND(AD29<>"",COUNTIFS(tcTipo,AD29,tcLiq,"Sí")>0),IF(OR(P29="Gasto",P29="Transferencia",P29="Pago tarjeta"),-1,1)*S29,0)+IF(AND(AE29<>"",COUNTIFS(tcTipo,AE29,tcLiq,"Sí")>0),S29,0)) | AI29: =IF(OR(L29="",P29=""),"",IF(COUNTIFS(L$6:L29,L29,P$6:P29,"?*")=1,MAX(AI$5:AI28)+1,""))
B30: 46246 | C30: Gasto | D30: Alimentación | E30: Supermercado | F30: DEMO · Compra de supermercado | G30: 6250 | H30: DOP | J30: Tarjeta de crédito | L30: Supermercado principal | N30: DEMOSTRACIÓN | O30: =IF(AND(B30="",G30="",C30="",D30="",J30=""),"",IF(B30="","⚠ Falta fecha",IF(G30="","⚠ Falta monto",IF(Q30="","⚠ Falta cuenta",IF(ISNA(MATCH(Q30,ctaNombre,0)),"⚠ Cuenta no registrada",IF(AND(OR(P30="Gasto",P30="Reembolso"),D30=""),"⚠ Falta categoría",IF(AND(D30<>"",E30<>"",ISNA(MATCH(D30&"|"&E30,catClave,0))),"⚠ Subcategoría no corresponde",IF(AND(OR(P30="Transferencia",P30="Pago tarjeta"),K30=""),"⚠ Falta cuenta destino",IF(AND(K30<>"",P30<>"Transferencia",P30<>"Pago tarjeta"),"⚠ Destino solo aplica a transferencias",IF(AND(K30<>"",K30=Q30),"⚠ Origen igual a destino",IF(AND(K30<>"",ISNA(MATCH(K30,ctaNombre,0))),"⚠ Destino no registrado",IF(AND(P30="Pago tarjeta",AE30<>"Tarjeta de crédito"),"⚠ El destino debe ser tarjeta de crédito",IF(AND(P30="Gasto",E30="Depósitos y retiros"),"⚠ Usa tipo Transferencia",IF(AND(P30="Resultado trading",AD30<>"Cuenta de trading"),"⚠ Usa una cuenta de trading",IF(AND(G30<=0,P30<>"Ajuste",P30<>"Resultado trading"),"⚠ El monto debe ser positivo","✓"))))))))))))))) | P30: =IF(OR(B30="",G30=""),"",IF(C30="","Gasto",C30)) | Q30: =IF(P30="","",IF(J30<>"",J30,CuentaPred&"")) | R30: =IF(P30="","",IF(ISNUMBER(I30),I30,TasaUSD)) | S30: =IF(P30="","",IF(H30="USD",G30*R30,G30)) | T30: =IF(P30="","",IF(H30="USD",G30,IF(R30>0,G30/R30,0))) | U30: =IF(P30="","",IF(P30="Gasto",S30,IF(P30="Reembolso",-S30,0))) | V30: =IF(P30="","",IF(P30="Ingreso",S30,0)) | W30: =IF(P30="","",IF(P30="Resultado trading",S30,0)) | X30: =IF(OR(P30="Gasto",P30="Reembolso"),IF(M30<>"",M30,IFERROR(INDEX(catClasif,MATCH(D30&"|"&E30,catClave,0))&"","Variable")),"") | Y30: =IF(P30="","",IFERROR(INDEX(catGrupo,MATCH(D30&"|"&E30,catClave,0))&"","")) | Z30: =IF(P30="","",WEEKDAY(B30,2)) | AA30: =IF(P30="","",IF(AND(P30="Gasto",X30="Variable",D30<>catTrading,S30>0,S30<=Umbral),1,0)) | AB30: =IF(OR(P30="",Q30=""),"",IFERROR(IF(INDEX(ctaVinc,MATCH(Q30,ctaNombre,0))&""<>"",INDEX(ctaVinc,MATCH(Q30,ctaNombre,0))&"",Q30),Q30)) | AC30: =IF(OR(K30="",AND(P30<>"Transferencia",P30<>"Pago tarjeta")),"",IFERROR(IF(INDEX(ctaVinc,MATCH(K30,ctaNombre,0))&""<>"",INDEX(ctaVinc,MATCH(K30,ctaNombre,0))&"",K30),K30)) | AD30: =IF(AB30="","",IFERROR(INDEX(ctaTipo,MATCH(AB30,ctaNombre,0))&"","")) | AE30: =IF(AC30="","",IFERROR(INDEX(ctaTipo,MATCH(AC30,ctaNombre,0))&"","")) | AF30: =IF(OR(P30="",AB30=""),"",IF(OR(P30="Gasto",P30="Transferencia",P30="Pago tarjeta"),-1,1)*IF(IFERROR(INDEX(ctaMoneda,MATCH(AB30,ctaNombre,0))&"","DOP")="USD",T30,S30)) | AG30: =IF(AC30="","",IF(IFERROR(INDEX(ctaMoneda,MATCH(AC30,ctaNombre,0))&"","DOP")="USD",T30,S30)) | AH30: =IF(P30="","",IF(AND(AD30<>"",COUNTIFS(tcTipo,AD30,tcLiq,"Sí")>0),IF(OR(P30="Gasto",P30="Transferencia",P30="Pago tarjeta"),-1,1)*S30,0)+IF(AND(AE30<>"",COUNTIFS(tcTipo,AE30,tcLiq,"Sí")>0),S30,0)) | AI30: =IF(OR(L30="",P30=""),"",IF(COUNTIFS(L$6:L30,L30,P$6:P30,"?*")=1,MAX(AI$5:AI29)+1,""))
B31: 46246 | C31: Gasto | D31: Hogar y servicios | E31: Electricidad | F31: DEMO · Factura de luz | G31: 3170 | H31: DOP | J31: Banco principal | L31: Empresa eléctrica | N31: DEMOSTRACIÓN | O31: =IF(AND(B31="",G31="",C31="",D31="",J31=""),"",IF(B31="","⚠ Falta fecha",IF(G31="","⚠ Falta monto",IF(Q31="","⚠ Falta cuenta",IF(ISNA(MATCH(Q31,ctaNombre,0)),"⚠ Cuenta no registrada",IF(AND(OR(P31="Gasto",P31="Reembolso"),D31=""),"⚠ Falta categoría",IF(AND(D31<>"",E31<>"",ISNA(MATCH(D31&"|"&E31,catClave,0))),"⚠ Subcategoría no corresponde",IF(AND(OR(P31="Transferencia",P31="Pago tarjeta"),K31=""),"⚠ Falta cuenta destino",IF(AND(K31<>"",P31<>"Transferencia",P31<>"Pago tarjeta"),"⚠ Destino solo aplica a transferencias",IF(AND(K31<>"",K31=Q31),"⚠ Origen igual a destino",IF(AND(K31<>"",ISNA(MATCH(K31,ctaNombre,0))),"⚠ Destino no registrado",IF(AND(P31="Pago tarjeta",AE31<>"Tarjeta de crédito"),"⚠ El destino debe ser tarjeta de crédito",IF(AND(P31="Gasto",E31="Depósitos y retiros"),"⚠ Usa tipo Transferencia",IF(AND(P31="Resultado trading",AD31<>"Cuenta de trading"),"⚠ Usa una cuenta de trading",IF(AND(G31<=0,P31<>"Ajuste",P31<>"Resultado trading"),"⚠ El monto debe ser positivo","✓"))))))))))))))) | P31: =IF(OR(B31="",G31=""),"",IF(C31="","Gasto",C31)) | Q31: =IF(P31="","",IF(J31<>"",J31,CuentaPred&"")) | R31: =IF(P31="","",IF(ISNUMBER(I31),I31,TasaUSD)) | S31: =IF(P31="","",IF(H31="USD",G31*R31,G31)) | T31: =IF(P31="","",IF(H31="USD",G31,IF(R31>0,G31/R31,0))) | U31: =IF(P31="","",IF(P31="Gasto",S31,IF(P31="Reembolso",-S31,0))) | V31: =IF(P31="","",IF(P31="Ingreso",S31,0)) | W31: =IF(P31="","",IF(P31="Resultado trading",S31,0)) | X31: =IF(OR(P31="Gasto",P31="Reembolso"),IF(M31<>"",M31,IFERROR(INDEX(catClasif,MATCH(D31&"|"&E31,catClave,0))&"","Variable")),"") | Y31: =IF(P31="","",IFERROR(INDEX(catGrupo,MATCH(D31&"|"&E31,catClave,0))&"","")) | Z31: =IF(P31="","",WEEKDAY(B31,2)) | AA31: =IF(P31="","",IF(AND(P31="Gasto",X31="Variable",D31<>catTrading,S31>0,S31<=Umbral),1,0)) | AB31: =IF(OR(P31="",Q31=""),"",IFERROR(IF(INDEX(ctaVinc,MATCH(Q31,ctaNombre,0))&""<>"",INDEX(ctaVinc,MATCH(Q31,ctaNombre,0))&"",Q31),Q31)) | AC31: =IF(OR(K31="",AND(P31<>"Transferencia",P31<>"Pago tarjeta")),"",IFERROR(IF(INDEX(ctaVinc,MATCH(K31,ctaNombre,0))&""<>"",INDEX(ctaVinc,MATCH(K31,ctaNombre,0))&"",K31),K31)) | AD31: =IF(AB31="","",IFERROR(INDEX(ctaTipo,MATCH(AB31,ctaNombre,0))&"","")) | AE31: =IF(AC31="","",IFERROR(INDEX(ctaTipo,MATCH(AC31,ctaNombre,0))&"","")) | AF31: =IF(OR(P31="",AB31=""),"",IF(OR(P31="Gasto",P31="Transferencia",P31="Pago tarjeta"),-1,1)*IF(IFERROR(INDEX(ctaMoneda,MATCH(AB31,ctaNombre,0))&"","DOP")="USD",T31,S31)) | AG31: =IF(AC31="","",IF(IFERROR(INDEX(ctaMoneda,MATCH(AC31,ctaNombre,0))&"","DOP")="USD",T31,S31)) | AH31: =IF(P31="","",IF(AND(AD31<>"",COUNTIFS(tcTipo,AD31,tcLiq,"Sí")>0),IF(OR(P31="Gasto",P31="Transferencia",P31="Pago tarjeta"),-1,1)*S31,0)+IF(AND(AE31<>"",COUNTIFS(tcTipo,AE31,tcLiq,"Sí")>0),S31,0)) | AI31: =IF(OR(L31="",P31=""),"",IF(COUNTIFS(L$6:L31,L31,P$6:P31,"?*")=1,MAX(AI$5:AI30)+1,""))
... B37: 46248 | C37: Gasto | D37: Compras personales | E37: Ropa y calzado | F37: DEMO · Camisa y pantalón | G37: 3200 | H37: DOP | J37: Tarjeta de crédito | L37: Tienda de ropa | N37: DEMOSTRACIÓN | O37: =IF(AND(B37="",G37="",C37="",D37="",J37=""),"",IF(B37="","⚠ Falta fecha",IF(G37="","⚠ Falta monto",IF(Q37="","⚠ Falta cuenta",IF(ISNA(MATCH(Q37,ctaNombre,0)),"⚠ Cuenta no registrada",IF(AND(OR(P37="Gasto",P37="Reembolso"),D37=""),"⚠ Falta categoría",IF(AND(D37<>"",E37<>"",ISNA(MATCH(D37&"|"&E37,catClave,0))),"⚠ Subcategoría no corresponde",IF(AND(OR(P37="Transferencia",P37="Pago tarjeta"),K37=""),"⚠ Falta cuenta destino",IF(AND(K37<>"",P37<>"Transferencia",P37<>"Pago tarjeta"),"⚠ Destino solo aplica a transferencias",IF(AND(K37<>"",K37=Q37),"⚠ Origen igual a destino",IF(AND(K37<>"",ISNA(MATCH(K37,ctaNombre,0))),"⚠ Destino no registrado",IF(AND(P37="Pago tarjeta",AE37<>"Tarjeta de crédito"),"⚠ El destino debe ser tarjeta de crédito",IF(AND(P37="Gasto",E37="Depósitos y retiros"),"⚠ Usa tipo Transferencia",IF(AND(P37="Resultado trading",AD37<>"Cuenta de trading"),"⚠ Usa una cuenta de trading",IF(AND(G37<=0,P37<>"Ajuste",P37<>"Resultado trading"),"⚠ El monto debe ser positivo","✓"))))))))))))))) | P37: =IF(OR(B37="",G37=""),"",IF(C37="","Gasto",C37)) | Q37: =IF(P37="","",IF(J37<>"",J37,CuentaPred&"")) | R37: =IF(P37="","",IF(ISNUMBER(I37),I37,TasaUSD)) | S37: =IF(P37="","",IF(H37="USD",G37*R37,G37)) | T37: =IF(P37="","",IF(H37="USD",G37,IF(R37>0,G37/R37,0))) | U37: =IF(P37="","",IF(P37="Gasto",S37,IF(P37="Reembolso",-S37,0))) | V37: =IF(P37="","",IF(P37="Ingreso",S37,0)) | W37: =IF(P37="","",IF(P37="Resultado trading",S37,0)) | X37: =IF(OR(P37="Gasto",P37="Reembolso"),IF(M37<>"",M37,IFERROR(INDEX(catClasif,MATCH(D37&"|"&E37,catClave,0))&"","Variable")),"") | Y37: =IF(P37="","",IFERROR(INDEX(catGrupo,MATCH(D37&"|"&E37,catClave,0))&"","")) | Z37: =IF(P37="","",WEEKDAY(B37,2)) | AA37: =IF(P37="","",IF(AND(P37="Gasto",X37="Variable",D37<>catTrading,S37>0,S37<=Umbral),1,0)) | AB37: =IF(OR(P37="",Q37=""),"",IFERROR(IF(INDEX(ctaVinc,MATCH(Q37,ctaNombre,0))&""<>"",INDEX(ctaVinc,MATCH(Q37,ctaNombre,0))&"",Q37),Q37)) | AC37: =IF(OR(K37="",AND(P37<>"Transferencia",P37<>"Pago tarjeta")),"",IFERROR(IF(INDEX(ctaVinc,MATCH(K37,ctaNombre,0))&""<>"",INDEX(ctaVinc,MATCH(K37,ctaNombre,0))&"",K37),K37)) | AD37: =IF(AB37="","",IFERROR(INDEX(ctaTipo,MATCH(AB37,ctaNombre,0))&"","")) | AE37: =IF(AC37="","",IFERROR(INDEX(ctaTipo,MATCH(AC37,ctaNombre,0))&"","")) | AF37: =IF(OR(P37="",AB37=""),"",IF(OR(P37="Gasto",P37="Transferencia",P37="Pago tarjeta"),-1,1)*IF(IFERROR(INDEX(ctaMoneda,MATCH(AB37,ctaNombre,0))&"","DOP")="USD",T37,S37)) | AG37: =IF(AC37="","",IF(IFERROR(INDEX(ctaMoneda,MATCH(AC37,ctaNombre,0))&"","DOP")="USD",T37,S37)) | AH37: =IF(P37="","",IF(AND(AD37<>"",COUNTIFS(tcTipo,AD37,tcLiq,"Sí")>0),IF(OR(P37="Gasto",P37="Transferencia",P37="Pago tarjeta"),-1,1)*S37,0)+IF(AND(AE37<>"",COUNTIFS(tcTipo,AE37,tcLiq,"Sí")>0),S37,0)) | AI37: =IF(OR(L37="",P37=""),"",IF(COUNTIFS(L$6:L37,L37,P$6:P37,"?*")=1,MAX(AI$5:AI36)+1,""))
B38: 46249 | C38: Ingreso | D38: Ingresos | E38: Salario | F38: DEMO · Salario quincenal (ficticio) | G38: 55000 | H38: DOP | J38: Banco principal | N38: DEMOSTRACIÓN | O38: =IF(AND(B38="",G38="",C38="",D38="",J38=""),"",IF(B38="","⚠ Falta fecha",IF(G38="","⚠ Falta monto",IF(Q38="","⚠ Falta cuenta",IF(ISNA(MATCH(Q38,ctaNombre,0)),"⚠ Cuenta no registrada",IF(AND(OR(P38="Gasto",P38="Reembolso"),D38=""),"⚠ Falta categoría",IF(AND(D38<>"",E38<>"",ISNA(MATCH(D38&"|"&E38,catClave,0))),"⚠ Subcategoría no corresponde",IF(AND(OR(P38="Transferencia",P38="Pago tarjeta"),K38=""),"⚠ Falta cuenta destino",IF(AND(K38<>"",P38<>"Transferencia",P38<>"Pago tarjeta"),"⚠ Destino solo aplica a transferencias",IF(AND(K38<>"",K38=Q38),"⚠ Origen igual a destino",IF(AND(K38<>"",ISNA(MATCH(K38,ctaNombre,0))),"⚠ Destino no registrado",IF(AND(P38="Pago tarjeta",AE38<>"Tarjeta de crédito"),"⚠ El destino debe ser tarjeta de crédito",IF(AND(P38="Gasto",E38="Depósitos y retiros"),"⚠ Usa tipo Transferencia",IF(AND(P38="Resultado trading",AD38<>"Cuenta de trading"),"⚠ Usa una cuenta de trading",IF(AND(G38<=0,P38<>"Ajuste",P38<>"Resultado trading"),"⚠ El monto debe ser positivo","✓"))))))))))))))) | P38: =IF(OR(B38="",G38=""),"",IF(C38="","Gasto",C38)) | Q38: =IF(P38="","",IF(J38<>"",J38,CuentaPred&"")) | R38: =IF(P38="","",IF(ISNUMBER(I38),I38,TasaUSD)) | S38: =IF(P38="","",IF(H38="USD",G38*R38,G38)) | T38: =IF(P38="","",IF(H38="USD",G38,IF(R38>0,G38/R38,0))) | U38: =IF(P38="","",IF(P38="Gasto",S38,IF(P38="Reembolso",-S38,0))) | V38: =IF(P38="","",IF(P38="Ingreso",S38,0)) | W38: =IF(P38="","",IF(P38="Resultado trading",S38,0)) | X38: =IF(OR(P38="Gasto",P38="Reembolso"),IF(M38<>"",M38,IFERROR(INDEX(catClasif,MATCH(D38&"|"&E38,catClave,0))&"","Variable")),"") | Y38: =IF(P38="","",IFERROR(INDEX(catGrupo,MATCH(D38&"|"&E38,catClave,0))&"","")) | Z38: =IF(P38="","",WEEKDAY(B38,2)) | AA38: =IF(P38="","",IF(AND(P38="Gasto",X38="Variable",D38<>catTrading,S38>0,S38<=Umbral),1,0)) | AB38: =IF(OR(P38="",Q38=""),"",IFERROR(IF(INDEX(ctaVinc,MATCH(Q38,ctaNombre,0))&""<>"",INDEX(ctaVinc,MATCH(Q38,ctaNombre,0))&"",Q38),Q38)) | AC38: =IF(OR(K38="",AND(P38<>"Transferencia",P38<>"Pago tarjeta")),"",IFERROR(IF(INDEX(ctaVinc,MATCH(K38,ctaNombre,0))&""<>"",INDEX(ctaVinc,MATCH(K38,ctaNombre,0))&"",K38),K38)) | AD38: =IF(AB38="","",IFERROR(INDEX(ctaTipo,MATCH(AB38,ctaNombre,0))&"","")) | AE38: =IF(AC38="","",IFERROR(INDEX(ctaTipo,MATCH(AC38,ctaNombre,0))&"","")) | AF38: =IF(OR(P38="",AB38=""),"",IF(OR(P38="Gasto",P38="Transferencia",P38="Pago tarjeta"),-1,1)*IF(IFERROR(INDEX(ctaMoneda,MATCH(AB38,ctaNombre,0))&"","DOP")="USD",T38,S38)) | AG38: =IF(AC38="","",IF(IFERROR(INDEX(ctaMoneda,MATCH(AC38,ctaNombre,0))&"","DOP")="USD",T38,S38)) | AH38: =IF(P38="","",IF(AND(AD38<>"",COUNTIFS(tcTipo,AD38,tcLiq,"Sí")>0),IF(OR(P38="Gasto",P38="Transferencia",P38="Pago tarjeta"),-1,1)*S38,0)+IF(AND(AE38<>"",COUNTIFS(tcTipo,AE38,tcLiq,"Sí")>0),S38,0)) | AI38: =IF(OR(L38="",P38=""),"",IF(COUNTIFS(L$6:L38,L38,P$6:P38,"?*")=1,MAX(AI$5:AI37)+1,""))
B39: 46250 | C39: Transferencia | F39: DEMO · Recarga de billetera digital | G39: 4000 | H39: DOP | J39: Banco principal | K39: Billetera digital | N39: DEMOSTRACIÓN | O39: =IF(AND(B39="",G39="",C39="",D39="",J39=""),"",IF(B39="","⚠ Falta fecha",IF(G39="","⚠ Falta monto",IF(Q39="","⚠ Falta cuenta",IF(ISNA(MATCH(Q39,ctaNombre,0)),"⚠ Cuenta no registrada",IF(AND(OR(P39="Gasto",P39="Reembolso"),D39=""),"⚠ Falta categoría",IF(AND(D39<>"",E39<>"",ISNA(MATCH(D39&"|"&E39,catClave,0))),"⚠ Subcategoría no corresponde",IF(AND(OR(P39="Transferencia",P39="Pago tarjeta"),K39=""),"⚠ Falta cuenta destino",IF(AND(K39<>"",P39<>"Transferencia",P39<>"Pago tarjeta"),"⚠ Destino solo aplica a transferencias",IF(AND(K39<>"",K39=Q39),"⚠ Origen igual a destino",IF(AND(K39<>"",ISNA(MATCH(K39,ctaNombre,0))),"⚠ Destino no registrado",IF(AND(P39="Pago tarjeta",AE39<>"Tarjeta de crédito"),"⚠ El destino debe ser tarjeta de crédito",IF(AND(P39="Gasto",E39="Depósitos y retiros"),"⚠ Usa tipo Transferencia",IF(AND(P39="Resultado trading",AD39<>"Cuenta de trading"),"⚠ Usa una cuenta de trading",IF(AND(G39<=0,P39<>"Ajuste",P39<>"Resultado trading"),"⚠ El monto debe ser positivo","✓"))))))))))))))) | P39: =IF(OR(B39="",G39=""),"",IF(C39="","Gasto",C39)) | Q39: =IF(P39="","",IF(J39<>"",J39,CuentaPred&"")) | R39: =IF(P39="","",IF(ISNUMBER(I39),I39,TasaUSD)) | S39: =IF(P39="","",IF(H39="USD",G39*R39,G39)) | T39: =IF(P39="","",IF(H39="USD",G39,IF(R39>0,G39/R39,0))) | U39: =IF(P39="","",IF(P39="Gasto",S39,IF(P39="Reembolso",-S39,0))) | V39: =IF(P39="","",IF(P39="Ingreso",S39,0)) | W39: =IF(P39="","",IF(P39="Resultado trading",S39,0)) | X39: =IF(OR(P39="Gasto",P39="Reembolso"),IF(M39<>"",M39,IFERROR(INDEX(catClasif,MATCH(D39&"|"&E39,catClave,0))&"","Variable")),"") | Y39: =IF(P39="","",IFERROR(INDEX(catGrupo,MATCH(D39&"|"&E39,catClave,0))&"","")) | Z39: =IF(P39="","",WEEKDAY(B39,2)) | AA39: =IF(P39="","",IF(AND(P39="Gasto",X39="Variable",D39<>catTrading,S39>0,S39<=Umbral),1,0)) | AB39: =IF(OR(P39="",Q39=""),"",IFERROR(IF(INDEX(ctaVinc,MATCH(Q39,ctaNombre,0))&""<>"",INDEX(ctaVinc,MATCH(Q39,ctaNombre,0))&"",Q39),Q39)) | AC39: =IF(OR(K39="",AND(P39<>"Transferencia",P39<>"Pago tarjeta")),"",IFERROR(IF(INDEX(ctaVinc,MATCH(K39,ctaNombre,0))&""<>"",INDEX(ctaVinc,MATCH(K39,ctaNombre,0))&"",K39),K39)) | AD39: =IF(AB39="","",IFERROR(INDEX(ctaTipo,MATCH(AB39,ctaNombre,0))&"","")) | AE39: =IF(AC39="","",IFERROR(INDEX(ctaTipo,MATCH(AC39,ctaNombre,0))&"","")) | AF39: =IF(OR(P39="",AB39=""),"",IF(OR(P39="Gasto",P39="Transferencia",P39="Pago tarjeta"),-1,1)*IF(IFERROR(INDEX(ctaMoneda,MATCH(AB39,ctaNombre,0))&"","DOP")="USD",T39,S39)) | AG39: =IF(AC39="","",IF(IFERROR(INDEX(ctaMoneda,MATCH(AC39,ctaNombre,0))&"","DOP")="USD",T39,S39)) | AH39: =IF(P39="","",IF(AND(AD39<>"",COUNTIFS(tcTipo,AD39,tcLiq,"Sí")>0),IF(OR(P39="Gasto",P39="Transferencia",P39="Pago tarjeta"),-1,1)*S39,0)+IF(AND(AE39<>"",COUNTIFS(tcTipo,AE39,tcLiq,"Sí")>0),S39,0)) | AI39: =IF(OR(L39="",P39=""),"",IF(COUNTIFS(L$6:L39,L39,P$6:P39,"?*")=1,MAX(AI$5:AI38)+1,""))
B40: 46250 | C40: Transferencia | F40: DEMO · Retiro en cajero | G40: 4000 | H40: DOP | J40: Banco principal | K40: Efectivo | N40: DEMOSTRACIÓN | O40: =IF(AND(B40="",G40="",C40="",D40="",J40=""),"",IF(B40="","⚠ Falta fecha",IF(G40="","⚠ Falta monto",IF(Q40="","⚠ Falta cuenta",IF(ISNA(MATCH(Q40,ctaNombre,0)),"⚠ Cuenta no registrada",IF(AND(OR(P40="Gasto",P40="Reembolso"),D40=""),"⚠ Falta categoría",IF(AND(D40<>"",E40<>"",ISNA(MATCH(D40&"|"&E40,catClave,0))),"⚠ Subcategoría no corresponde",IF(AND(OR(P40="Transferencia",P40="Pago tarjeta"),K40=""),"⚠ Falta cuenta destino",IF(AND(K40<>"",P40<>"Transferencia",P40<>"Pago tarjeta"),"⚠ Destino solo aplica a transferencias",IF(AND(K40<>"",K40=Q40),"⚠ Origen igual a destino",IF(AND(K40<>"",ISNA(MATCH(K40,ctaNombre,0))),"⚠ Destino no registrado",IF(AND(P40="Pago tarjeta",AE40<>"Tarjeta de crédito"),"⚠ El destino debe ser tarjeta de crédito",IF(AND(P40="Gasto",E40="Depósitos y retiros"),"⚠ Usa tipo Transferencia",IF(AND(P40="Resultado trading",AD40<>"Cuenta de trading"),"⚠ Usa una cuenta de trading",IF(AND(G40<=0,P40<>"Ajuste",P40<>"Resultado trading"),"⚠ El monto debe ser positivo","✓"))))))))))))))) | P40: =IF(OR(B40="",G40=""),"",IF(C40="","Gasto",C40)) | Q40: =IF(P40="","",IF(J40<>"",J40,CuentaPred&"")) | R40: =IF(P40="","",IF(ISNUMBER(I40),I40,TasaUSD)) | S40: =IF(P40="","",IF(H40="USD",G40*R40,G40)) | T40: =IF(P40="","",IF(H40="USD",G40,IF(R40>0,G40/R40,0))) | U40: =IF(P40="","",IF(P40="Gasto",S40,IF(P40="Reembolso",-S40,0))) | V40: =IF(P40="","",IF(P40="Ingreso",S40,0)) | W40: =IF(P40="","",IF(P40="Resultado trading",S40,0)) | X40: =IF(OR(P40="Gasto",P40="Reembolso"),IF(M40<>"",M40,IFERROR(INDEX(catClasif,MATCH(D40&"|"&E40,catClave,0))&"","Variable")),"") | Y40: =IF(P40="","",IFERROR(INDEX(catGrupo,MATCH(D40&"|"&E40,catClave,0))&"","")) | Z40: =IF(P40="","",WEEKDAY(B40,2)) | AA40: =IF(P40="","",IF(AND(P40="Gasto",X40="Variable",D40<>catTrading,S40>0,S40<=Umbral),1,0)) | AB40: =IF(OR(P40="",Q40=""),"",IFERROR(IF(INDEX(ctaVinc,MATCH(Q40,ctaNombre,0))&""<>"",INDEX(ctaVinc,MATCH(Q40,ctaNombre,0))&"",Q40),Q40)) | AC40: =IF(OR(K40="",AND(P40<>"Transferencia",P40<>"Pago tarjeta")),"",IFERROR(IF(INDEX(ctaVinc,MATCH(K40,ctaNombre,0))&""<>"",INDEX(ctaVinc,MATCH(K40,ctaNombre,0))&"",K40),K40)) | AD40: =IF(AB40="","",IFERROR(INDEX(ctaTipo,MATCH(AB40,ctaNombre,0))&"","")) | AE40: =IF(AC40="","",IFERROR(INDEX(ctaTipo,MATCH(AC40,ctaNombre,0))&"","")) | AF40: =IF(OR(P40="",AB40=""),"",IF(OR(P40="Gasto",P40="Transferencia",P40="Pago tarjeta"),-1,1)*IF(IFERROR(INDEX(ctaMoneda,MATCH(AB40,ctaNombre,0))&"","DOP")="USD",T40,S40)) | AG40: =IF(AC40="","",IF(IFERROR(INDEX(ctaMoneda,MATCH(AC40,ctaNombre,0))&"","DOP")="USD",T40,S40)) | AH40: =IF(P40="","",IF(AND(AD40<>"",COUNTIFS(tcTipo,AD40,tcLiq,"Sí")>0),IF(OR(P40="Gasto",P40="Transferencia",P40="Pago tarjeta"),-1,1)*S40,0)+IF(AND(AE40<>"",COUNTIFS(tcTipo,AE40,tcLiq,"Sí")>0),S40,0)) | AI40: =IF(OR(L40="",P40=""),"",IF(COUNTIFS(L$6:L40,L40,P$6:P40,"?*")=1,MAX(AI$5:AI39)+1,""))
B41: 46251 | C41: Gasto | D41: Alimentación | E41: Almuerzos laborales | F41: DEMO · Almuerzo laboral | G41: 375 | H41: DOP | J41: Billetera digital | L41: Comedor ejecutivo | N41: DEMOSTRACIÓN | O41: =IF(AND(B41="",G41="",C41="",D41="",J41=""),"",IF(B41="","⚠ Falta fecha",IF(G41="","⚠ Falta monto",IF(Q41="","⚠ Falta cuenta",IF(ISNA(MATCH(Q41,ctaNombre,0)),"⚠ Cuenta no registrada",IF(AND(OR(P41="Gasto",P41="Reembolso"),D41=""),"⚠ Falta categoría",IF(AND(D41<>"",E41<>"",ISNA(MATCH(D41&"|"&E41,catClave,0))),"⚠ Subcategoría no corresponde",IF(AND(OR(P41="Transferencia",P41="Pago tarjeta"),K41=""),"⚠ Falta cuenta destino",IF(AND(K41<>"",P41<>"Transferencia",P41<>"Pago tarjeta"),"⚠ Destino solo aplica a transferencias",IF(AND(K41<>"",K41=Q41),"⚠ Origen igual a destino",IF(AND(K41<>"",ISNA(MATCH(K41,ctaNombre,0))),"⚠ Destino no registrado",IF(AND(P41="Pago tarjeta",AE41<>"Tarjeta de crédito"),"⚠ El destino debe ser tarjeta de crédito",IF(AND(P41="Gasto",E41="Depósitos y retiros"),"⚠ Usa tipo Transferencia",IF(AND(P41="Resultado trading",AD41<>"Cuenta de trading"),"⚠ Usa una cuenta de trading",IF(AND(G41<=0,P41<>"Ajuste",P41<>"Resultado trading"),"⚠ El monto debe ser positivo","✓"))))))))))))))) | P41: =IF(OR(B41="",G41=""),"",IF(C41="","Gasto",C41)) | Q41: =IF(P41="","",IF(J41<>"",J41,CuentaPred&"")) | R41: =IF(P41="","",IF(ISNUMBER(I41),I41,TasaUSD)) | S41: =IF(P41="","",IF(H41="USD",G41*R41,G41)) | T41: =IF(P41="","",IF(H41="USD",G41,IF(R41>0,G41/R41,0))) | U41: =IF(P41="","",IF(P41="Gasto",S41,IF(P41="Reembolso",-S41,0))) | V41: =IF(P41="","",IF(P41="Ingreso",S41,0)) | W41: =IF(P41="","",IF(P41="Resultado trading",S41,0)) | X41: =IF(OR(P41="Gasto",P41="Reembolso"),IF(M41<>"",M41,IFERROR(INDEX(catClasif,MATCH(D41&"|"&E41,catClave,0))&"","Variable")),"") | Y41: =IF(P41="","",IFERROR(INDEX(catGrupo,MATCH(D41&"|"&E41,catClave,0))&"","")) | Z41: =IF(P41="","",WEEKDAY(B41,2)) | AA41: =IF(P41="","",IF(AND(P41="Gasto",X41="Variable",D41<>catTrading,S41>0,S41<=Umbral),1,0)) | AB41: =IF(OR(P41="",Q41=""),"",IFERROR(IF(INDEX(ctaVinc,MATCH(Q41,ctaNombre,0))&""<>"",INDEX(ctaVinc,MATCH(Q41,ctaNombre,0))&"",Q41),Q41)) | AC41: =IF(OR(K41="",AND(P41<>"Transferencia",P41<>"Pago tarjeta")),"",IFERROR(IF(INDEX(ctaVinc,MATCH(K41,ctaNombre,0))&""<>"",INDEX(ctaVinc,MATCH(K41,ctaNombre,0))&"",K41),K41)) | AD41: =IF(AB41="","",IFERROR(INDEX(ctaTipo,MATCH(AB41,ctaNombre,0))&"","")) | AE41: =IF(AC41="","",IFERROR(INDEX(ctaTipo,MATCH(AC41,ctaNombre,0))&"","")) | AF41: =IF(OR(P41="",AB41=""),"",IF(OR(P41="Gasto",P41="Transferencia",P41="Pago tarjeta"),-1,1)*IF(IFERROR(INDEX(ctaMoneda,MATCH(AB41,ctaNombre,0))&"","DOP")="USD",T41,S41)) | AG41: =IF(AC41="","",IF(IFERROR(INDEX(ctaMoneda,MATCH(AC41,ctaNombre,0))&"","DOP")="USD",T41,S41)) | AH41: =IF(P41="","",IF(AND(AD41<>"",COUNTIFS(tcTipo,AD41,tcLiq,"Sí")>0),IF(OR(P41="Gasto",P41="Transferencia",P41="Pago tarjeta"),-1,1)*S41,0)+IF(AND(AE41<>"",COUNTIFS(tcTipo,AE41,tcLiq,"Sí")>0),S41,0)) | AI41: =IF(OR(L41="",P41=""),"",IF(COUNTIFS(L$6:L41,L41,P$6:P41,"?*")=1,MAX(AI$5:AI40)+1,""))
B42: 46251 | C42: Gasto | D42: Transporte y vehículo | E42: Combustible | F42: DEMO · Combustible | G42: 2800 | H42: DOP | J42: Tarjeta de crédito | L42: Estación de combustible | N42: DEMOSTRACIÓN | O42: =IF(AND(B42="",G42="",C42="",D42="",J42=""),"",IF(B42="","⚠ Falta fecha",IF(G42="","⚠ Falta monto",IF(Q42="","⚠ Falta cuenta",IF(ISNA(MATCH(Q42,ctaNombre,0)),"⚠ Cuenta no registrada",IF(AND(OR(P42="Gasto",P42="Reembolso"),D42=""),"⚠ Falta categoría",IF(AND(D42<>"",E42<>"",ISNA(MATCH(D42&"|"&E42,catClave,0))),"⚠ Subcategoría no corresponde",IF(AND(OR(P42="Transferencia",P42="Pago tarjeta"),K42=""),"⚠ Falta cuenta destino",IF(AND(K42<>"",P42<>"Transferencia",P42<>"Pago tarjeta"),"⚠ Destino solo aplica a transferencias",IF(AND(K42<>"",K42=Q42),"⚠ Origen igual a destino",IF(AND(K42<>"",ISNA(MATCH(K42,ctaNombre,0))),"⚠ Destino no registrado",IF(AND(P42="Pago tarjeta",AE42<>"Tarjeta de crédito"),"⚠ El destino debe ser tarjeta de crédito",IF(AND(P42="Gasto",E42="Depósitos y retiros"),"⚠ Usa tipo Transferencia",IF(AND(P42="Resultado trading",AD42<>"Cuenta de trading"),"⚠ Usa una cuenta de trading",IF(AND(G42<=0,P42<>"Ajuste",P42<>"Resultado trading"),"⚠ El monto debe ser positivo","✓"))))))))))))))) | P42: =IF(OR(B42="",G42=""),"",IF(C42="","Gasto",C42)) | Q42: =IF(P42="","",IF(J42<>"",J42,CuentaPred&"")) | R42: =IF(P42="","",IF(ISNUMBER(I42),I42,TasaUSD)) | S42: =IF(P42="","",IF(H42="USD",G42*R42,G42)) | T42: =IF(P42="","",IF(H42="USD",G42,IF(R42>0,G42/R42,0))) | U42: =IF(P42="","",IF(P42="Gasto",S42,IF(P42="Reembolso",-S42,0))) | V42: =IF(P42="","",IF(P42="Ingreso",S42,0)) | W42: =IF(P42="","",IF(P42="Resultado trading",S42,0)) | X42: =IF(OR(P42="Gasto",P42="Reembolso"),IF(M42<>"",M42,IFERROR(INDEX(catClasif,MATCH(D42&"|"&E42,catClave,0))&"","Variable")),"") | Y42: =IF(P42="","",IFERROR(INDEX(catGrupo,MATCH(D42&"|"&E42,catClave,0))&"","")) | Z42: =IF(P42="","",WEEKDAY(B42,2)) | AA42: =IF(P42="","",IF(AND(P42="Gasto",X42="Variable",D42<>catTrading,S42>0,S42<=Umbral),1,0)) | AB42: =IF(OR(P42="",Q42=""),"",IFERROR(IF(INDEX(ctaVinc,MATCH(Q42,ctaNombre,0))&""<>"",INDEX(ctaVinc,MATCH(Q42,ctaNombre,0))&"",Q42),Q42)) | AC42: =IF(OR(K42="",AND(P42<>"Transferencia",P42<>"Pago tarjeta")),"",IFERROR(IF(INDEX(ctaVinc,MATCH(K42,ctaNombre,0))&""<>"",INDEX(ctaVinc,MATCH(K42,ctaNombre,0))&"",K42),K42)) | AD42: =IF(AB42="","",IFERROR(INDEX(ctaTipo,MATCH(AB42,ctaNombre,0))&"","")) | AE42: =IF(AC42="","",IFERROR(INDEX(ctaTipo,MATCH(AC42,ctaNombre,0))&"","")) | AF42: =IF(OR(P42="",AB42=""),"",IF(OR(P42="Gasto",P42="Transferencia",P42="Pago tarjeta"),-1,1)*IF(IFERROR(INDEX(ctaMoneda,MATCH(AB42,ctaNombre,0))&"","DOP")="USD",T42,S42)) | AG42: =IF(AC42="","",IF(IFERROR(INDEX(ctaMoneda,MATCH(AC42,ctaNombre,0))&"","DOP")="USD",T42,S42)) | AH42: =IF(P42="","",IF(AND(AD42<>"",COUNTIFS(tcTipo,AD42,tcLiq,"Sí")>0),IF(OR(P42="Gasto",P42="Transferencia",P42="Pago tarjeta"),-1,1)*S42,0)+IF(AND(AE42<>"",COUNTIFS(tcTipo,AE42,tcLiq,"Sí")>0),S42,0)) | AI42: =IF(OR(L42="",P42=""),"",IF(COUNTIFS(L$6:L42,L42,P$6:P42,"?*")=1,MAX(AI$5:AI41)+1,""))
B43: 46252 | C43: Gasto | D43: Alimentación | E43: Desayunos comprados | F43: DEMO · Desayuno en la oficina | G43: 230 | H43: DOP | J43: Efectivo | L43: Cafetería del trabajo | N43: DEMOSTRACIÓN | O43: =IF(AND(B43="",G43="",C43="",D43="",J43=""),"",IF(B43="","⚠ Falta fecha",IF(G43="","⚠ Falta monto",IF(Q43="","⚠ Falta cuenta",IF(ISNA(MATCH(Q43,ctaNombre,0)),"⚠ Cuenta no registrada",IF(AND(OR(P43="Gasto",P43="Reembolso"),D43=""),"⚠ Falta categoría",IF(AND(D43<>"",E43<>"",ISNA(MATCH(D43&"|"&E43,catClave,0))),"⚠ Subcategoría no corresponde",IF(AND(OR(P43="Transferencia",P43="Pago tarjeta"),K43=""),"⚠ Falta cuenta destino",IF(AND(K43<>"",P43<>"Transferencia",P43<>"Pago tarjeta"),"⚠ Destino solo aplica a transferencias",IF(AND(K43<>"",K43=Q43),"⚠ Origen igual a destino",IF(AND(K43<>"",ISNA(MATCH(K43,ctaNombre,0))),"⚠ Destino no registrado",IF(AND(P43="Pago tarjeta",AE43<>"Tarjeta de crédito"),"⚠ El destino debe ser tarjeta de crédito",IF(AND(P43="Gasto",E43="Depósitos y retiros"),"⚠ Usa tipo Transferencia",IF(AND(P43="Resultado trading",AD43<>"Cuenta de trading"),"⚠ Usa una cuenta de trading",IF(AND(G43<=0,P43<>"Ajuste",P43<>"Resultado trading"),"⚠ El monto debe ser positivo","✓"))))))))))))))) | P43: =IF(OR(B43="",G43=""),"",IF(C43="","Gasto",C43)) | Q43: =IF(P43="","",IF(J43<>"",J43,CuentaPred&"")) | R43: =IF(P43="","",IF(ISNUMBER(I43),I43,TasaUSD)) | S43: =IF(P43="","",IF(H43="USD",G43*R43,G43)) | T43: =IF(P43="","",IF(H43="USD",G43,IF(R43>0,G43/R43,0))) | U43: =IF(P43="","",IF(P43="Gasto",S43,IF(P43="Reembolso",-S43,0))) | V43: =IF(P43="","",IF(P43="Ingreso",S43,0)) | W43: =IF(P43="","",IF(P43="Resultado trading",S43,0)) | X43: =IF(OR(P43="Gasto",P43="Reembolso"),IF(M43<>"",M43,IFERROR(INDEX(catClasif,MATCH(D43&"|"&E43,catClave,0))&"","Variable")),"") | Y43: =IF(P43="","",IFERROR(INDEX(catGrupo,MATCH(D43&"|"&E43,catClave,0))&"","")) | Z43: =IF(P43="","",WEEKDAY(B43,2)) | AA43: =IF(P43="","",IF(AND(P43="Gasto",X43="Variable",D43<>catTrading,S43>0,S43<=Umbral),1,0)) | AB43: =IF(OR(P43="",Q43=""),"",IFERROR(IF(INDEX(ctaVinc,MATCH(Q43,ctaNombre,0))&""<>"",INDEX(ctaVinc,MATCH(Q43,ctaNombre,0))&"",Q43),Q43)) | AC43: =IF(OR(K43="",AND(P43<>"Transferencia",P43<>"Pago tarjeta")),"",IFERROR(IF(INDEX(ctaVinc,MATCH(K43,ctaNombre,0))&""<>"",INDEX(ctaVinc,MATCH(K43,ctaNombre,0))&"",K43),K43)) | AD43: =IF(AB43="","",IFERROR(INDEX(ctaTipo,MATCH(AB43,ctaNombre,0))&"","")) | AE43: =IF(AC43="","",IFERROR(INDEX(ctaTipo,MATCH(AC43,ctaNombre,0))&"","")) | AF43: =IF(OR(P43="",AB43=""),"",IF(OR(P43="Gasto",P43="Transferencia",P43="Pago tarjeta"),-1,1)*IF(IFERROR(INDEX(ctaMoneda,MATCH(AB43,ctaNombre,0))&"","DOP")="USD",T43,S43)) | AG43: =IF(AC43="","",IF(IFERROR(INDEX(ctaMoneda,MATCH(AC43,ctaNombre,0))&"","DOP")="USD",T43,S43)) | AH43: =IF(P43="","",IF(AND(AD43<>"",COUNTIFS(tcTipo,AD43,tcLiq,"Sí")>0),IF(OR(P43="Gasto",P43="Transferencia",P43="Pago tarjeta"),-1,1)*S43,0)+IF(AND(AE43<>"",COUNTIFS(tcTipo,AE43,tcLiq,"Sí")>0),S43,0)) | AI43: =IF(OR(L43="",P43=""),"",IF(COUNTIFS(L$6:L43,L43,P$6:P43,"?*")=1,MAX(AI$5:AI42)+1,""))
B44: 46252 | C44: Gasto | D44: Transporte y vehículo | E44: Parqueos y peajes | F44: DEMO · Parqueo | G44: 75 | H44: DOP | J44: Efectivo | L44: Parqueo centro | N44: DEMOSTRACIÓN | O44: =IF(AND(B44="",G44="",C44="",D44="",J44=""),"",IF(B44="","⚠ Falta fecha",IF(G44="","⚠ Falta monto",IF(Q44="","⚠ Falta cuenta",IF(ISNA(MATCH(Q44,ctaNombre,0)),"⚠ Cuenta no registrada",IF(AND(OR(P44="Gasto",P44="Reembolso"),D44=""),"⚠ Falta categoría",IF(AND(D44<>"",E44<>"",ISNA(MATCH(D44&"|"&E44,catClave,0))),"⚠ Subcategoría no corresponde",IF(AND(OR(P44="Transferencia",P44="Pago tarjeta"),K44=""),"⚠ Falta cuenta destino",IF(AND(K44<>"",P44<>"Transferencia",P44<>"Pago tarjeta"),"⚠ Destino solo aplica a transferencias",IF(AND(K44<>"",K44=Q44),"⚠ Origen igual a destino",IF(AND(K44<>"",ISNA(MATCH(K44,ctaNombre,0))),"⚠ Destino no registrado",IF(AND(P44="Pago tarjeta",AE44<>"Tarjeta de crédito"),"⚠ El destino debe ser tarjeta de crédito",IF(AND(P44="Gasto",E44="Depósitos y retiros"),"⚠ Usa tipo Transferencia",IF(AND(P44="Resultado trading",AD44<>"Cuenta de trading"),"⚠ Usa una cuenta de trading",IF(AND(G44<=0,P44<>"Ajuste",P44<>"Resultado trading"),"⚠ El monto debe ser positivo","✓"))))))))))))))) | P44: =IF(OR(B44="",G44=""),"",IF(C44="","Gasto",C44)) | Q44: =IF(P44="","",IF(J44<>"",J44,CuentaPred&"")) | R44: =IF(P44="","",IF(ISNUMBER(I44),I44,TasaUSD)) | S44: =IF(P44="","",IF(H44="USD",G44*R44,G44)) | T44: =IF(P44="","",IF(H44="USD",G44,IF(R44>0,G44/R44,0))) | U44: =IF(P44="","",IF(P44="Gasto",S44,IF(P44="Reembolso",-S44,0))) | V44: =IF(P44="","",IF(P44="Ingreso",S44,0)) | W44: =IF(P44="","",IF(P44="Resultado trading",S44,0)) | X44: =IF(OR(P44="Gasto",P44="Reembolso"),IF(M44<>"",M44,IFERROR(INDEX(catClasif,MATCH(D44&"|"&E44,catClave,0))&"","Variable")),"") | Y44: =IF(P44="","",IFERROR(INDEX(catGrupo,MATCH(D44&"|"&E44,catClave,0))&"","")) | Z44: =IF(P44="","",WEEKDAY(B44,2)) | AA44: =IF(P44="","",IF(AND(P44="Gasto",X44="Variable",D44<>catTrading,S44>0,S44<=Umbral),1,0)) | AB44: =IF(OR(P44="",Q44=""),"",IFERROR(IF(INDEX(ctaVinc,MATCH(Q44,ctaNombre,0))&""<>"",INDEX(ctaVinc,MATCH(Q44,ctaNombre,0))&"",Q44),Q44)) | AC44: =IF(OR(K44="",AND(P44<>"Transferencia",P44<>"Pago tarjeta")),"",IFERROR(IF(INDEX(ctaVinc,MATCH(K44,ctaNombre,0))&""<>"",INDEX(ctaVinc,MATCH(K44,ctaNombre,0))&"",K44),K44)) | AD44: =IF(AB44="","",IFERROR(INDEX(ctaTipo,MATCH(AB44,ctaNombre,0))&"","")) | AE44: =IF(AC44="","",IFERROR(INDEX(ctaTipo,MATCH(AC44,ctaNombre,0))&"","")) | AF44: =IF(OR(P44="",AB44=""),"",IF(OR(P44="Gasto",P44="Transferencia",P44="Pago tarjeta"),-1,1)*IF(IFERROR(INDEX(ctaMoneda,MATCH(AB44,ctaNombre,0))&"","DOP")="USD",T44,S44)) | AG44: =IF(AC44="","",IF(IFERROR(INDEX(ctaMoneda,MATCH(AC44,ctaNombre,0))&"","DOP")="USD",T44,S44)) | AH44: =IF(P44="","",IF(AND(AD44<>"",COUNTIFS(tcTipo,AD44,tcLiq,"Sí")>0),IF(OR(P44="Gasto",P44="Transferencia",P44="Pago tarjeta"),-1,1)*S44,0)+IF(AND(AE44<>"",COUNTIFS(tcTipo,AE44,tcLiq,"Sí")>0),S44,0)) | AI44: =IF(OR(L44="",P44=""),"",IF(COUNTIFS(L$6:L44,L44,P$6:P44,"?*")=1,MAX(AI$5:AI43)+1,""))
B45: 46252 | C45: Gasto | D45: Tecnología y suscripciones | E45: Entretenimiento | F45: DEMO · Streaming de video | G45: 10.99 | H45: USD | J45: Tarjeta de crédito | L45: Streaming | N45: DEMOSTRACIÓN | O45: =IF(AND(B45="",G45="",C45="",D45="",J45=""),"",IF(B45="","⚠ Falta fecha",IF(G45="","⚠ Falta monto",IF(Q45="","⚠ Falta cuenta",IF(ISNA(MATCH(Q45,ctaNombre,0)),"⚠ Cuenta no registrada",IF(AND(OR(P45="Gasto",P45="Reembolso"),D45=""),"⚠ Falta categoría",IF(AND(D45<>"",E45<>"",ISNA(MATCH(D45&"|"&E45,catClave,0))),"⚠ Subcategoría no corresponde",IF(AND(OR(P45="Transferencia",P45="Pago tarjeta"),K45=""),"⚠ Falta cuenta destino",IF(AND(K45<>"",P45<>"Transferencia",P45<>"Pago tarjeta"),"⚠ Destino solo aplica a transferencias",IF(AND(K45<>"",K45=Q45),"⚠ Origen igual a destino",IF(AND(K45<>"",ISNA(MATCH(K45,ctaNombre,0))),"⚠ Destino no registrado",IF(AND(P45="Pago tarjeta",AE45<>"Tarjeta de crédito"),"⚠ El destino debe ser tarjeta de crédito",IF(AND(P45="Gasto",E45="Depósitos y retiros"),"⚠ Usa tipo Transferencia",IF(AND(P45="Resultado trading",AD45<>"Cuenta de trading"),"⚠ Usa una cuenta de trading",IF(AND(G45<=0,P45<>"Ajuste",P45<>"Resultado trading"),"⚠ El monto debe ser positivo","✓"))))))))))))))) | P45: =IF(OR(B45="",G45=""),"",IF(C45="","Gasto",C45)) | Q45: =IF(P45="","",IF(J45<>"",J45,CuentaPred&"")) | R45: =IF(P45="","",IF(ISNUMBER(I45),I45,TasaUSD)) | S45: =IF(P45="","",IF(H45="USD",G45*R45,G45)) | T45: =IF(P45="","",IF(H45="USD",G45,IF(R45>0,G45/R45,0))) | U45: =IF(P45="","",IF(P45="Gasto",S45,IF(P45="Reembolso",-S45,0))) | V45: =IF(P45="","",IF(P45="Ingreso",S45,0)) | W45: =IF(P45="","",IF(P45="Resultado trading",S45,0)) | X45: =IF(OR(P45="Gasto",P45="Reembolso"),IF(M45<>"",M45,IFERROR(INDEX(catClasif,MATCH(D45&"|"&E45,catClave,0))&"","Variable")),"") | Y45: =IF(P45="","",IFERROR(INDEX(catGrupo,MATCH(D45&"|"&E45,catClave,0))&"","")) | Z45: =IF(P45="","",WEEKDAY(B45,2)) | AA45: =IF(P45="","",IF(AND(P45="Gasto",X45="Variable",D45<>catTrading,S45>0,S45<=Umbral),1,0)) | AB45: =IF(OR(P45="",Q45=""),"",IFERROR(IF(INDEX(ctaVinc,MATCH(Q45,ctaNombre,0))&""<>"",INDEX(ctaVinc,MATCH(Q45,ctaNombre,0))&"",Q45),Q45)) | AC45: =IF(OR(K45="",AND(P45<>"Transferencia",P45<>"Pago tarjeta")),"",IFERROR(IF(INDEX(ctaVinc,MATCH(K45,ctaNombre,0))&""<>"",INDEX(ctaVinc,MATCH(K45,ctaNombre,0))&"",K45),K45)) | AD45: =IF(AB45="","",IFERROR(INDEX(ctaTipo,MATCH(AB45,ctaNombre,0))&"","")) | AE45: =IF(AC45="","",IFERROR(INDEX(ctaTipo,MATCH(AC45,ctaNombre,0))&"","")) | AF45: =IF(OR(P45="",AB45=""),"",IF(OR(P45="Gasto",P45="Transferencia",P45="Pago tarjeta"),-1,1)*IF(IFERROR(INDEX(ctaMoneda,MATCH(AB45,ctaNombre,0))&"","DOP")="USD",T45,S45)) | AG45: =IF(AC45="","",IF(IFERROR(INDEX(ctaMoneda,MATCH(AC45,ctaNombre,0))&"","DOP")="USD",T45,S45)) | AH45: =IF(P45="","",IF(AND(AD45<>"",COUNTIFS(tcTipo,AD45,tcLiq,"Sí")>0),IF(OR(P45="Gasto",P45="Transferencia",P45="Pago tarjeta"),-1,1)*S45,0)+IF(AND(AE45<>"",COUNTIFS(tcTipo,AE45,tcLiq,"Sí")>0),S45,0)) | AI45: =IF(OR(L45="",P45=""),"",IF(COUNTIFS(L$6:L45,L45,P$6:P45,"?*")=1,MAX(AI$5:AI44)+1,""))
B46: 46253 | C46: Gasto | D46: Alimentación | E46: Desayunos comprados | F46: DEMO · Desayuno en la oficina | G46: 240 | H46: DOP | J46: Efectivo | L46: Cafetería del trabajo | N46: DEMOSTRACIÓN | O46: =IF(AND(B46="",G46="",C46="",D46="",J46=""),"",IF(B46="","⚠ Falta fecha",IF(G46="","⚠ Falta monto",IF(Q46="","⚠ Falta cuenta",IF(ISNA(MATCH(Q46,ctaNombre,0)),"⚠ Cuenta no registrada",IF(AND(OR(P46="Gasto",P46="Reembolso"),D46=""),"⚠ Falta categoría",IF(AND(D46<>"",E46<>"",ISNA(MATCH(D46&"|"&E46,catClave,0))),"⚠ Subcategoría no corresponde",IF(AND(OR(P46="Transferencia",P46="Pago tarjeta"),K46=""),"⚠ Falta cuenta destino",IF(AND(K46<>"",P46<>"Transferencia",P46<>"Pago tarjeta"),"⚠ Destino solo aplica a transferencias",IF(AND(K46<>"",K46=Q46),"⚠ Origen igual a destino",IF(AND(K46<>"",ISNA(MATCH(K46,ctaNombre,0))),"⚠ Destino no registrado",IF(AND(P46="Pago tarjeta",AE46<>"Tarjeta de crédito"),"⚠ El destino debe ser tarjeta de crédito",IF(AND(P46="Gasto",E46="Depósitos y retiros"),"⚠ Usa tipo Transferencia",IF(AND(P46="Resultado trading",AD46<>"Cuenta de trading"),"⚠ Usa una cuenta de trading",IF(AND(G46<=0,P46<>"Ajuste",P46<>"Resultado trading"),"⚠ El monto debe ser positivo","✓"))))))))))))))) | P46: =IF(OR(B46="",G46=""),"",IF(C46="","Gasto",C46)) | Q46: =IF(P46="","",IF(J46<>"",J46,CuentaPred&"")) | R46: =IF(P46="","",IF(ISNUMBER(I46),I46,TasaUSD)) | S46: =IF(P46="","",IF(H46="USD",G46*R46,G46)) | T46: =IF(P46="","",IF(H46="USD",G46,IF(R46>0,G46/R46,0))) | U46: =IF(P46="","",IF(P46="Gasto",S46,IF(P46="Reembolso",-S46,0))) | V46: =IF(P46="","",IF(P46="Ingreso",S46,0)) | W46: =IF(P46="","",IF(P46="Resultado trading",S46,0)) | X46: =IF(OR(P46="Gasto",P46="Reembolso"),IF(M46<>"",M46,IFERROR(INDEX(catClasif,MATCH(D46&"|"&E46,catClave,0))&"","Variable")),"") | Y46: =IF(P46="","",IFERROR(INDEX(catGrupo,MATCH(D46&"|"&E46,catClave,0))&"","")) | Z46: =IF(P46="","",WEEKDAY(B46,2)) | AA46: =IF(P46="","",IF(AND(P46="Gasto",X46="Variable",D46<>catTrading,S46>0,S46<=Umbral),1,0)) | AB46: =IF(OR(P46="",Q46=""),"",IFERROR(IF(INDEX(ctaVinc,MATCH(Q46,ctaNombre,0))&""<>"",INDEX(ctaVinc,MATCH(Q46,ctaNombre,0))&"",Q46),Q46)) | AC46: =IF(OR(K46="",AND(P46<>"Transferencia",P46<>"Pago tarjeta")),"",IFERROR(IF(INDEX(ctaVinc,MATCH(K46,ctaNombre,0))&""<>"",INDEX(ctaVinc,MATCH(K46,ctaNombre,0))&"",K46),K46)) | AD46: =IF(AB46="","",IFERROR(INDEX(ctaTipo,MATCH(AB46,ctaNombre,0))&"","")) | AE46: =IF(AC46="","",IFERROR(INDEX(ctaTipo,MATCH(AC46,ctaNombre,0))&"","")) | AF46: =IF(OR(P46="",AB46=""),"",IF(OR(P46="Gasto",P46="Transferencia",P46="Pago tarjeta"),-1,1)*IF(IFERROR(INDEX(ctaMoneda,MATCH(AB46,ctaNombre,0))&"","DOP")="USD",T46,S46)) | AG46: =IF(AC46="","",IF(IFERROR(INDEX(ctaMoneda,MATCH(AC46,ctaNombre,0))&"","DOP")="USD",T46,S46)) | AH46: =IF(P46="","",IF(AND(AD46<>"",COUNTIFS(tcTipo,AD46,tcLiq,"Sí")>0),IF(OR(P46="Gasto",P46="Transferencia",P46="Pago tarjeta"),-1,1)*S46,0)+IF(AND(AE46<>"",COUNTIFS(tcTipo,AE46,tcLiq,"Sí")>0),S46,0)) | AI46: =IF(OR(L46="",P46=""),"",IF(COUNTIFS(L$6:L46,L46,P$6:P46,"?*")=1,MAX(AI$5:AI45)+1,""))
B47: 46253 | C47: Gasto | D47: Alimentación | E47: Almuerzos laborales | F47: DEMO · Almuerzo laboral | G47: 350 | H47: DOP | J47: Tarjeta de débito | L47: Comedor ejecutivo | N47: DEMOSTRACIÓN | O47: =IF(AND(B47="",G47="",C47="",D47="",J47=""),"",IF(B47="","⚠ Falta fecha",IF(G47="","⚠ Falta monto",IF(Q47="","⚠ Falta cuenta",IF(ISNA(MATCH(Q47,ctaNombre,0)),"⚠ Cuenta no registrada",IF(AND(OR(P47="Gasto",P47="Reembolso"),D47=""),"⚠ Falta categoría",IF(AND(D47<>"",E47<>"",ISNA(MATCH(D47&"|"&E47,catClave,0))),"⚠ Subcategoría no corresponde",IF(AND(OR(P47="Transferencia",P47="Pago tarjeta"),K47=""),"⚠ Falta cuenta destino",IF(AND(K47<>"",P47<>"Transferencia",P47<>"Pago tarjeta"),"⚠ Destino solo aplica a transferencias",IF(AND(K47<>"",K47=Q47),"⚠ Origen igual a destino",IF(AND(K47<>"",ISNA(MATCH(K47,ctaNombre,0))),"⚠ Destino no registrado",IF(AND(P47="Pago tarjeta",AE47<>"Tarjeta de crédito"),"⚠ El destino debe ser tarjeta de crédito",IF(AND(P47="Gasto",E47="Depósitos y retiros"),"⚠ Usa tipo Transferencia",IF(AND(P47="Resultado trading",AD47<>"Cuenta de trading"),"⚠ Usa una cuenta de trading",IF(AND(G47<=0,P47<>"Ajuste",P47<>"Resultado trading"),"⚠ El monto debe ser positivo","✓"))))))))))))))) | P47: =IF(OR(B47="",G47=""),"",IF(C47="","Gasto",C47)) | Q47: =IF(P47="","",IF(J47<>"",J47,CuentaPred&"")) | R47: =IF(P47="","",IF(ISNUMBER(I47),I47,TasaUSD)) | S47: =IF(P47="","",IF(H47="USD",G47*R47,G47)) | T47: =IF(P47="","",IF(H47="USD",G47,IF(R47>0,G47/R47,0))) | U47: =IF(P47="","",IF(P47="Gasto",S47,IF(P47="Reembolso",-S47,0))) | V47: =IF(P47="","",IF(P47="Ingreso",S47,0)) | W47: =IF(P47="","",IF(P47="Resultado trading",S47,0)) | X47: =IF(OR(P47="Gasto",P47="Reembolso"),IF(M47<>"",M47,IFERROR(INDEX(catClasif,MATCH(D47&"|"&E47,catClave,0))&"","Variable")),"") | Y47: =IF(P47="","",IFERROR(INDEX(catGrupo,MATCH(D47&"|"&E47,catClave,0))&"","")) | Z47: =IF(P47="","",WEEKDAY(B47,2)) | AA47: =IF(P47="","",IF(AND(P47="Gasto",X47="Variable",D47<>catTrading,S47>0,S47<=Umbral),1,0)) | AB47: =IF(OR(P47="",Q47=""),"",IFERROR(IF(INDEX(ctaVinc,MATCH(Q47,ctaNombre,0))&""<>"",INDEX(ctaVinc,MATCH(Q47,ctaNombre,0))&"",Q47),Q47)) | AC47: =IF(OR(K47="",AND(P47<>"Transferencia",P47<>"Pago tarjeta")),"",IFERROR(IF(INDEX(ctaVinc,MATCH(K47,ctaNombre,0))&""<>"",INDEX(ctaVinc,MATCH(K47,ctaNombre,0))&"",K47),K47)) | AD47: =IF(AB47="","",IFERROR(INDEX(ctaTipo,MATCH(AB47,ctaNombre,0))&"","")) | AE47: =IF(AC47="","",IFERROR(INDEX(ctaTipo,MATCH(AC47,ctaNombre,0))&"","")) | AF47: =IF(OR(P47="",AB47=""),"",IF(OR(P47="Gasto",P47="Transferencia",P47="Pago tarjeta"),-1,1)*IF(IFERROR(INDEX(ctaMoneda,MATCH(AB47,ctaNombre,0))&"","DOP")="USD",T47,S47)) | AG47: =IF(AC47="","",IF(IFERROR(INDEX(ctaMoneda,MATCH(AC47,ctaNombre,0))&"","DOP")="USD",T47,S47)) | AH47: =IF(P47="","",IF(AND(AD47<>"",COUNTIFS(tcTipo,AD47,tcLiq,"Sí")>0),IF(OR(P47="Gasto",P47="Transferencia",P47="Pago tarjeta"),-1,1)*S47,0)+IF(AND(AE47<>"",COUNTIFS(tcTipo,AE47,tcLiq,"Sí")>0),S47,0)) | AI47: =IF(OR(L47="",P47=""),"",IF(COUNTIFS(L$6:L47,L47,P$6:P47,"?*")=1,MAX(AI$5:AI46)+1,""))
B48: 46253 | C48: Gasto | D48: Alimentación | E48: Bebidas, snacks y otros consumos | F48: DEMO · Jugo y galletas | G48: 170 | H48: DOP | J48: Efectivo | L48: Cafetería del trabajo | N48: DEMOSTRACIÓN | O48: =IF(AND(B48="",G48="",C48="",D48="",J48=""),"",IF(B48="","⚠ Falta fecha",IF(G48="","⚠ Falta monto",IF(Q48="","⚠ Falta cuenta",IF(ISNA(MATCH(Q48,ctaNombre,0)),"⚠ Cuenta no registrada",IF(AND(OR(P48="Gasto",P48="Reembolso"),D48=""),"⚠ Falta categoría",IF(AND(D48<>"",E48<>"",ISNA(MATCH(D48&"|"&E48,catClave,0))),"⚠ Subcategoría no corresponde",IF(AND(OR(P48="Transferencia",P48="Pago tarjeta"),K48=""),"⚠ Falta cuenta destino",IF(AND(K48<>"",P48<>"Transferencia",P48<>"Pago tarjeta"),"⚠ Destino solo aplica a transferencias",IF(AND(K48<>"",K48=Q48),"⚠ Origen igual a destino",IF(AND(K48<>"",ISNA(MATCH(K48,ctaNombre,0))),"⚠ Destino no registrado",IF(AND(P48="Pago tarjeta",AE48<>"Tarjeta de crédito"),"⚠ El destino debe ser tarjeta de crédito",IF(AND(P48="Gasto",E48="Depósitos y retiros"),"⚠ Usa tipo Transferencia",IF(AND(P48="Resultado trading",AD48<>"Cuenta de trading"),"⚠ Usa una cuenta de trading",IF(AND(G48<=0,P48<>"Ajuste",P48<>"Resultado trading"),"⚠ El monto debe ser positivo","✓"))))))))))))))) | P48: =IF(OR(B48="",G48=""),"",IF(C48="","Gasto",C48)) | Q48: =IF(P48="","",IF(J48<>"",J48,CuentaPred&"")) | R48: =IF(P48="","",IF(ISNUMBER(I48),I48,TasaUSD)) | S48: =IF(P48="","",IF(H48="USD",G48*R48,G48)) | T48: =IF(P48="","",IF(H48="USD",G48,IF(R48>0,G48/R48,0))) | U48: =IF(P48="","",IF(P48="Gasto",S48,IF(P48="Reembolso",-S48,0))) | V48: =IF(P48="","",IF(P48="Ingreso",S48,0)) | W48: =IF(P48="","",IF(P48="Resultado trading",S48,0)) | X48: =IF(OR(P48="Gasto",P48="Reembolso"),IF(M48<>"",M48,IFERROR(INDEX(catClasif,MATCH(D48&"|"&E48,catClave,0))&"","Variable")),"") | Y48: =IF(P48="","",IFERROR(INDEX(catGrupo,MATCH(D48&"|"&E48,catClave,0))&"","")) | Z48: =IF(P48="","",WEEKDAY(B48,2)) | AA48: =IF(P48="","",IF(AND(P48="Gasto",X48="Variable",D48<>catTrading,S48>0,S48<=Umbral),1,0)) | AB48: =IF(OR(P48="",Q48=""),"",IFERROR(IF(INDEX(ctaVinc,MATCH(Q48,ctaNombre,0))&""<>"",INDEX(ctaVinc,MATCH(Q48,ctaNombre,0))&"",Q48),Q48)) | AC48: =IF(OR(K48="",AND(P48<>"Transferencia",P48<>"Pago tarjeta")),"",IFERROR(IF(INDEX(ctaVinc,MATCH(K48,ctaNombre,0))&""<>"",INDEX(ctaVinc,MATCH(K48,ctaNombre,0))&"",K48),K48)) | AD48: =IF(AB48="","",IFERROR(INDEX(ctaTipo,MATCH(AB48,ctaNombre,0))&"","")) | AE48: =IF(AC48="","",IFERROR(INDEX(ctaTipo,MATCH(AC48,ctaNombre,0))&"","")) | AF48: =IF(OR(P48="",AB48=""),"",IF(OR(P48="Gasto",P48="Transferencia",P48="Pago tarjeta"),-1,1)*IF(IFERROR(INDEX(ctaMoneda,MATCH(AB48,ctaNombre,0))&"","DOP")="USD",T48,S48)) | AG48: =IF(AC48="","",IF(IFERROR(INDEX(ctaMoneda,MATCH(AC48,ctaNombre,0))&"","DOP")="USD",T48,S48)) | AH48: =IF(P48="","",IF(AND(AD48<>"",COUNTIFS(tcTipo,AD48,tcLiq,"Sí")>0),IF(OR(P48="Gasto",P48="Transferencia",P48="Pago tarjeta"),-1,1)*S48,0)+IF(AND(AE48<>"",COUNTIFS(tcTipo,AE48,tcLiq,"Sí")>0),S48,0)) | AI48: =IF(OR(L48="",P48=""),"",IF(COUNTIFS(L$6:L48,L48,P$6:P48,"?*")=1,MAX(AI$5:AI47)+1,""))
B49: 46254 | C49: Resultado trading | D49: Trading y actividades financieras | E49: Ganancias y pérdidas realizadas | F49: DEMO · Pérdida realizada | G49: -85 | H49: USD | J49: Cuenta de trading | N49: DEMOSTRACIÓN | O49: =IF(AND(B49="",G49="",C49="",D49="",J49=""),"",IF(B49="","⚠ Falta fecha",IF(G49="","⚠ Falta monto",IF(Q49="","⚠ Falta cuenta",IF(ISNA(MATCH(Q49,ctaNombre,0)),"⚠ Cuenta no registrada",IF(AND(OR(P49="Gasto",P49="Reembolso"),D49=""),"⚠ Falta categoría",IF(AND(D49<>"",E49<>"",ISNA(MATCH(D49&"|"&E49,catClave,0))),"⚠ Subcategoría no corresponde",IF(AND(OR(P49="Transferencia",P49="Pago tarjeta"),K49=""),"⚠ Falta cuenta destino",IF(AND(K49<>"",P49<>"Transferencia",P49<>"Pago tarjeta"),"⚠ Destino solo aplica a transferencias",IF(AND(K49<>"",K49=Q49),"⚠ Origen igual a destino",IF(AND(K49<>"",ISNA(MATCH(K49,ctaNombre,0))),"⚠ Destino no registrado",IF(AND(P49="Pago tarjeta",AE49<>"Tarjeta de crédito"),"⚠ El destino debe ser tarjeta de crédito",IF(AND(P49="Gasto",E49="Depósitos y retiros"),"⚠ Usa tipo Transferencia",IF(AND(P49="Resultado trading",AD49<>"Cuenta de trading"),"⚠ Usa una cuenta de trading",IF(AND(G49<=0,P49<>"Ajuste",P49<>"Resultado trading"),"⚠ El monto debe ser positivo","✓"))))))))))))))) | P49: =IF(OR(B49="",G49=""),"",IF(C49="","Gasto",C49)) | Q49: =IF(P49="","",IF(J49<>"",J49,CuentaPred&"")) | R49: =IF(P49="","",IF(ISNUMBER(I49),I49,TasaUSD)) | S49: =IF(P49="","",IF(H49="USD",G49*R49,G49)) | T49: =IF(P49="","",IF(H49="USD",G49,IF(R49>0,G49/R49,0))) | U49: =IF(P49="","",IF(P49="Gasto",S49,IF(P49="Reembolso",-S49,0))) | V49: =IF(P49="","",IF(P49="Ingreso",S49,0)) | W49: =IF(P49="","",IF(P49="Resultado trading",S49,0)) | X49: =IF(OR(P49="Gasto",P49="Reembolso"),IF(M49<>"",M49,IFERROR(INDEX(catClasif,MATCH(D49&"|"&E49,catClave,0))&"","Variable")),"") | Y49: =IF(P49="","",IFERROR(INDEX(catGrupo,MATCH(D49&"|"&E49,catClave,0))&"","")) | Z49: =IF(P49="","",WEEKDAY(B49,2)) | AA49: =IF(P49="","",IF(AND(P49="Gasto",X49="Variable",D49<>catTrading,S49>0,S49<=Umbral),1,0)) | AB49: =IF(OR(P49="",Q49=""),"",IFERROR(IF(INDEX(ctaVinc,MATCH(Q49,ctaNombre,0))&""<>"",INDEX(ctaVinc,MATCH(Q49,ctaNombre,0))&"",Q49),Q49)) | AC49: =IF(OR(K49="",AND(P49<>"Transferencia",P49<>"Pago tarjeta")),"",IFERROR(IF(INDEX(ctaVinc,MATCH(K49,ctaNombre,0))&""<>"",INDEX(ctaVinc,MATCH(K49,ctaNombre,0))&"",K49),K49)) | AD49: =IF(AB49="","",IFERROR(INDEX(ctaTipo,MATCH(AB49,ctaNombre,0))&"","")) | AE49: =IF(AC49="","",IFERROR(INDEX(ctaTipo,MATCH(AC49,ctaNombre,0))&"","")) | AF49: =IF(OR(P49="",AB49=""),"",IF(OR(P49="Gasto",P49="Transferencia",P49="Pago tarjeta"),-1,1)*IF(IFERROR(INDEX(ctaMoneda,MATCH(AB49,ctaNombre,0))&"","DOP")="USD",T49,S49)) | AG49: =IF(AC49="","",IF(IFERROR(INDEX(ctaMoneda,MATCH(AC49,ctaNombre,0))&"","DOP")="USD",T49,S49)) | AH49: =IF(P49="","",IF(AND(AD49<>"",COUNTIFS(tcTipo,AD49,tcLiq,"Sí")>0),IF(OR(P49="Gasto",P49="Transferencia",P49="Pago tarjeta"),-1,1)*S49,0)+IF(AND(AE49<>"",COUNTIFS(tcTipo,AE49,tcLiq,"Sí")>0),S49,0)) | AI49: =IF(OR(L49="",P49=""),"",IF(COUNTIFS(L$6:L49,L49,P$6:P49,"?*")=1,MAX(AI$5:AI48)+1,""))
B50: 46254 | C50: Gasto | D50: Trading y actividades financieras | E50: Comisiones | F50: DEMO · Comisiones del broker | G50: 4.5 | H50: USD | J50: Cuenta de trading | L50: Broker | N50: DEMOSTRACIÓN | O50: =IF(AND(B50="",G50="",C50="",D50="",J50=""),"",IF(B50="","⚠ Falta fecha",IF(G50="","⚠ Falta monto",IF(Q50="","⚠ Falta cuenta",IF(ISNA(MATCH(Q50,ctaNombre,0)),"⚠ Cuenta no registrada",IF(AND(OR(P50="Gasto",P50="Reembolso"),D50=""),"⚠ Falta categoría",IF(AND(D50<>"",E50<>"",ISNA(MATCH(D50&"|"&E50,catClave,0))),"⚠ Subcategoría no corresponde",IF(AND(OR(P50="Transferencia",P50="Pago tarjeta"),K50=""),"⚠ Falta cuenta destino",IF(AND(K50<>"",P50<>"Transferencia",P50<>"Pago tarjeta"),"⚠ Destino solo aplica a transferencias",IF(AND(K50<>"",K50=Q50),"⚠ Origen igual a destino",IF(AND(K50<>"",ISNA(MATCH(K50,ctaNombre,0))),"⚠ Destino no registrado",IF(AND(P50="Pago tarjeta",AE50<>"Tarjeta de crédito"),"⚠ El destino debe ser tarjeta de crédito",IF(AND(P50="Gasto",E50="Depósitos y retiros"),"⚠ Usa tipo Transferencia",IF(AND(P50="Resultado trading",AD50<>"Cuenta de trading"),"⚠ Usa una cuenta de trading",IF(AND(G50<=0,P50<>"Ajuste",P50<>"Resultado trading"),"⚠ El monto debe ser positivo","✓"))))))))))))))) | P50: =IF(OR(B50="",G50=""),"",IF(C50="","Gasto",C50)) | Q50: =IF(P50="","",IF(J50<>"",J50,CuentaPred&"")) | R50: =IF(P50="","",IF(ISNUMBER(I50),I50,TasaUSD)) | S50: =IF(P50="","",IF(H50="USD",G50*R50,G50)) | T50: =IF(P50="","",IF(H50="USD",G50,IF(R50>0,G50/R50,0))) | U50: =IF(P50="","",IF(P50="Gasto",S50,IF(P50="Reembolso",-S50,0))) | V50: =IF(P50="","",IF(P50="Ingreso",S50,0)) | W50: =IF(P50="","",IF(P50="Resultado trading",S50,0)) | X50: =IF(OR(P50="Gasto",P50="Reembolso"),IF(M50<>"",M50,IFERROR(INDEX(catClasif,MATCH(D50&"|"&E50,catClave,0))&"","Variable")),"") | Y50: =IF(P50="","",IFERROR(INDEX(catGrupo,MATCH(D50&"|"&E50,catClave,0))&"","")) | Z50: =IF(P50="","",WEEKDAY(B50,2)) | AA50: =IF(P50="","",IF(AND(P50="Gasto",X50="Variable",D50<>catTrading,S50>0,S50<=Umbral),1,0)) | AB50: =IF(OR(P50="",Q50=""),"",IFERROR(IF(INDEX(ctaVinc,MATCH(Q50,ctaNombre,0))&""<>"",INDEX(ctaVinc,MATCH(Q50,ctaNombre,0))&"",Q50),Q50)) | AC50: =IF(OR(K50="",AND(P50<>"Transferencia",P50<>"Pago tarjeta")),"",IFERROR(IF(INDEX(ctaVinc,MATCH(K50,ctaNombre,0))&""<>"",INDEX(ctaVinc,MATCH(K50,ctaNombre,0))&"",K50),K50)) | AD50: =IF(AB50="","",IFERROR(INDEX(ctaTipo,MATCH(AB50,ctaNombre,0))&"","")) | AE50: =IF(AC50="","",IFERROR(INDEX(ctaTipo,MATCH(AC50,ctaNombre,0))&"","")) | AF50: =IF(OR(P50="",AB50=""),"",IF(OR(P50="Gasto",P50="Transferencia",P50="Pago tarjeta"),-1,1)*IF(IFERROR(INDEX(ctaMoneda,MATCH(AB50,ctaNombre,0))&"","DOP")="USD",T50,S50)) | AG50: =IF(AC50="","",IF(IFERROR(INDEX(ctaMoneda,MATCH(AC50,ctaNombre,0))&"","DOP")="USD",T50,S50)) | AH50: =IF(P50="","",IF(AND(AD50<>"",COUNTIFS(tcTipo,AD50,tcLiq,"Sí")>0),IF(OR(P50="Gasto",P50="Transferencia",P50="Pago tarjeta"),-1,1)*S50,0)+IF(AND(AE50<>"",COUNTIFS(tcTipo,AE50,tcLiq,"Sí")>0),S50,0)) | AI50: =IF(OR(L50="",P50=""),"",IF(COUNTIFS(L$6:L50,L50,P$6:P50,"?*")=1,MAX(AI$5:AI49)+1,""))
B51: 46255 | C51: Gasto | D51: Alimentación | E51: Desayunos comprados | F51: DEMO · Desayuno en la oficina | G51: 280 | H51: DOP | J51: Efectivo | L51: Cafetería del trabajo | N51: DEMOSTRACIÓN | O51: =IF(AND(B51="",G51="",C51="",D51="",J51=""),"",IF(B51="","⚠ Falta fecha",IF(G51="","⚠ Falta monto",IF(Q51="","⚠ Falta cuenta",IF(ISNA(MATCH(Q51,ctaNombre,0)),"⚠ Cuenta no registrada",IF(AND(OR(P51="Gasto",P51="Reembolso"),D51=""),"⚠ Falta categoría",IF(AND(D51<>"",E51<>"",ISNA(MATCH(D51&"|"&E51,catClave,0))),"⚠ Subcategoría no corresponde",IF(AND(OR(P51="Transferencia",P51="Pago tarjeta"),K51=""),"⚠ Falta cuenta destino",IF(AND(K51<>"",P51<>"Transferencia",P51<>"Pago tarjeta"),"⚠ Destino solo aplica a transferencias",IF(AND(K51<>"",K51=Q51),"⚠ Origen igual a destino",IF(AND(K51<>"",ISNA(MATCH(K51,ctaNombre,0))),"⚠ Destino no registrado",IF(AND(P51="Pago tarjeta",AE51<>"Tarjeta de crédito"),"⚠ El destino debe ser tarjeta de crédito",IF(AND(P51="Gasto",E51="Depósitos y retiros"),"⚠ Usa tipo Transferencia",IF(AND(P51="Resultado trading",AD51<>"Cuenta de trading"),"⚠ Usa una cuenta de trading",IF(AND(G51<=0,P51<>"Ajuste",P51<>"Resultado trading"),"⚠ El monto debe ser positivo","✓"))))))))))))))) | P51: =IF(OR(B51="",G51=""),"",IF(C51="","Gasto",C51)) | Q51: =IF(P51="","",IF(J51<>"",J51,CuentaPred&"")) | R51: =IF(P51="","",IF(ISNUMBER(I51),I51,TasaUSD)) | S51: =IF(P51="","",IF(H51="USD",G51*R51,G51)) | T51: =IF(P51="","",IF(H51="USD",G51,IF(R51>0,G51/R51,0))) | U51: =IF(P51="","",IF(P51="Gasto",S51,IF(P51="Reembolso",-S51,0))) | V51: =IF(P51="","",IF(P51="Ingreso",S51,0)) | W51: =IF(P51="","",IF(P51="Resultado trading",S51,0)) | X51: =IF(OR(P51="Gasto",P51="Reembolso"),IF(M51<>"",M51,IFERROR(INDEX(catClasif,MATCH(D51&"|"&E51,catClave,0))&"","Variable")),"") | Y51: =IF(P51="","",IFERROR(INDEX(catGrupo,MATCH(D51&"|"&E51,catClave,0))&"","")) | Z51: =IF(P51="","",WEEKDAY(B51,2)) | AA51: =IF(P51="","",IF(AND(P51="Gasto",X51="Variable",D51<>catTrading,S51>0,S51<=Umbral),1,0)) | AB51: =IF(OR(P51="",Q51=""),"",IFERROR(IF(INDEX(ctaVinc,MATCH(Q51,ctaNombre,0))&""<>"",INDEX(ctaVinc,MATCH(Q51,ctaNombre,0))&"",Q51),Q51)) | AC51: =IF(OR(K51="",AND(P51<>"Transferencia",P51<>"Pago tarjeta")),"",IFERROR(IF(INDEX(ctaVinc,MATCH(K51,ctaNombre,0))&""<>"",INDEX(ctaVinc,MATCH(K51,ctaNombre,0))&"",K51),K51)) | AD51: =IF(AB51="","",IFERROR(INDEX(ctaTipo,MATCH(AB51,ctaNombre,0))&"","")) | AE51: =IF(AC51="","",IFERROR(INDEX(ctaTipo,MATCH(AC51,ctaNombre,0))&"","")) | AF51: =IF(OR(P51="",AB51=""),"",IF(OR(P51="Gasto",P51="Transferencia",P51="Pago tarjeta"),-1,1)*IF(IFERROR(INDEX(ctaMoneda,MATCH(AB51,ctaNombre,0))&"","DOP")="USD",T51,S51)) | AG51: =IF(AC51="","",IF(IFERROR(INDEX(ctaMoneda,MATCH(AC51,ctaNombre,0))&"","DOP")="USD",T51,S51)) | AH51: =IF(P51="","",IF(AND(AD51<>"",COUNTIFS(tcTipo,AD51,tcLiq,"Sí")>0),IF(OR(P51="Gasto",P51="Transferencia",P51="Pago tarjeta"),-1,1)*S51,0)+IF(AND(AE51<>"",COUNTIFS(tcTipo,AE51,tcLiq,"Sí")>0),S51,0)) | AI51: =IF(OR(L51="",P51=""),"",IF(COUNTIFS(L$6:L51,L51,P$6:P51,"?*")=1,MAX(AI$5:AI50)+1,""))
B52: 46255 | C52: Gasto | D52: Alimentación | E52: Almuerzos laborales | F52: DEMO · Almuerzo laboral | G52: 400 | H52: DOP | J52: Tarjeta de débito | L52: Comedor ejecutivo | N52: DEMOSTRACIÓN | O52: =IF(AND(B52="",G52="",C52="",D52="",J52=""),"",IF(B52="","⚠ Falta fecha",IF(G52="","⚠ Falta monto",IF(Q52="","⚠ Falta cuenta",IF(ISNA(MATCH(Q52,ctaNombre,0)),"⚠ Cuenta no registrada",IF(AND(OR(P52="Gasto",P52="Reembolso"),D52=""),"⚠ Falta categoría",IF(AND(D52<>"",E52<>"",ISNA(MATCH(D52&"|"&E52,catClave,0))),"⚠ Subcategoría no corresponde",IF(AND(OR(P52="Transferencia",P52="Pago tarjeta"),K52=""),"⚠ Falta cuenta destino",IF(AND(K52<>"",P52<>"Transferencia",P52<>"Pago tarjeta"),"⚠ Destino solo aplica a transferencias",IF(AND(K52<>"",K52=Q52),"⚠ Origen igual a destino",IF(AND(K52<>"",ISNA(MATCH(K52,ctaNombre,0))),"⚠ Destino no registrado",IF(AND(P52="Pago tarjeta",AE52<>"Tarjeta de crédito"),"⚠ El destino debe ser tarjeta de crédito",IF(AND(P52="Gasto",E52="Depósitos y retiros"),"⚠ Usa tipo Transferencia",IF(AND(P52="Resultado trading",AD52<>"Cuenta de trading"),"⚠ Usa una cuenta de trading",IF(AND(G52<=0,P52<>"Ajuste",P52<>"Resultado trading"),"⚠ El monto debe ser positivo","✓"))))))))))))))) | P52: =IF(OR(B52="",G52=""),"",IF(C52="","Gasto",C52)) | Q52: =IF(P52="","",IF(J52<>"",J52,CuentaPred&"")) | R52: =IF(P52="","",IF(ISNUMBER(I52),I52,TasaUSD)) | S52: =IF(P52="","",IF(H52="USD",G52*R52,G52)) | T52: =IF(P52="","",IF(H52="USD",G52,IF(R52>0,G52/R52,0))) | U52: =IF(P52="","",IF(P52="Gasto",S52,IF(P52="Reembolso",-S52,0))) | V52: =IF(P52="","",IF(P52="Ingreso",S52,0)) | W52: =IF(P52="","",IF(P52="Resultado trading",S52,0)) | X52: =IF(OR(P52="Gasto",P52="Reembolso"),IF(M52<>"",M52,IFERROR(INDEX(catClasif,MATCH(D52&"|"&E52,catClave,0))&"","Variable")),"") | Y52: =IF(P52="","",IFERROR(INDEX(catGrupo,MATCH(D52&"|"&E52,catClave,0))&"","")) | Z52: =IF(P52="","",WEEKDAY(B52,2)) | AA52: =IF(P52="","",IF(AND(P52="Gasto",X52="Variable",D52<>catTrading,S52>0,S52<=Umbral),1,0)) | AB52: =IF(OR(P52="",Q52=""),"",IFERROR(IF(INDEX(ctaVinc,MATCH(Q52,ctaNombre,0))&""<>"",INDEX(ctaVinc,MATCH(Q52,ctaNombre,0))&"",Q52),Q52)) | AC52: =IF(OR(K52="",AND(P52<>"Transferencia",P52<>"Pago tarjeta")),"",IFERROR(IF(INDEX(ctaVinc,MATCH(K52,ctaNombre,0))&""<>"",INDEX(ctaVinc,MATCH(K52,ctaNombre,0))&"",K52),K52)) | AD52: =IF(AB52="","",IFERROR(INDEX(ctaTipo,MATCH(AB52,ctaNombre,0))&"","")) | AE52: =IF(AC52="","",IFERROR(INDEX(ctaTipo,MATCH(AC52,ctaNombre,0))&"","")) | AF52: =IF(OR(P52="",AB52=""),"",IF(OR(P52="Gasto",P52="Transferencia",P52="Pago tarjeta"),-1,1)*IF(IFERROR(INDEX(ctaMoneda,MATCH(AB52,ctaNombre,0))&"","DOP")="USD",T52,S52)) | AG52: =IF(AC52="","",IF(IFERROR(INDEX(ctaMoneda,MATCH(AC52,ctaNombre,0))&"","DOP")="USD",T52,S52)) | AH52: =IF(P52="","",IF(AND(AD52<>"",COUNTIFS(tcTipo,AD52,tcLiq,"Sí")>0),IF(OR(P52="Gasto",P52="Transferencia",P52="Pago tarjeta"),-1,1)*S52,0)+IF(AND(AE52<>"",COUNTIFS(tcTipo,AE52,tcLiq,"Sí")>0),S52,0)) | AI52: =IF(OR(L52="",P52=""),"",IF(COUNTIFS(L$6:L52,L52,P$6:P52,"?*")=1,MAX(AI$5:AI51)+1,""))
B53: 46255 | C53: Gasto | D53: Alimentación | E53: Bebidas, snacks y otros consumos | F53: DEMO · Jugo y galletas | G53: 110 | H53: DOP | J53: Billetera digital | L53: Cafetería del trabajo | N53: DEMOSTRACIÓN | O53: =IF(AND(B53="",G53="",C53="",D53="",J53=""),"",IF(B53="","⚠ Falta fecha",IF(G53="","⚠ Falta monto",IF(Q53="","⚠ Falta cuenta",IF(ISNA(MATCH(Q53,ctaNombre,0)),"⚠ Cuenta no registrada",IF(AND(OR(P53="Gasto",P53="Reembolso"),D53=""),"⚠ Falta categoría",IF(AND(D53<>"",E53<>"",ISNA(MATCH(D53&"|"&E53,catClave,0))),"⚠ Subcategoría no corresponde",IF(AND(OR(P53="Transferencia",P53="Pago tarjeta"),K53=""),"⚠ Falta cuenta destino",IF(AND(K53<>"",P53<>"Transferencia",P53<>"Pago tarjeta"),"⚠ Destino solo aplica a transferencias",IF(AND(K53<>"",K53=Q53),"⚠ Origen igual a destino",IF(AND(K53<>"",ISNA(MATCH(K53,ctaNombre,0))),"⚠ Destino no registrado",IF(AND(P53="Pago tarjeta",AE53<>"Tarjeta de crédito"),"⚠ El destino debe ser tarjeta de crédito",IF(AND(P53="Gasto",E53="Depósitos y retiros"),"⚠ Usa tipo Transferencia",IF(AND(P53="Resultado trading",AD53<>"Cuenta de trading"),"⚠ Usa una cuenta de trading",IF(AND(G53<=0,P53<>"Ajuste",P53<>"Resultado trading"),"⚠ El monto debe ser positivo","✓"))))))))))))))) | P53: =IF(OR(B53="",G53=""),"",IF(C53="","Gasto",C53)) | Q53: =IF(P53="","",IF(J53<>"",J53,CuentaPred&"")) | R53: =IF(P53="","",IF(ISNUMBER(I53),I53,TasaUSD)) | S53: =IF(P53="","",IF(H53="USD",G53*R53,G53)) | T53: =IF(P53="","",IF(H53="USD",G53,IF(R53>0,G53/R53,0))) | U53: =IF(P53="","",IF(P53="Gasto",S53,IF(P53="Reembolso",-S53,0))) | V53: =IF(P53="","",IF(P53="Ingreso",S53,0)) | W53: =IF(P53="","",IF(P53="Resultado trading",S53,0)) | X53: =IF(OR(P53="Gasto",P53="Reembolso"),IF(M53<>"",M53,IFERROR(INDEX(catClasif,MATCH(D53&"|"&E53,catClave,0))&"","Variable")),"") | Y53: =IF(P53="","",IFERROR(INDEX(catGrupo,MATCH(D53&"|"&E53,catClave,0))&"","")) | Z53: =IF(P53="","",WEEKDAY(B53,2)) | AA53: =IF(P53="","",IF(AND(P53="Gasto",X53="Variable",D53<>catTrading,S53>0,S53<=Umbral),1,0)) | AB53: =IF(OR(P53="",Q53=""),"",IFERROR(IF(INDEX(ctaVinc,MATCH(Q53,ctaNombre,0))&""<>"",INDEX(ctaVinc,MATCH(Q53,ctaNombre,0))&"",Q53),Q53)) | AC53: =IF(OR(K53="",AND(P53<>"Transferencia",P53<>"Pago tarjeta")),"",IFERROR(IF(INDEX(ctaVinc,MATCH(K53,ctaNombre,0))&""<>"",INDEX(ctaVinc,MATCH(K53,ctaNombre,0))&"",K53),K53)) | AD53: =IF(AB53="","",IFERROR(INDEX(ctaTipo,MATCH(AB53,ctaNombre,0))&"","")) | AE53: =IF(AC53="","",IFERROR(INDEX(ctaTipo,MATCH(AC53,ctaNombre,0))&"","")) | AF53: =IF(OR(P53="",AB53=""),"",IF(OR(P53="Gasto",P53="Transferencia",P53="Pago tarjeta"),-1,1)*IF(IFERROR(INDEX(ctaMoneda,MATCH(AB53,ctaNombre,0))&"","DOP")="USD",T53,S53)) | AG53: =IF(AC53="","",IF(IFERROR(INDEX(ctaMoneda,MATCH(AC53,ctaNombre,0))&"","DOP")="USD",T53,S53)) | AH53: =IF(P53="","",IF(AND(AD53<>"",COUNTIFS(tcTipo,AD53,tcLiq,"Sí")>0),IF(OR(P53="Gasto",P53="Transferencia",P53="Pago tarjeta"),-1,1)*S53,0)+IF(AND(AE53<>"",COUNTIFS(tcTipo,AE53,tcLiq,"Sí")>0),S53,0)) | AI53: =IF(OR(L53="",P53=""),"",IF(COUNTIFS(L$6:L53,L53,P$6:P53,"?*")=1,MAX(AI$5:AI52)+1,""))
B54: 46255 | C54: Gasto | D54: Alimentación | E54: Delivery | F54: DEMO · Pedido a domicilio | G54: 750 | H54: DOP | J54: Tarjeta de crédito | L54: App de delivery | N54: DEMOSTRACIÓN | O54: =IF(AND(B54="",G54="",C54="",D54="",J54=""),"",IF(B54="","⚠ Falta fecha",IF(G54="","⚠ Falta monto",IF(Q54="","⚠ Falta cuenta",IF(ISNA(MATCH(Q54,ctaNombre,0)),"⚠ Cuenta no registrada",IF(AND(OR(P54="Gasto",P54="Reembolso"),D54=""),"⚠ Falta categoría",IF(AND(D54<>"",E54<>"",ISNA(MATCH(D54&"|"&E54,catClave,0))),"⚠ Subcategoría no corresponde",IF(AND(OR(P54="Transferencia",P54="Pago tarjeta"),K54=""),"⚠ Falta cuenta destino",IF(AND(K54<>"",P54<>"Transferencia",P54<>"Pago tarjeta"),"⚠ Destino solo aplica a transferencias",IF(AND(K54<>"",K54=Q54),"⚠ Origen igual a destino",IF(AND(K54<>"",ISNA(MATCH(K54,ctaNombre,0))),"⚠ Destino no registrado",IF(AND(P54="Pago tarjeta",AE54<>"Tarjeta de crédito"),"⚠ El destino debe ser tarjeta de crédito",IF(AND(P54="Gasto",E54="Depósitos y retiros"),"⚠ Usa tipo Transferencia",IF(AND(P54="Resultado trading",AD54<>"Cuenta de trading"),"⚠ Usa una cuenta de trading",IF(AND(G54<=0,P54<>"Ajuste",P54<>"Resultado trading"),"⚠ El monto debe ser positivo","✓"))))))))))))))) | P54: =IF(OR(B54="",G54=""),"",IF(C54="","Gasto",C54)) | Q54: =IF(P54="","",IF(J54<>"",J54,CuentaPred&"")) | R54: =IF(P54="","",IF(ISNUMBER(I54),I54,TasaUSD)) | S54: =IF(P54="","",IF(H54="USD",G54*R54,G54)) | T54: =IF(P54="","",IF(H54="USD",G54,IF(R54>0,G54/R54,0))) | U54: =IF(P54="","",IF(P54="Gasto",S54,IF(P54="Reembolso",-S54,0))) | V54: =IF(P54="","",IF(P54="Ingreso",S54,0)) | W54: =IF(P54="","",IF(P54="Resultado trading",S54,0)) | X54: =IF(OR(P54="Gasto",P54="Reembolso"),IF(M54<>"",M54,IFERROR(INDEX(catClasif,MATCH(D54&"|"&E54,catClave,0))&"","Variable")),"") | Y54: =IF(P54="","",IFERROR(INDEX(catGrupo,MATCH(D54&"|"&E54,catClave,0))&"","")) | Z54: =IF(P54="","",WEEKDAY(B54,2)) | AA54: =IF(P54="","",IF(AND(P54="Gasto",X54="Variable",D54<>catTrading,S54>0,S54<=Umbral),1,0)) | AB54: =IF(OR(P54="",Q54=""),"",IFERROR(IF(INDEX(ctaVinc,MATCH(Q54,ctaNombre,0))&""<>"",INDEX(ctaVinc,MATCH(Q54,ctaNombre,0))&"",Q54),Q54)) | AC54: =IF(OR(K54="",AND(P54<>"Transferencia",P54<>"Pago tarjeta")),"",IFERROR(IF(INDEX(ctaVinc,MATCH(K54,ctaNombre,0))&""<>"",INDEX(ctaVinc,MATCH(K54,ctaNombre,0))&"",K54),K54)) | AD54: =IF(AB54="","",IFERROR(INDEX(ctaTipo,MATCH(AB54,ctaNombre,0))&"","")) | AE54: =IF(AC54="","",IFERROR(INDEX(ctaTipo,MATCH(AC54,ctaNombre,0))&"","")) | AF54: =IF(OR(P54="",AB54=""),"",IF(OR(P54="Gasto",P54="Transferencia",P54="Pago tarjeta"),-1,1)*IF(IFERROR(INDEX(ctaMoneda,MATCH(AB54,ctaNombre,0))&"","DOP")="USD",T54,S54)) | AG54: =IF(AC54="","",IF(IFERROR(INDEX(ctaMoneda,MATCH(AC54,ctaNombre,0))&"","DOP")="USD",T54,S54)) | AH54: =IF(P54="","",IF(AND(AD54<>"",COUNTIFS(tcTipo,AD54,tcLiq,"Sí")>0),IF(OR(P54="Gasto",P54="Transferencia",P54="Pago tarjeta"),-1,1)*S54,0)+IF(AND(AE54<>"",COUNTIFS(tcTipo,AE54,tcLiq,"Sí")>0),S54,0)) | AI54: =IF(OR(L54="",P54=""),"",IF(COUNTIFS(L$6:L54,L54,P$6:P54,"?*")=1,MAX(AI$5:AI53)+1,""))
B55: 46255 | C55: Gasto | D55: Trading y actividades financieras | E55: Plataformas y herramientas | F55: DEMO · Plataforma de gráficos | G55: 39 | H55: USD | J55: Tarjeta de crédito | L55: Plataforma de trading | N55: DEMOSTRACIÓN | O55: =IF(AND(B55="",G55="",C55="",D55="",J55=""),"",IF(B55="","⚠ Falta fecha",IF(G55="","⚠ Falta monto",IF(Q55="","⚠ Falta cuenta",IF(ISNA(MATCH(Q55,ctaNombre,0)),"⚠ Cuenta no registrada",IF(AND(OR(P55="Gasto",P55="Reembolso"),D55=""),"⚠ Falta categoría",IF(AND(D55<>"",E55<>"",ISNA(MATCH(D55&"|"&E55,catClave,0))),"⚠ Subcategoría no corresponde",IF(AND(OR(P55="Transferencia",P55="Pago tarjeta"),K55=""),"⚠ Falta cuenta destino",IF(AND(K55<>"",P55<>"Transferencia",P55<>"Pago tarjeta"),"⚠ Destino solo aplica a transferencias",IF(AND(K55<>"",K55=Q55),"⚠ Origen igual a destino",IF(AND(K55<>"",ISNA(MATCH(K55,ctaNombre,0))),"⚠ Destino no registrado",IF(AND(P55="Pago tarjeta",AE55<>"Tarjeta de crédito"),"⚠ El destino debe ser tarjeta de crédito",IF(AND(P55="Gasto",E55="Depósitos y retiros"),"⚠ Usa tipo Transferencia",IF(AND(P55="Resultado trading",AD55<>"Cuenta de trading"),"⚠ Usa una cuenta de trading",IF(AND(G55<=0,P55<>"Ajuste",P55<>"Resultado trading"),"⚠ El monto debe ser positivo","✓"))))))))))))))) | P55: =IF(OR(B55="",G55=""),"",IF(C55="","Gasto",C55)) | Q55: =IF(P55="","",IF(J55<>"",J55,CuentaPred&"")) | R55: =IF(P55="","",IF(ISNUMBER(I55),I55,TasaUSD)) | S55: =IF(P55="","",IF(H55="USD",G55*R55,G55)) | T55: =IF(P55="","",IF(H55="USD",G55,IF(R55>0,G55/R55,0))) | U55: =IF(P55="","",IF(P55="Gasto",S55,IF(P55="Reembolso",-S55,0))) | V55: =IF(P55="","",IF(P55="Ingreso",S55,0)) | W55: =IF(P55="","",IF(P55="Resultado trading",S55,0)) | X55: =IF(OR(P55="Gasto",P55="Reembolso"),IF(M55<>"",M55,IFERROR(INDEX(catClasif,MATCH(D55&"|"&E55,catClave,0))&"","Variable")),"") | Y55: =IF(P55="","",IFERROR(INDEX(catGrupo,MATCH(D55&"|"&E55,catClave,0))&"","")) | Z55: =IF(P55="","",WEEKDAY(B55,2)) | AA55: =IF(P55="","",IF(AND(P55="Gasto",X55="Variable",D55<>catTrading,S55>0,S55<=Umbral),1,0)) | AB55: =IF(OR(P55="",Q55=""),"",IFERROR(IF(INDEX(ctaVinc,MATCH(Q55,ctaNombre,0))&""<>"",INDEX(ctaVinc,MATCH(Q55,ctaNombre,0))&"",Q55),Q55)) | AC55: =IF(OR(K55="",AND(P55<>"Transferencia",P55<>"Pago tarjeta")),"",IFERROR(IF(INDEX(ctaVinc,MATCH(K55,ctaNombre,0))&""<>"",INDEX(ctaVinc,MATCH(K55,ctaNombre,0))&"",K55),K55)) | AD55: =IF(AB55="","",IFERROR(INDEX(ctaTipo,MATCH(AB55,ctaNombre,0))&"","")) | AE55: =IF(AC55="","",IFERROR(INDEX(ctaTipo,MATCH(AC55,ctaNombre,0))&"","")) | AF55: =IF(OR(P55="",AB55=""),"",IF(OR(P55="Gasto",P55="Transferencia",P55="Pago tarjeta"),-1,1)*IF(IFERROR(INDEX(ctaMoneda,MATCH(AB55,ctaNombre,0))&"","DOP")="USD",T55,S55)) | AG55: =IF(AC55="","",IF(IFERROR(INDEX(ctaMoneda,MATCH(AC55,ctaNombre,0))&"","DOP")="USD",T55,S55)) | AH55: =IF(P55="","",IF(AND(AD55<>"",COUNTIFS(tcTipo,AD55,tcLiq,"Sí")>0),IF(OR(P55="Gasto",P55="Transferencia",P55="Pago tarjeta"),-1,1)*S55,0)+IF(AND(AE55<>"",COUNTIFS(tcTipo,AE55,tcLiq,"Sí")>0),S55,0)) | AI55: =IF(OR(L55="",P55=""),"",IF(COUNTIFS(L$6:L55,L55,P$6:P55,"?*")=1,MAX(AI$5:AI54)+1,""))
B56: 46256 | C56: Gasto | D56: Alimentación | E56: Restaurantes | F56: DEMO · Almuerzo de fin de semana | G56: 2700 | H56: DOP | J56: Tarjeta de crédito | L56: Restaurante del malecón | N56: DEMOSTRACIÓN | O56: =IF(AND(B56="",G56="",C56="",D56="",J56=""),"",IF(B56="","⚠ Falta fecha",IF(G56="","⚠ Falta monto",IF(Q56="","⚠ Falta cuenta",IF(ISNA(MATCH(Q56,ctaNombre,0)),"⚠ Cuenta no registrada",IF(AND(OR(P56="Gasto",P56="Reembolso"),D56=""),"⚠ Falta categoría",IF(AND(D56<>"",E56<>"",ISNA(MATCH(D56&"|"&E56,catClave,0))),"⚠ Subcategoría no corresponde",IF(AND(OR(P56="Transferencia",P56="Pago tarjeta"),K56=""),"⚠ Falta cuenta destino",IF(AND(K56<>"",P56<>"Transferencia",P56<>"Pago tarjeta"),"⚠ Destino solo aplica a transferencias",IF(AND(K56<>"",K56=Q56),"⚠ Origen igual a destino",IF(AND(K56<>"",ISNA(MATCH(K56,ctaNombre,0))),"⚠ Destino no registrado",IF(AND(P56="Pago tarjeta",AE56<>"Tarjeta de crédito"),"⚠ El destino debe ser tarjeta de crédito",IF(AND(P56="Gasto",E56="Depósitos y retiros"),"⚠ Usa tipo Transferencia",IF(AND(P56="Resultado trading",AD56<>"Cuenta de trading"),"⚠ Usa una cuenta de trading",IF(AND(G56<=0,P56<>"Ajuste",P56<>"Resultado trading"),"⚠ El monto debe ser positivo","✓"))))))))))))))) | P56: =IF(OR(B56="",G56=""),"",IF(C56="","Gasto",C56)) | Q56: =IF(P56="","",IF(J56<>"",J56,CuentaPred&"")) | R56: =IF(P56="","",IF(ISNUMBER(I56),I56,TasaUSD)) | S56: =IF(P56="","",IF(H56="USD",G56*R56,G56)) | T56: =IF(P56="","",IF(H56="USD",G56,IF(R56>0,G56/R56,0))) | U56: =IF(P56="","",IF(P56="Gasto",S56,IF(P56="Reembolso",-S56,0))) | V56: =IF(P56="","",IF(P56="Ingreso",S56,0)) | W56: =IF(P56="","",IF(P56="Resultado trading",S56,0)) | X56: =IF(OR(P56="Gasto",P56="Reembolso"),IF(M56<>"",M56,IFERROR(INDEX(catClasif,MATCH(D56&"|"&E56,catClave,0))&"","Variable")),"") | Y56: =IF(P56="","",IFERROR(INDEX(catGrupo,MATCH(D56&"|"&E56,catClave,0))&"","")) | Z56: =IF(P56="","",WEEKDAY(B56,2)) | AA56: =IF(P56="","",IF(AND(P56="Gasto",X56="Variable",D56<>catTrading,S56>0,S56<=Umbral),1,0)) | AB56: =IF(OR(P56="",Q56=""),"",IFERROR(IF(INDEX(ctaVinc,MATCH(Q56,ctaNombre,0))&""<>"",INDEX(ctaVinc,MATCH(Q56,ctaNombre,0))&"",Q56),Q56)) | AC56: =IF(OR(K56="",AND(P56<>"Transferencia",P56<>"Pago tarjeta")),"",IFERROR(IF(INDEX(ctaVinc,MATCH(K56,ctaNombre,0))&""<>"",INDEX(ctaVinc,MATCH(K56,ctaNombre,0))&"",K56),K56)) | AD56: =IF(AB56="","",IFERROR(INDEX(ctaTipo,MATCH(AB56,ctaNombre,0))&"","")) | AE56: =IF(AC56="","",IFERROR(INDEX(ctaTipo,MATCH(AC56,ctaNombre,0))&"","")) | AF56: =IF(OR(P56="",AB56=""),"",IF(OR(P56="Gasto",P56="Transferencia",P56="Pago tarjeta"),-1,1)*IF(IFERROR(INDEX(ctaMoneda,MATCH(AB56,ctaNombre,0))&"","DOP")="USD",T56,S56)) | AG56: =IF(AC56="","",IF(IFERROR(INDEX(ctaMoneda,MATCH(AC56,ctaNombre,0))&"","DOP")="USD",T56,S56)) | AH56: =IF(P56="","",IF(AND(AD56<>"",COUNTIFS(tcTipo,AD56,tcLiq,"Sí")>0),IF(OR(P56="Gasto",P56="Transferencia",P56="Pago tarjeta"),-1,1)*S56,0)+IF(AND(AE56<>"",COUNTIFS(tcTipo,AE56,tcLiq,"Sí")>0),S56,0)) | AI56: =IF(OR(L56="",P56=""),"",IF(COUNTIFS(L$6:L56,L56,P$6:P56,"?*")=1,MAX(AI$5:AI55)+1,""))
B57: 46256 | C57: Gasto | D57: Alimentación | E57: Supermercado | F57: DEMO · Compra de supermercado | G57: 6400 | H57: DOP | J57: Tarjeta de crédito | L57: Supermercado principal | N57: DEMOSTRACIÓN | O57: =IF(AND(B57="",G57="",C57="",D57="",J57=""),"",IF(B57="","⚠ Falta fecha",IF(G57="","⚠ Falta monto",IF(Q57="","⚠ Falta cuenta",IF(ISNA(MATCH(Q57,ctaNombre,0)),"⚠ Cuenta no registrada",IF(AND(OR(P57="Gasto",P57="Reembolso"),D57=""),"⚠ Falta categoría",IF(AND(D57<>"",E57<>"",ISNA(MATCH(D57&"|"&E57,catClave,0))),"⚠ Subcategoría no corresponde",IF(AND(OR(P57="Transferencia",P57="Pago tarjeta"),K57=""),"⚠ Falta cuenta destino",IF(AND(K57<>"",P57<>"Transferencia",P57<>"Pago tarjeta"),"⚠ Destino solo aplica a transferencias",IF(AND(K57<>"",K57=Q57),"⚠ Origen igual a destino",IF(AND(K57<>"",ISNA(MATCH(K57,ctaNombre,0))),"⚠ Destino no registrado",IF(AND(P57="Pago tarjeta",AE57<>"Tarjeta de crédito"),"⚠ El destino debe ser tarjeta de crédito",IF(AND(P57="Gasto",E57="Depósitos y retiros"),"⚠ Usa tipo Transferencia",IF(AND(P57="Resultado trading",AD57<>"Cuenta de trading"),"⚠ Usa una cuenta de trading",IF(AND(G57<=0,P57<>"Ajuste",P57<>"Resultado trading"),"⚠ El monto debe ser positivo","✓"))))))))))))))) | P57: =IF(OR(B57="",G57=""),"",IF(C57="","Gasto",C57)) | Q57: =IF(P57="","",IF(J57<>"",J57,CuentaPred&"")) | R57: =IF(P57="","",IF(ISNUMBER(I57),I57,TasaUSD)) | S57: =IF(P57="","",IF(H57="USD",G57*R57,G57)) | T57: =IF(P57="","",IF(H57="USD",G57,IF(R57>0,G57/R57,0))) | U57: =IF(P57="","",IF(P57="Gasto",S57,IF(P57="Reembolso",-S57,0))) | V57: =IF(P57="","",IF(P57="Ingreso",S57,0)) | W57: =IF(P57="","",IF(P57="Resultado trading",S57,0)) | X57: =IF(OR(P57="Gasto",P57="Reembolso"),IF(M57<>"",M57,IFERROR(INDEX(catClasif,MATCH(D57&"|"&E57,catClave,0))&"","Variable")),"") | Y57: =IF(P57="","",IFERROR(INDEX(catGrupo,MATCH(D57&"|"&E57,catClave,0))&"","")) | Z57: =IF(P57="","",WEEKDAY(B57,2)) | AA57: =IF(P57="","",IF(AND(P57="Gasto",X57="Variable",D57<>catTrading,S57>0,S57<=Umbral),1,0)) | AB57: =IF(OR(P57="",Q57=""),"",IFERROR(IF(INDEX(ctaVinc,MATCH(Q57,ctaNombre,0))&""<>"",INDEX(ctaVinc,MATCH(Q57,ctaNombre,0))&"",Q57),Q57)) | AC57: =IF(OR(K57="",AND(P57<>"Transferencia",P57<>"Pago tarjeta")),"",IFERROR(IF(INDEX(ctaVinc,MATCH(K57,ctaNombre,0))&""<>"",INDEX(ctaVinc,MATCH(K57,ctaNombre,0))&"",K57),K57)) | AD57: =IF(AB57="","",IFERROR(INDEX(ctaTipo,MATCH(AB57,ctaNombre,0))&"","")) | AE57: =IF(AC57="","",IFERROR(INDEX(ctaTipo,MATCH(AC57,ctaNombre,0))&"","")) | AF57: =IF(OR(P57="",AB57=""),"",IF(OR(P57="Gasto",P57="Transferencia",P57="Pago tarjeta"),-1,1)*IF(IFERROR(INDEX(ctaMoneda,MATCH(AB57,ctaNombre,0))&"","DOP")="USD",T57,S57)) | AG57: =IF(AC57="","",IF(IFERROR(INDEX(ctaMoneda,MATCH(AC57,ctaNombre,0))&"","DOP")="USD",T57,S57)) | AH57: =IF(P57="","",IF(AND(AD57<>"",COUNTIFS(tcTipo,AD57,tcLiq,"Sí")>0),IF(OR(P57="Gasto",P57="Transferencia",P57="Pago tarjeta"),-1,1)*S57,0)+IF(AND(AE57<>"",COUNTIFS(tcTipo,AE57,tcLiq,"Sí")>0),S57,0)) | AI57: =IF(OR(L57="",P57=""),"",IF(COUNTIFS(L$6:L57,L57,P$6:P57,"?*")=1,MAX(AI$5:AI56)+1,""))
B58: 46258 | C58: Gasto | D58: Alimentación | E58: Almuerzos laborales | F58: DEMO · Almuerzo laboral | G58: 350 | H58: DOP | J58: Tarjeta de débito | L58: Comedor ejecutivo | N58: DEMOSTRACIÓN | O58: =IF(AND(B58="",G58="",C58="",D58="",J58=""),"",IF(B58="","⚠ Falta fecha",IF(G58="","⚠ Falta monto",IF(Q58="","⚠ Falta cuenta",IF(ISNA(MATCH(Q58,ctaNombre,0)),"⚠ Cuenta no registrada",IF(AND(OR(P58="Gasto",P58="Reembolso"),D58=""),"⚠ Falta categoría",IF(AND(D58<>"",E58<>"",ISNA(MATCH(D58&"|"&E58,catClave,0))),"⚠ Subcategoría no corresponde",IF(AND(OR(P58="Transferencia",P58="Pago tarjeta"),K58=""),"⚠ Falta cuenta destino",IF(AND(K58<>"",P58<>"Transferencia",P58<>"Pago tarjeta"),"⚠ Destino solo aplica a transferencias",IF(AND(K58<>"",K58=Q58),"⚠ Origen igual a destino",IF(AND(K58<>"",ISNA(MATCH(K58,ctaNombre,0))),"⚠ Destino no registrado",IF(AND(P58="Pago tarjeta",AE58<>"Tarjeta de crédito"),"⚠ El destino debe ser tarjeta de crédito",IF(AND(P58="Gasto",E58="Depósitos y retiros"),"⚠ Usa tipo Transferencia",IF(AND(P58="Resultado trading",AD58<>"Cuenta de trading"),"⚠ Usa una cuenta de trading",IF(AND(G58<=0,P58<>"Ajuste",P58<>"Resultado trading"),"⚠ El monto debe ser positivo","✓"))))))))))))))) | P58: =IF(OR(B58="",G58=""),"",IF(C58="","Gasto",C58)) | Q58: =IF(P58="","",IF(J58<>"",J58,CuentaPred&"")) | R58: =IF(P58="","",IF(ISNUMBER(I58),I58,TasaUSD)) | S58: =IF(P58="","",IF(H58="USD",G58*R58,G58)) | T58: =IF(P58="","",IF(H58="USD",G58,IF(R58>0,G58/R58,0))) | U58: =IF(P58="","",IF(P58="Gasto",S58,IF(P58="Reembolso",-S58,0))) | V58: =IF(P58="","",IF(P58="Ingreso",S58,0)) | W58: =IF(P58="","",IF(P58="Resultado trading",S58,0)) | X58: =IF(OR(P58="Gasto",P58="Reembolso"),IF(M58<>"",M58,IFERROR(INDEX(catClasif,MATCH(D58&"|"&E58,catClave,0))&"","Variable")),"") | Y58: =IF(P58="","",IFERROR(INDEX(catGrupo,MATCH(D58&"|"&E58,catClave,0))&"","")) | Z58: =IF(P58="","",WEEKDAY(B58,2)) | AA58: =IF(P58="","",IF(AND(P58="Gasto",X58="Variable",D58<>catTrading,S58>0,S58<=Umbral),1,0)) | AB58: =IF(OR(P58="",Q58=""),"",IFERROR(IF(INDEX(ctaVinc,MATCH(Q58,ctaNombre,0))&""<>"",INDEX(ctaVinc,MATCH(Q58,ctaNombre,0))&"",Q58),Q58)) | AC58: =IF(OR(K58="",AND(P58<>"Transferencia",P58<>"Pago tarjeta")),"",IFERROR(IF(INDEX(ctaVinc,MATCH(K58,ctaNombre,0))&""<>"",INDEX(ctaVinc,MATCH(K58,ctaNombre,0))&"",K58),K58)) | AD58: =IF(AB58="","",IFERROR(INDEX(ctaTipo,MATCH(AB58,ctaNombre,0))&"","")) | AE58: =IF(AC58="","",IFERROR(INDEX(ctaTipo,MATCH(AC58,ctaNombre,0))&"","")) | AF58: =IF(OR(P58="",AB58=""),"",IF(OR(P58="Gasto",P58="Transferencia",P58="Pago tarjeta"),-1,1)*IF(IFERROR(INDEX(ctaMoneda,MATCH(AB58,ctaNombre,0))&"","DOP")="USD",T58,S58)) | AG58: =IF(AC58="","",IF(IFERROR(INDEX(ctaMoneda,MATCH(AC58,ctaNombre,0))&"","DOP")="USD",T58,S58)) | AH58: =IF(P58="","",IF(AND(AD58<>"",COUNTIFS(tcTipo,AD58,tcLiq,"Sí")>0),IF(OR(P58="Gasto",P58="Transferencia",P58="Pago tarjeta"),-1,1)*S58,0)+IF(AND(AE58<>"",COUNTIFS(tcTipo,AE58,tcLiq,"Sí")>0),S58,0)) | AI58: =IF(OR(L58="",P58=""),"",IF(COUNTIFS(L$6:L58,L58,P$6:P58,"?*")=1,MAX(AI$5:AI57)+1,""))
B59: 46258 | C59: Gasto | D59: Alimentación | E59: Bebidas, snacks y otros consumos | F59: DEMO · Café | G59: 90 | H59: DOP | J59: Billetera digital | L59: Colmado del barrio | N59: DEMOSTRACIÓN | O59: =IF(AND(B59="",G59="",C59="",D59="",J59=""),"",IF(B59="","⚠ Falta fecha",IF(G59="","⚠ Falta monto",IF(Q59="","⚠ Falta cuenta",IF(ISNA(MATCH(Q59,ctaNombre,0)),"⚠ Cuenta no registrada",IF(AND(OR(P59="Gasto",P59="Reembolso"),D59=""),"⚠ Falta categoría",IF(AND(D59<>"",E59<>"",ISNA(MATCH(D59&"|"&E59,catClave,0))),"⚠ Subcategoría no corresponde",IF(AND(OR(P59="Transferencia",P59="Pago tarjeta"),K59=""),"⚠ Falta cuenta destino",IF(AND(K59<>"",P59<>"Transferencia",P59<>"Pago tarjeta"),"⚠ Destino solo aplica a transferencias",IF(AND(K59<>"",K59=Q59),"⚠ Origen igual a destino",IF(AND(K59<>"",ISNA(MATCH(K59,ctaNombre,0))),"⚠ Destino no registrado",IF(AND(P59="Pago tarjeta",AE59<>"Tarjeta de crédito"),"⚠ El destino debe ser tarjeta de crédito",IF(AND(P59="Gasto",E59="Depósitos y retiros"),"⚠ Usa tipo Transferencia",IF(AND(P59="Resultado trading",AD59<>"Cuenta de trading"),"⚠ Usa una cuenta de trading",IF(AND(G59<=0,P59<>"Ajuste",P59<>"Resultado trading"),"⚠ El monto debe ser positivo","✓"))))))))))))))) | P59: =IF(OR(B59="",G59=""),"",IF(C59="","Gasto",C59)) | Q59: =IF(P59="","",IF(J59<>"",J59,CuentaPred&"")) | R59: =IF(P59="","",IF(ISNUMBER(I59),I59,TasaUSD)) | S59: =IF(P59="","",IF(H59="USD",G59*R59,G59)) | T59: =IF(P59="","",IF(H59="USD",G59,IF(R59>0,G59/R59,0))) | U59: =IF(P59="","",IF(P59="Gasto",S59,IF(P59="Reembolso",-S59,0))) | V59: =IF(P59="","",IF(P59="Ingreso",S59,0)) | W59: =IF(P59="","",IF(P59="Resultado trading",S59,0)) | X59: =IF(OR(P59="Gasto",P59="Reembolso"),IF(M59<>"",M59,IFERROR(INDEX(catClasif,MATCH(D59&"|"&E59,catClave,0))&"","Variable")),"") | Y59: =IF(P59="","",IFERROR(INDEX(catGrupo,MATCH(D59&"|"&E59,catClave,0))&"","")) | Z59: =IF(P59="","",WEEKDAY(B59,2)) | AA59: =IF(P59="","",IF(AND(P59="Gasto",X59="Variable",D59<>catTrading,S59>0,S59<=Umbral),1,0)) | AB59: =IF(OR(P59="",Q59=""),"",IFERROR(IF(INDEX(ctaVinc,MATCH(Q59,ctaNombre,0))&""<>"",INDEX(ctaVinc,MATCH(Q59,ctaNombre,0))&"",Q59),Q59)) | AC59: =IF(OR(K59="",AND(P59<>"Transferencia",P59<>"Pago tarjeta")),"",IFERROR(IF(INDEX(ctaVinc,MATCH(K59,ctaNombre,0))&""<>"",INDEX(ctaVinc,MATCH(K59,ctaNombre,0))&"",K59),K59)) | AD59: =IF(AB59="","",IFERROR(INDEX(ctaTipo,MATCH(AB59,ctaNombre,0))&"","")) | AE59: =IF(AC59="","",IFERROR(INDEX(ctaTipo,MATCH(AC59,ctaNombre,0))&"","")) | AF59: =IF(OR(P59="",AB59=""),"",IF(OR(P59="Gasto",P59="Transferencia",P59="Pago tarjeta"),-1,1)*IF(IFERROR(INDEX(ctaMoneda,MATCH(AB59,ctaNombre,0))&"","DOP")="USD",T59,S59)) | AG59: =IF(AC59="","",IF(IFERROR(INDEX(ctaMoneda,MATCH(AC59,ctaNombre,0))&"","DOP")="USD",T59,S59)) | AH59: =IF(P59="","",IF(AND(AD59<>"",COUNTIFS(tcTipo,AD59,tcLiq,"Sí")>0),IF(OR(P59="Gasto",P59="Transferencia",P59="Pago tarjeta"),-1,1)*S59,0)+IF(AND(AE59<>"",COUNTIFS(tcTipo,AE59,tcLiq,"Sí")>0),S59,0)) | AI59: =IF(OR(L59="",P59=""),"",IF(COUNTIFS(L$6:L59,L59,P$6:P59,"?*")=1,MAX(AI$5:AI58)+1,""))
B60: 46258 | C60: Gasto | D60: Transporte y vehículo | E60: Combustible | F60: DEMO · Combustible | G60: 2000 | H60: DOP | J60: Tarjeta de crédito | L60: Estación de combustible | N60: DEMOSTRACIÓN | O60: =IF(AND(B60="",G60="",C60="",D60="",J60=""),"",IF(B60="","⚠ Falta fecha",IF(G60="","⚠ Falta monto",IF(Q60="","⚠ Falta cuenta",IF(ISNA(MATCH(Q60,ctaNombre,0)),"⚠ Cuenta no registrada",IF(AND(OR(P60="Gasto",P60="Reembolso"),D60=""),"⚠ Falta categoría",IF(AND(D60<>"",E60<>"",ISNA(MATCH(D60&"|"&E60,catClave,0))),"⚠ Subcategoría no corresponde",IF(AND(OR(P60="Transferencia",P60="Pago tarjeta"),K60=""),"⚠ Falta cuenta destino",IF(AND(K60<>"",P60<>"Transferencia",P60<>"Pago tarjeta"),"⚠ Destino solo aplica a transferencias",IF(AND(K60<>"",K60=Q60),"⚠ Origen igual a destino",IF(AND(K60<>"",ISNA(MATCH(K60,ctaNombre,0))),"⚠ Destino no registrado",IF(AND(P60="Pago tarjeta",AE60<>"Tarjeta de crédito"),"⚠ El destino debe ser tarjeta de crédito",IF(AND(P60="Gasto",E60="Depósitos y retiros"),"⚠ Usa tipo Transferencia",IF(AND(P60="Resultado trading",AD60<>"Cuenta de trading"),"⚠ Usa una cuenta de trading",IF(AND(G60<=0,P60<>"Ajuste",P60<>"Resultado trading"),"⚠ El monto debe ser positivo","✓"))))))))))))))) | P60: =IF(OR(B60="",G60=""),"",IF(C60="","Gasto",C60)) | Q60: =IF(P60="","",IF(J60<>"",J60,CuentaPred&"")) | R60: =IF(P60="","",IF(ISNUMBER(I60),I60,TasaUSD)) | S60: =IF(P60="","",IF(H60="USD",G60*R60,G60)) | T60: =IF(P60="","",IF(H60="USD",G60,IF(R60>0,G60/R60,0))) | U60: =IF(P60="","",IF(P60="Gasto",S60,IF(P60="Reembolso",-S60,0))) | V60: =IF(P60="","",IF(P60="Ingreso",S60,0)) | W60: =IF(P60="","",IF(P60="Resultado trading",S60,0)) | X60: =IF(OR(P60="Gasto",P60="Reembolso"),IF(M60<>"",M60,IFERROR(INDEX(catClasif,MATCH(D60&"|"&E60,catClave,0))&"","Variable")),"") | Y60: =IF(P60="","",IFERROR(INDEX(catGrupo,MATCH(D60&"|"&E60,catClave,0))&"","")) | Z60: =IF(P60="","",WEEKDAY(B60,2)) | AA60: =IF(P60="","",IF(AND(P60="Gasto",X60="Variable",D60<>catTrading,S60>0,S60<=Umbral),1,0)) | AB60: =IF(OR(P60="",Q60=""),"",IFERROR(IF(INDEX(ctaVinc,MATCH(Q60,ctaNombre,0))&""<>"",INDEX(ctaVinc,MATCH(Q60,ctaNombre,0))&"",Q60),Q60)) | AC60: =IF(OR(K60="",AND(P60<>"Transferencia",P60<>"Pago tarjeta")),"",IFERROR(IF(INDEX(ctaVinc,MATCH(K60,ctaNombre,0))&""<>"",INDEX(ctaVinc,MATCH(K60,ctaNombre,0))&"",K60),K60)) | AD60: =IF(AB60="","",IFERROR(INDEX(ctaTipo,MATCH(AB60,ctaNombre,0))&"","")) | AE60: =IF(AC60="","",IFERROR(INDEX(ctaTipo,MATCH(AC60,ctaNombre,0))&"","")) | AF60: =IF(OR(P60="",AB60=""),"",IF(OR(P60="Gasto",P60="Transferencia",P60="Pago tarjeta"),-1,1)*IF(IFERROR(INDEX(ctaMoneda,MATCH(AB60,ctaNombre,0))&"","DOP")="USD",T60,S60)) | AG60: =IF(AC60="","",IF(IFERROR(INDEX(ctaMoneda,MATCH(AC60,ctaNombre,0))&"","DOP")="USD",T60,S60)) | AH60: =IF(P60="","",IF(AND(AD60<>"",COUNTIFS(tcTipo,AD60,tcLiq,"Sí")>0),IF(OR(P60="Gasto",P60="Transferencia",P60="Pago tarjeta"),-1,1)*S60,0)+IF(AND(AE60<>"",COUNTIFS(tcTipo,AE60,tcLiq,"Sí")>0),S60,0)) | AI60: =IF(OR(L60="",P60=""),"",IF(COUNTIFS(L$6:L60,L60,P$6:P60,"?*")=1,MAX(AI$5:AI59)+1,""))
B61: 46259 | C61: Gasto | D61: Alimentación | E61: Desayunos comprados | F61: DEMO · Desayuno en la oficina | G61: 330 | H61: DOP | J61: Efectivo | L61: Cafetería del trabajo | N61: DEMOSTRACIÓN | O61: =IF(AND(B61="",G61="",C61="",D61="",J61=""),"",IF(B61="","⚠ Falta fecha",IF(G61="","⚠ Falta monto",IF(Q61="","⚠ Falta cuenta",IF(ISNA(MATCH(Q61,ctaNombre,0)),"⚠ Cuenta no registrada",IF(AND(OR(P61="Gasto",P61="Reembolso"),D61=""),"⚠ Falta categoría",IF(AND(D61<>"",E61<>"",ISNA(MATCH(D61&"|"&E61,catClave,0))),"⚠ Subcategoría no corresponde",IF(AND(OR(P61="Transferencia",P61="Pago tarjeta"),K61=""),"⚠ Falta cuenta destino",IF(AND(K61<>"",P61<>"Transferencia",P61<>"Pago tarjeta"),"⚠ Destino solo aplica a transferencias",IF(AND(K61<>"",K61=Q61),"⚠ Origen igual a destino",IF(AND(K61<>"",ISNA(MATCH(K61,ctaNombre,0))),"⚠ Destino no registrado",IF(AND(P61="Pago tarjeta",AE61<>"Tarjeta de crédito"),"⚠ El destino debe ser tarjeta de crédito",IF(AND(P61="Gasto",E61="Depósitos y retiros"),"⚠ Usa tipo Transferencia",IF(AND(P61="Resultado trading",AD61<>"Cuenta de trading"),"⚠ Usa una cuenta de trading",IF(AND(G61<=0,P61<>"Ajuste",P61<>"Resultado trading"),"⚠ El monto debe ser positivo","✓"))))))))))))))) | P61: =IF(OR(B61="",G61=""),"",IF(C61="","Gasto",C61)) | Q61: =IF(P61="","",IF(J61<>"",J61,CuentaPred&"")) | R61: =IF(P61="","",IF(ISNUMBER(I61),I61,TasaUSD)) | S61: =IF(P61="","",IF(H61="USD",G61*R61,G61)) | T61: =IF(P61="","",IF(H61="USD",G61,IF(R61>0,G61/R61,0))) | U61: =IF(P61="","",IF(P61="Gasto",S61,IF(P61="Reembolso",-S61,0))) | V61: =IF(P61="","",IF(P61="Ingreso",S61,0)) | W61: =IF(P61="","",IF(P61="Resultado trading",S61,0)) | X61: =IF(OR(P61="Gasto",P61="Reembolso"),IF(M61<>"",M61,IFERROR(INDEX(catClasif,MATCH(D61&"|"&E61,catClave,0))&"","Variable")),"") | Y61: =IF(P61="","",IFERROR(INDEX(catGrupo,MATCH(D61&"|"&E61,catClave,0))&"","")) | Z61: =IF(P61="","",WEEKDAY(B61,2)) | AA61: =IF(P61="","",IF(AND(P61="Gasto",X61="Variable",D61<>catTrading,S61>0,S61<=Umbral),1,0)) | AB61: =IF(OR(P61="",Q61=""),"",IFERROR(IF(INDEX(ctaVinc,MATCH(Q61,ctaNombre,0))&""<>"",INDEX(ctaVinc,MATCH(Q61,ctaNombre,0))&"",Q61),Q61)) | AC61: =IF(OR(K61="",AND(P61<>"Transferencia",P61<>"Pago tarjeta")),"",IFERROR(IF(INDEX(ctaVinc,MATCH(K61,ctaNombre,0))&""<>"",INDEX(ctaVinc,MATCH(K61,ctaNombre,0))&"",K61),K61)) | AD61: =IF(AB61="","",IFERROR(INDEX(ctaTipo,MATCH(AB61,ctaNombre,0))&"","")) | AE61: =IF(AC61="","",IFERROR(INDEX(ctaTipo,MATCH(AC61,ctaNombre,0))&"","")) | AF61: =IF(OR(P61="",AB61=""),"",IF(OR(P61="Gasto",P61="Transferencia",P61="Pago tarjeta"),-1,1)*IF(IFERROR(INDEX(ctaMoneda,MATCH(AB61,ctaNombre,0))&"","DOP")="USD",T61,S61)) | AG61: =IF(AC61="","",IF(IFERROR(INDEX(ctaMoneda,MATCH(AC61,ctaNombre,0))&"","DOP")="USD",T61,S61)) | AH61: =IF(P61="","",IF(AND(AD61<>"",COUNTIFS(tcTipo,AD61,tcLiq,"Sí")>0),IF(OR(P61="Gasto",P61="Transferencia",P61="Pago tarjeta"),-1,1)*S61,0)+IF(AND(AE61<>"",COUNTIFS(tcTipo,AE61,tcLiq,"Sí")>0),S61,0)) | AI61: =IF(OR(L61="",P61=""),"",IF(COUNTIFS(L$6:L61,L61,P$6:P61,"?*")=1,MAX(AI$5:AI60)+1,""))
B62: 46259 | C62: Gasto | D62: Alimentación | E62: Almuerzos laborales | F62: DEMO · Almuerzo laboral | G62: 525 | H62: DOP | J62: Billetera digital | L62: Comedor ejecutivo | N62: DEMOSTRACIÓN | O62: =IF(AND(B62="",G62="",C62="",D62="",J62=""),"",IF(B62="","⚠ Falta fecha",IF(G62="","⚠ Falta monto",IF(Q62="","⚠ Falta cuenta",IF(ISNA(MATCH(Q62,ctaNombre,0)),"⚠ Cuenta no registrada",IF(AND(OR(P62="Gasto",P62="Reembolso"),D62=""),"⚠ Falta categoría",IF(AND(D62<>"",E62<>"",ISNA(MATCH(D62&"|"&E62,catClave,0))),"⚠ Subcategoría no corresponde",IF(AND(OR(P62="Transferencia",P62="Pago tarjeta"),K62=""),"⚠ Falta cuenta destino",IF(AND(K62<>"",P62<>"Transferencia",P62<>"Pago tarjeta"),"⚠ Destino solo aplica a transferencias",IF(AND(K62<>"",K62=Q62),"⚠ Origen igual a destino",IF(AND(K62<>"",ISNA(MATCH(K62,ctaNombre,0))),"⚠ Destino no registrado",IF(AND(P62="Pago tarjeta",AE62<>"Tarjeta de crédito"),"⚠ El destino debe ser tarjeta de crédito",IF(AND(P62="Gasto",E62="Depósitos y retiros"),"⚠ Usa tipo Transferencia",IF(AND(P62="Resultado trading",AD62<>"Cuenta de trading"),"⚠ Usa una cuenta de trading",IF(AND(G62<=0,P62<>"Ajuste",P62<>"Resultado trading"),"⚠ El monto debe ser positivo","✓"))))))))))))))) | P62: =IF(OR(B62="",G62=""),"",IF(C62="","Gasto",C62)) | Q62: =IF(P62="","",IF(J62<>"",J62,CuentaPred&"")) | R62: =IF(P62="","",IF(ISNUMBER(I62),I62,TasaUSD)) | S62: =IF(P62="","",IF(H62="USD",G62*R62,G62)) | T62: =IF(P62="","",IF(H62="USD",G62,IF(R62>0,G62/R62,0))) | U62: =IF(P62="","",IF(P62="Gasto",S62,IF(P62="Reembolso",-S62,0))) | V62: =IF(P62="","",IF(P62="Ingreso",S62,0)) | W62: =IF(P62="","",IF(P62="Resultado trading",S62,0)) | X62: =IF(OR(P62="Gasto",P62="Reembolso"),IF(M62<>"",M62,IFERROR(INDEX(catClasif,MATCH(D62&"|"&E62,catClave,0))&"","Variable")),"") | Y62: =IF(P62="","",IFERROR(INDEX(catGrupo,MATCH(D62&"|"&E62,catClave,0))&"","")) | Z62: =IF(P62="","",WEEKDAY(B62,2)) | AA62: =IF(P62="","",IF(AND(P62="Gasto",X62="Variable",D62<>catTrading,S62>0,S62<=Umbral),1,0)) | AB62: =IF(OR(P62="",Q62=""),"",IFERROR(IF(INDEX(ctaVinc,MATCH(Q62,ctaNombre,0))&""<>"",INDEX(ctaVinc,MATCH(Q62,ctaNombre,0))&"",Q62),Q62)) | AC62: =IF(OR(K62="",AND(P62<>"Transferencia",P62<>"Pago tarjeta")),"",IFERROR(IF(INDEX(ctaVinc,MATCH(K62,ctaNombre,0))&""<>"",INDEX(ctaVinc,MATCH(K62,ctaNombre,0))&"",K62),K62)) | AD62: =IF(AB62="","",IFERROR(INDEX(ctaTipo,MATCH(AB62,ctaNombre,0))&"","")) | AE62: =IF(AC62="","",IFERROR(INDEX(ctaTipo,MATCH(AC62,ctaNombre,0))&"","")) | AF62: =IF(OR(P62="",AB62=""),"",IF(OR(P62="Gasto",P62="Transferencia",P62="Pago tarjeta"),-1,1)*IF(IFERROR(INDEX(ctaMoneda,MATCH(AB62,ctaNombre,0))&"","DOP")="USD",T62,S62)) | AG62: =IF(AC62="","",IF(IFERROR(INDEX(ctaMoneda,MATCH(AC62,ctaNombre,0))&"","DOP")="USD",T62,S62)) | AH62: =IF(P62="","",IF(AND(AD62<>"",COUNTIFS(tcTipo,AD62,tcLiq,"Sí")>0),IF(OR(P62="Gasto",P62="Transferencia",P62="Pago tarjeta"),-1,1)*S62,0)+IF(AND(AE62<>"",COUNTIFS(tcTipo,AE62,tcLiq,"Sí")>0),S62,0)) | AI62: =IF(OR(L62="",P62=""),"",IF(COUNTIFS(L$6:L62,L62,P$6:P62,"?*")=1,MAX(AI$5:AI61)+1,""))
B63: 46259 | C63: Pago tarjeta | F63: DEMO · Pago de tarjeta de crédito | G63: 30000 | H63: DOP | J63: Banco principal | K63: Tarjeta de crédito | N63: DEMOSTRACIÓN | O63: =IF(AND(B63="",G63="",C63="",D63="",J63=""),"",IF(B63="","⚠ Falta fecha",IF(G63="","⚠ Falta monto",IF(Q63="","⚠ Falta cuenta",IF(ISNA(MATCH(Q63,ctaNombre,0)),"⚠ Cuenta no registrada",IF(AND(OR(P63="Gasto",P63="Reembolso"),D63=""),"⚠ Falta categoría",IF(AND(D63<>"",E63<>"",ISNA(MATCH(D63&"|"&E63,catClave,0))),"⚠ Subcategoría no corresponde",IF(AND(OR(P63="Transferencia",P63="Pago tarjeta"),K63=""),"⚠ Falta cuenta destino",IF(AND(K63<>"",P63<>"Transferencia",P63<>"Pago tarjeta"),"⚠ Destino solo aplica a transferencias",IF(AND(K63<>"",K63=Q63),"⚠ Origen igual a destino",IF(AND(K63<>"",ISNA(MATCH(K63,ctaNombre,0))),"⚠ Destino no registrado",IF(AND(P63="Pago tarjeta",AE63<>"Tarjeta de crédito"),"⚠ El destino debe ser tarjeta de crédito",IF(AND(P63="Gasto",E63="Depósitos y retiros"),"⚠ Usa tipo Transferencia",IF(AND(P63="Resultado trading",AD63<>"Cuenta de trading"),"⚠ Usa una cuenta de trading",IF(AND(G63<=0,P63<>"Ajuste",P63<>"Resultado trading"),"⚠ El monto debe ser positivo","✓"))))))))))))))) | P63: =IF(OR(B63="",G63=""),"",IF(C63="","Gasto",C63)) | Q63: =IF(P63="","",IF(J63<>"",J63,CuentaPred&"")) | R63: =IF(P63="","",IF(ISNUMBER(I63),I63,TasaUSD)) | S63: =IF(P63="","",IF(H63="USD",G63*R63,G63)) | T63: =IF(P63="","",IF(H63="USD",G63,IF(R63>0,G63/R63,0))) | U63: =IF(P63="","",IF(P63="Gasto",S63,IF(P63="Reembolso",-S63,0))) | V63: =IF(P63="","",IF(P63="Ingreso",S63,0)) | W63: =IF(P63="","",IF(P63="Resultado trading",S63,0)) | X63: =IF(OR(P63="Gasto",P63="Reembolso"),IF(M63<>"",M63,IFERROR(INDEX(catClasif,MATCH(D63&"|"&E63,catClave,0))&"","Variable")),"") | Y63: =IF(P63="","",IFERROR(INDEX(catGrupo,MATCH(D63&"|"&E63,catClave,0))&"","")) | Z63: =IF(P63="","",WEEKDAY(B63,2)) | AA63: =IF(P63="","",IF(AND(P63="Gasto",X63="Variable",D63<>catTrading,S63>0,S63<=Umbral),1,0)) | AB63: =IF(OR(P63="",Q63=""),"",IFERROR(IF(INDEX(ctaVinc,MATCH(Q63,ctaNombre,0))&""<>"",INDEX(ctaVinc,MATCH(Q63,ctaNombre,0))&"",Q63),Q63)) | AC63: =IF(OR(K63="",AND(P63<>"Transferencia",P63<>"Pago tarjeta")),"",IFERROR(IF(INDEX(ctaVinc,MATCH(K63,ctaNombre,0))&""<>"",INDEX(ctaVinc,MATCH(K63,ctaNombre,0))&"",K63),K63)) | AD63: =IF(AB63="","",IFERROR(INDEX(ctaTipo,MATCH(AB63,ctaNombre,0))&"","")) | AE63: =IF(AC63="","",IFERROR(INDEX(ctaTipo,MATCH(AC63,ctaNombre,0))&"","")) | AF63: =IF(OR(P63="",AB63=""),"",IF(OR(P63="Gasto",P63="Transferencia",P63="Pago tarjeta"),-1,1)*IF(IFERROR(INDEX(ctaMoneda,MATCH(AB63,ctaNombre,0))&"","DOP")="USD",T63,S63)) | AG63: =IF(AC63="","",IF(IFERROR(INDEX(ctaMoneda,MATCH(AC63,ctaNombre,0))&"","DOP")="USD",T63,S63)) | AH63: =IF(P63="","",IF(AND(AD63<>"",COUNTIFS(tcTipo,AD63,tcLiq,"Sí")>0),IF(OR(P63="Gasto",P63="Transferencia",P63="Pago tarjeta"),-1,1)*S63,0)+IF(AND(AE63<>"",COUNTIFS(tcTipo,AE63,tcLiq,"Sí")>0),S63,0)) | AI63: =IF(OR(L63="",P63=""),"",IF(COUNTIFS(L$6:L63,L63,P$6:P63,"?*")=1,MAX(AI$5:AI62)+1,""))
B64: 46260 | C64: Gasto | D64: Alimentación | E64: Almuerzos laborales | F64: DEMO · Almuerzo laboral | G64: 575 | H64: DOP | J64: Tarjeta de débito | L64: Comedor ejecutivo | N64: DEMOSTRACIÓN | O64: =IF(AND(B64="",G64="",C64="",D64="",J64=""),"",IF(B64="","⚠ Falta fecha",IF(G64="","⚠ Falta monto",IF(Q64="","⚠ Falta cuenta",IF(ISNA(MATCH(Q64,ctaNombre,0)),"⚠ Cuenta no registrada",IF(AND(OR(P64="Gasto",P64="Reembolso"),D64=""),"⚠ Falta categoría",IF(AND(D64<>"",E64<>"",ISNA(MATCH(D64&"|"&E64,catClave,0))),"⚠ Subcategoría no corresponde",IF(AND(OR(P64="Transferencia",P64="Pago tarjeta"),K64=""),"⚠ Falta cuenta destino",IF(AND(K64<>"",P64<>"Transferencia",P64<>"Pago tarjeta"),"⚠ Destino solo aplica a transferencias",IF(AND(K64<>"",K64=Q64),"⚠ Origen igual a destino",IF(AND(K64<>"",ISNA(MATCH(K64,ctaNombre,0))),"⚠ Destino no registrado",IF(AND(P64="Pago tarjeta",AE64<>"Tarjeta de crédito"),"⚠ El destino debe ser tarjeta de crédito",IF(AND(P64="Gasto",E64="Depósitos y retiros"),"⚠ Usa tipo Transferencia",IF(AND(P64="Resultado trading",AD64<>"Cuenta de trading"),"⚠ Usa una cuenta de trading",IF(AND(G64<=0,P64<>"Ajuste",P64<>"Resultado trading"),"⚠ El monto debe ser positivo","✓"))))))))))))))) | P64: =IF(OR(B64="",G64=""),"",IF(C64="","Gasto",C64)) | Q64: =IF(P64="","",IF(J64<>"",J64,CuentaPred&"")) | R64: =IF(P64="","",IF(ISNUMBER(I64),I64,TasaUSD)) | S64: =IF(P64="","",IF(H64="USD",G64*R64,G64)) | T64: =IF(P64="","",IF(H64="USD",G64,IF(R64>0,G64/R64,0))) | U64: =IF(P64="","",IF(P64="Gasto",S64,IF(P64="Reembolso",-S64,0))) | V64: =IF(P64="","",IF(P64="Ingreso",S64,0)) | W64: =IF(P64="","",IF(P64="Resultado trading",S64,0)) | X64: =IF(OR(P64="Gasto",P64="Reembolso"),IF(M64<>"",M64,IFERROR(INDEX(catClasif,MATCH(D64&"|"&E64,catClave,0))&"","Variable")),"") | Y64: =IF(P64="","",IFERROR(INDEX(catGrupo,MATCH(D64&"|"&E64,catClave,0))&"","")) | Z64: =IF(P64="","",WEEKDAY(B64,2)) | AA64: =IF(P64="","",IF(AND(P64="Gasto",X64="Variable",D64<>catTrading,S64>0,S64<=Umbral),1,0)) | AB64: =IF(OR(P64="",Q64=""),"",IFERROR(IF(INDEX(ctaVinc,MATCH(Q64,ctaNombre,0))&""<>"",INDEX(ctaVinc,MATCH(Q64,ctaNombre,0))&"",Q64),Q64)) | AC64: =IF(OR(K64="",AND(P64<>"Transferencia",P64<>"Pago tarjeta")),"",IFERROR(IF(INDEX(ctaVinc,MATCH(K64,ctaNombre,0))&""<>"",INDEX(ctaVinc,MATCH(K64,ctaNombre,0))&"",K64),K64)) | AD64: =IF(AB64="","",IFERROR(INDEX(ctaTipo,MATCH(AB64,ctaNombre,0))&"","")) | AE64: =IF(AC64="","",IFERROR(INDEX(ctaTipo,MATCH(AC64,ctaNombre,0))&"","")) | AF64: =IF(OR(P64="",AB64=""),"",IF(OR(P64="Gasto",P64="Transferencia",P64="Pago tarjeta"),-1,1)*IF(IFERROR(INDEX(ctaMoneda,MATCH(AB64,ctaNombre,0))&"","DOP")="USD",T64,S64)) | AG64: =IF(AC64="","",IF(IFERROR(INDEX(ctaMoneda,MATCH(AC64,ctaNombre,0))&"","DOP")="USD",T64,S64)) | AH64: =IF(P64="","",IF(AND(AD64<>"",COUNTIFS(tcTipo,AD64,tcLiq,"Sí")>0),IF(OR(P64="Gasto",P64="Transferencia",P64="Pago tarjeta"),-1,1)*S64,0)+IF(AND(AE64<>"",COUNTIFS(tcTipo,AE64,tcLiq,"Sí")>0),S64,0)) | AI64: =IF(OR(L64="",P64=""),"",IF(COUNTIFS(L$6:L64,L64,P$6:P64,"?*")=1,MAX(AI$5:AI63)+1,""))
B65: 46260 | C65: Gasto | D65: Alimentación | E65: Bebidas, snacks y otros consumos | F65: DEMO · Jugo y galletas | G65: 140 | H65: DOP | J65: Billetera digital | L65: Cafetería del trabajo | N65: DEMOSTRACIÓN | O65: =IF(AND(B65="",G65="",C65="",D65="",J65=""),"",IF(B65="","⚠ Falta fecha",IF(G65="","⚠ Falta monto",IF(Q65="","⚠ Falta cuenta",IF(ISNA(MATCH(Q65,ctaNombre,0)),"⚠ Cuenta no registrada",IF(AND(OR(P65="Gasto",P65="Reembolso"),D65=""),"⚠ Falta categoría",IF(AND(D65<>"",E65<>"",ISNA(MATCH(D65&"|"&E65,catClave,0))),"⚠ Subcategoría no corresponde",IF(AND(OR(P65="Transferencia",P65="Pago tarjeta"),K65=""),"⚠ Falta cuenta destino",IF(AND(K65<>"",P65<>"Transferencia",P65<>"Pago tarjeta"),"⚠ Destino solo aplica a transferencias",IF(AND(K65<>"",K65=Q65),"⚠ Origen igual a destino",IF(AND(K65<>"",ISNA(MATCH(K65,ctaNombre,0))),"⚠ Destino no registrado",IF(AND(P65="Pago tarjeta",AE65<>"Tarjeta de crédito"),"⚠ El destino debe ser tarjeta de crédito",IF(AND(P65="Gasto",E65="Depósitos y retiros"),"⚠ Usa tipo Transferencia",IF(AND(P65="Resultado trading",AD65<>"Cuenta de trading"),"⚠ Usa una cuenta de trading",IF(AND(G65<=0,P65<>"Ajuste",P65<>"Resultado trading"),"⚠ El monto debe ser positivo","✓"))))))))))))))) | P65: =IF(OR(B65="",G65=""),"",IF(C65="","Gasto",C65)) | Q65: =IF(P65="","",IF(J65<>"",J65,CuentaPred&"")) | R65: =IF(P65="","",IF(ISNUMBER(I65),I65,TasaUSD)) | S65: =IF(P65="","",IF(H65="USD",G65*R65,G65)) | T65: =IF(P65="","",IF(H65="USD",G65,IF(R65>0,G65/R65,0))) | U65: =IF(P65="","",IF(P65="Gasto",S65,IF(P65="Reembolso",-S65,0))) | V65: =IF(P65="","",IF(P65="Ingreso",S65,0)) | W65: =IF(P65="","",IF(P65="Resultado trading",S65,0)) | X65: =IF(OR(P65="Gasto",P65="Reembolso"),IF(M65<>"",M65,IFERROR(INDEX(catClasif,MATCH(D65&"|"&E65,catClave,0))&"","Variable")),"") | Y65: =IF(P65="","",IFERROR(INDEX(catGrupo,MATCH(D65&"|"&E65,catClave,0))&"","")) | Z65: =IF(P65="","",WEEKDAY(B65,2)) | AA65: =IF(P65="","",IF(AND(P65="Gasto",X65="Variable",D65<>catTrading,S65>0,S65<=Umbral),1,0)) | AB65: =IF(OR(P65="",Q65=""),"",IFERROR(IF(INDEX(ctaVinc,MATCH(Q65,ctaNombre,0))&""<>"",INDEX(ctaVinc,MATCH(Q65,ctaNombre,0))&"",Q65),Q65)) | AC65: =IF(OR(K65="",AND(P65<>"Transferencia",P65<>"Pago tarjeta")),"",IFERROR(IF(INDEX(ctaVinc,MATCH(K65,ctaNombre,0))&""<>"",INDEX(ctaVinc,MATCH(K65,ctaNombre,0))&"",K65),K65)) | AD65: =IF(AB65="","",IFERROR(INDEX(ctaTipo,MATCH(AB65,ctaNombre,0))&"","")) | AE65: =IF(AC65="","",IFERROR(INDEX(ctaTipo,MATCH(AC65,ctaNombre,0))&"","")) | AF65: =IF(OR(P65="",AB65=""),"",IF(OR(P65="Gasto",P65="Transferencia",P65="Pago tarjeta"),-1,1)*IF(IFERROR(INDEX(ctaMoneda,MATCH(AB65,ctaNombre,0))&"","DOP")="USD",T65,S65)) | AG65: =IF(AC65="","",IF(IFERROR(INDEX(ctaMoneda,MATCH(AC65,ctaNombre,0))&"","DOP")="USD",T65,S65)) | AH65: =IF(P65="","",IF(AND(AD65<>"",COUNTIFS(tcTipo,AD65,tcLiq,"Sí")>0),IF(OR(P65="Gasto",P65="Transferencia",P65="Pago tarjeta"),-1,1)*S65,0)+IF(AND(AE65<>"",COUNTIFS(tcTipo,AE65,tcLiq,"Sí")>0),S65,0)) | AI65: =IF(OR(L65="",P65=""),"",IF(COUNTIFS(L$6:L65,L65,P$6:P65,"?*")=1,MAX(AI$5:AI64)+1,""))
B66: 46261 | C66: Gasto | D66: Alimentación | E66: Desayunos comprados | F66: DEMO · Desayuno en la oficina | G66: 300 | H66: DOP | J66: Tarjeta de débito | L66: Cafetería del trabajo | N66: DEMOSTRACIÓN | O66: =IF(AND(B66="",G66="",C66="",D66="",J66=""),"",IF(B66="","⚠ Falta fecha",IF(G66="","⚠ Falta monto",IF(Q66="","⚠ Falta cuenta",IF(ISNA(MATCH(Q66,ctaNombre,0)),"⚠ Cuenta no registrada",IF(AND(OR(P66="Gasto",P66="Reembolso"),D66=""),"⚠ Falta categoría",IF(AND(D66<>"",E66<>"",ISNA(MATCH(D66&"|"&E66,catClave,0))),"⚠ Subcategoría no corresponde",IF(AND(OR(P66="Transferencia",P66="Pago tarjeta"),K66=""),"⚠ Falta cuenta destino",IF(AND(K66<>"",P66<>"Transferencia",P66<>"Pago tarjeta"),"⚠ Destino solo aplica a transferencias",IF(AND(K66<>"",K66=Q66),"⚠ Origen igual a destino",IF(AND(K66<>"",ISNA(MATCH(K66,ctaNombre,0))),"⚠ Destino no registrado",IF(AND(P66="Pago tarjeta",AE66<>"Tarjeta de crédito"),"⚠ El destino debe ser tarjeta de crédito",IF(AND(P66="Gasto",E66="Depósitos y retiros"),"⚠ Usa tipo Transferencia",IF(AND(P66="Resultado trading",AD66<>"Cuenta de trading"),"⚠ Usa una cuenta de trading",IF(AND(G66<=0,P66<>"Ajuste",P66<>"Resultado trading"),"⚠ El monto debe ser positivo","✓"))))))))))))))) | P66: =IF(OR(B66="",G66=""),"",IF(C66="","Gasto",C66)) | Q66: =IF(P66="","",IF(J66<>"",J66,CuentaPred&"")) | R66: =IF(P66="","",IF(ISNUMBER(I66),I66,TasaUSD)) | S66: =IF(P66="","",IF(H66="USD",G66*R66,G66)) | T66: =IF(P66="","",IF(H66="USD",G66,IF(R66>0,G66/R66,0))) | U66: =IF(P66="","",IF(P66="Gasto",S66,IF(P66="Reembolso",-S66,0))) | V66: =IF(P66="","",IF(P66="Ingreso",S66,0)) | W66: =IF(P66="","",IF(P66="Resultado trading",S66,0)) | X66: =IF(OR(P66="Gasto",P66="Reembolso"),IF(M66<>"",M66,IFERROR(INDEX(catClasif,MATCH(D66&"|"&E66,catClave,0))&"","Variable")),"") | Y66: =IF(P66="","",IFERROR(INDEX(catGrupo,MATCH(D66&"|"&E66,catClave,0))&"","")) | Z66: =IF(P66="","",WEEKDAY(B66,2)) | AA66: =IF(P66="","",IF(AND(P66="Gasto",X66="Variable",D66<>catTrading,S66>0,S66<=Umbral),1,0)) | AB66: =IF(OR(P66="",Q66=""),"",IFERROR(IF(INDEX(ctaVinc,MATCH(Q66,ctaNombre,0))&""<>"",INDEX(ctaVinc,MATCH(Q66,ctaNombre,0))&"",Q66),Q66)) | AC66: =IF(OR(K66="",AND(P66<>"Transferencia",P66<>"Pago tarjeta")),"",IFERROR(IF(INDEX(ctaVinc,MATCH(K66,ctaNombre,0))&""<>"",INDEX(ctaVinc,MATCH(K66,ctaNombre,0))&"",K66),K66)) | AD66: =IF(AB66="","",IFERROR(INDEX(ctaTipo,MATCH(AB66,ctaNombre,0))&"","")) | AE66: =IF(AC66="","",IFERROR(INDEX(ctaTipo,MATCH(AC66,ctaNombre,0))&"","")) | AF66: =IF(OR(P66="",AB66=""),"",IF(OR(P66="Gasto",P66="Transferencia",P66="Pago tarjeta"),-1,1)*IF(IFERROR(INDEX(ctaMoneda,MATCH(AB66,ctaNombre,0))&"","DOP")="USD",T66,S66)) | AG66: =IF(AC66="","",IF(IFERROR(INDEX(ctaMoneda,MATCH(AC66,ctaNombre,0))&"","DOP")="USD",T66,S66)) | AH66: =IF(P66="","",IF(AND(AD66<>"",COUNTIFS(tcTipo,AD66,tcLiq,"Sí")>0),IF(OR(P66="Gasto",P66="Transferencia",P66="Pago tarjeta"),-1,1)*S66,0)+IF(AND(AE66<>"",COUNTIFS(tcTipo,AE66,tcLiq,"Sí")>0),S66,0)) | AI66: =IF(OR(L66="",P66=""),"",IF(COUNTIFS(L$6:L66,L66,P$6:P66,"?*")=1,MAX(AI$5:AI65)+1,""))
B67: 46261 | C67: Gasto | D67: Alimentación | E67: Almuerzos laborales | F67: DEMO · Almuerzo laboral | G67: 400 | H67: DOP | J67: Tarjeta de débito | L67: Comedor ejecutivo | N67: DEMOSTRACIÓN | O67: =IF(AND(B67="",G67="",C67="",D67="",J67=""),"",IF(B67="","⚠ Falta fecha",IF(G67="","⚠ Falta monto",IF(Q67="","⚠ Falta cuenta",IF(ISNA(MATCH(Q67,ctaNombre,0)),"⚠ Cuenta no registrada",IF(AND(OR(P67="Gasto",P67="Reembolso"),D67=""),"⚠ Falta categoría",IF(AND(D67<>"",E67<>"",ISNA(MATCH(D67&"|"&E67,catClave,0))),"⚠ Subcategoría no corresponde",IF(AND(OR(P67="Transferencia",P67="Pago tarjeta"),K67=""),"⚠ Falta cuenta destino",IF(AND(K67<>"",P67<>"Transferencia",P67<>"Pago tarjeta"),"⚠ Destino solo aplica a transferencias",IF(AND(K67<>"",K67=Q67),"⚠ Origen igual a destino",IF(AND(K67<>"",ISNA(MATCH(K67,ctaNombre,0))),"⚠ Destino no registrado",IF(AND(P67="Pago tarjeta",AE67<>"Tarjeta de crédito"),"⚠ El destino debe ser tarjeta de crédito",IF(AND(P67="Gasto",E67="Depósitos y retiros"),"⚠ Usa tipo Transferencia",IF(AND(P67="Resultado trading",AD67<>"Cuenta de trading"),"⚠ Usa una cuenta de trading",IF(AND(G67<=0,P67<>"Ajuste",P67<>"Resultado trading"),"⚠ El monto debe ser positivo","✓"))))))))))))))) | P67: =IF(OR(B67="",G67=""),"",IF(C67="","Gasto",C67)) | Q67: =IF(P67="","",IF(J67<>"",J67,CuentaPred&"")) | R67: =IF(P67="","",IF(ISNUMBER(I67),I67,TasaUSD)) | S67: =IF(P67="","",IF(H67="USD",G67*R67,G67)) | T67: =IF(P67="","",IF(H67="USD",G67,IF(R67>0,G67/R67,0))) | U67: =IF(P67="","",IF(P67="Gasto",S67,IF(P67="Reembolso",-S67,0))) | V67: =IF(P67="","",IF(P67="Ingreso",S67,0)) | W67: =IF(P67="","",IF(P67="Resultado trading",S67,0)) | X67: =IF(OR(P67="Gasto",P67="Reembolso"),IF(M67<>"",M67,IFERROR(INDEX(catClasif,MATCH(D67&"|"&E67,catClave,0))&"","Variable")),"") | Y67: =IF(P67="","",IFERROR(INDEX(catGrupo,MATCH(D67&"|"&E67,catClave,0))&"","")) | Z67: =IF(P67="","",WEEKDAY(B67,2)) | AA67: =IF(P67="","",IF(AND(P67="Gasto",X67="Variable",D67<>catTrading,S67>0,S67<=Umbral),1,0)) | AB67: =IF(OR(P67="",Q67=""),"",IFERROR(IF(INDEX(ctaVinc,MATCH(Q67,ctaNombre,0))&""<>"",INDEX(ctaVinc,MATCH(Q67,ctaNombre,0))&"",Q67),Q67)) | AC67: =IF(OR(K67="",AND(P67<>"Transferencia",P67<>"Pago tarjeta")),"",IFERROR(IF(INDEX(ctaVinc,MATCH(K67,ctaNombre,0))&""<>"",INDEX(ctaVinc,MATCH(K67,ctaNombre,0))&"",K67),K67)) | AD67: =IF(AB67="","",IFERROR(INDEX(ctaTipo,MATCH(AB67,ctaNombre,0))&"","")) | AE67: =IF(AC67="","",IFERROR(INDEX(ctaTipo,MATCH(AC67,ctaNombre,0))&"","")) | AF67: =IF(OR(P67="",AB67=""),"",IF(OR(P67="Gasto",P67="Transferencia",P67="Pago tarjeta"),-1,1)*IF(IFERROR(INDEX(ctaMoneda,MATCH(AB67,ctaNombre,0))&"","DOP")="USD",T67,S67)) | AG67: =IF(AC67="","",IF(IFERROR(INDEX(ctaMoneda,MATCH(AC67,ctaNombre,0))&"","DOP")="USD",T67,S67)) | AH67: =IF(P67="","",IF(AND(AD67<>"",COUNTIFS(tcTipo,AD67,tcLiq,"Sí")>0),IF(OR(P67="Gasto",P67="Transferencia",P67="Pago tarjeta"),-1,1)*S67,0)+IF(AND(AE67<>"",COUNTIFS(tcTipo,AE67,tcLiq,"Sí")>0),S67,0)) | AI67: =IF(OR(L67="",P67=""),"",IF(COUNTIFS(L$6:L67,L67,P$6:P67,"?*")=1,MAX(AI$5:AI66)+1,""))
B68: 46261 | C68: Gasto | D68: Alimentación | E68: Cenas compradas | F68: DEMO · Cena comprada | G68: 725 | H68: DOP | J68: Tarjeta de crédito | L68: Pizzería del sector | N68: DEMOSTRACIÓN | O68: =IF(AND(B68="",G68="",C68="",D68="",J68=""),"",IF(B68="","⚠ Falta fecha",IF(G68="","⚠ Falta monto",IF(Q68="","⚠ Falta cuenta",IF(ISNA(MATCH(Q68,ctaNombre,0)),"⚠ Cuenta no registrada",IF(AND(OR(P68="Gasto",P68="Reembolso"),D68=""),"⚠ Falta categoría",IF(AND(D68<>"",E68<>"",ISNA(MATCH(D68&"|"&E68,catClave,0))),"⚠ Subcategoría no corresponde",IF(AND(OR(P68="Transferencia",P68="Pago tarjeta"),K68=""),"⚠ Falta cuenta destino",IF(AND(K68<>"",P68<>"Transferencia",P68<>"Pago tarjeta"),"⚠ Destino solo aplica a transferencias",IF(AND(K68<>"",K68=Q68),"⚠ Origen igual a destino",IF(AND(K68<>"",ISNA(MATCH(K68,ctaNombre,0))),"⚠ Destino no registrado",IF(AND(P68="Pago tarjeta",AE68<>"Tarjeta de crédito"),"⚠ El destino debe ser tarjeta de crédito",IF(AND(P68="Gasto",E68="Depósitos y retiros"),"⚠ Usa tipo Transferencia",IF(AND(P68="Resultado trading",AD68<>"Cuenta de trading"),"⚠ Usa una cuenta de trading",IF(AND(G68<=0,P68<>"Ajuste",P68<>"Resultado trading"),"⚠ El monto debe ser positivo","✓"))))))))))))))) | P68: =IF(OR(B68="",G68=""),"",IF(C68="","Gasto",C68)) | Q68: =IF(P68="","",IF(J68<>"",J68,CuentaPred&"")) | R68: =IF(P68="","",IF(ISNUMBER(I68),I68,TasaUSD)) | S68: =IF(P68="","",IF(H68="USD",G68*R68,G68)) | T68: =IF(P68="","",IF(H68="USD",G68,IF(R68>0,G68/R68,0))) | U68: =IF(P68="","",IF(P68="Gasto",S68,IF(P68="Reembolso",-S68,0))) | V68: =IF(P68="","",IF(P68="Ingreso",S68,0)) | W68: =IF(P68="","",IF(P68="Resultado trading",S68,0)) | X68: =IF(OR(P68="Gasto",P68="Reembolso"),IF(M68<>"",M68,IFERROR(INDEX(catClasif,MATCH(D68&"|"&E68,catClave,0))&"","Variable")),"") | Y68: =IF(P68="","",IFERROR(INDEX(catGrupo,MATCH(D68&"|"&E68,catClave,0))&"","")) | Z68: =IF(P68="","",WEEKDAY(B68,2)) | AA68: =IF(P68="","",IF(AND(P68="Gasto",X68="Variable",D68<>catTrading,S68>0,S68<=Umbral),1,0)) | AB68: =IF(OR(P68="",Q68=""),"",IFERROR(IF(INDEX(ctaVinc,MATCH(Q68,ctaNombre,0))&""<>"",INDEX(ctaVinc,MATCH(Q68,ctaNombre,0))&"",Q68),Q68)) | AC68: =IF(OR(K68="",AND(P68<>"Transferencia",P68<>"Pago tarjeta")),"",IFERROR(IF(INDEX(ctaVinc,MATCH(K68,ctaNombre,0))&""<>"",INDEX(ctaVinc,MATCH(K68,ctaNombre,0))&"",K68),K68)) | AD68: =IF(AB68="","",IFERROR(INDEX(ctaTipo,MATCH(AB68,ctaNombre,0))&"","")) | AE68: =IF(AC68="","",IFERROR(INDEX(ctaTipo,MATCH(AC68,ctaNombre,0))&"","")) | AF68: =IF(OR(P68="",AB68=""),"",IF(OR(P68="Gasto",P68="Transferencia",P68="Pago tarjeta"),-1,1)*IF(IFERROR(INDEX(ctaMoneda,MATCH(AB68,ctaNombre,0))&"","DOP")="USD",T68,S68)) | AG68: =IF(AC68="","",IF(IFERROR(INDEX(ctaMoneda,MATCH(AC68,ctaNombre,0))&"","DOP")="USD",T68,S68)) | AH68: =IF(P68="","",IF(AND(AD68<>"",COUNTIFS(tcTipo,AD68,tcLiq,"Sí")>0),IF(OR(P68="Gasto",P68="Transferencia",P68="Pago tarjeta"),-1,1)*S68,0)+IF(AND(AE68<>"",COUNTIFS(tcTipo,AE68,tcLiq,"Sí")>0),S68,0)) | AI68: =IF(OR(L68="",P68=""),"",IF(COUNTIFS(L$6:L68,L68,P$6:P68,"?*")=1,MAX(AI$5:AI67)+1,""))
B69: 46261 | C69: Gasto | D69: Salud | E69: Medicamentos y farmacia | F69: DEMO · Farmacia | G69: 650 | H69: DOP | J69: Tarjeta de débito | L69: Farmacia | N69: DEMOSTRACIÓN | O69: =IF(AND(B69="",G69="",C69="",D69="",J69=""),"",IF(B69="","⚠ Falta fecha",IF(G69="","⚠ Falta monto",IF(Q69="","⚠ Falta cuenta",IF(ISNA(MATCH(Q69,ctaNombre,0)),"⚠ Cuenta no registrada",IF(AND(OR(P69="Gasto",P69="Reembolso"),D69=""),"⚠ Falta categoría",IF(AND(D69<>"",E69<>"",ISNA(MATCH(D69&"|"&E69,catClave,0))),"⚠ Subcategoría no corresponde",IF(AND(OR(P69="Transferencia",P69="Pago tarjeta"),K69=""),"⚠ Falta cuenta destino",IF(AND(K69<>"",P69<>"Transferencia",P69<>"Pago tarjeta"),"⚠ Destino solo aplica a transferencias",IF(AND(K69<>"",K69=Q69),"⚠ Origen igual a destino",IF(AND(K69<>"",ISNA(MATCH(K69,ctaNombre,0))),"⚠ Destino no registrado",IF(AND(P69="Pago tarjeta",AE69<>"Tarjeta de crédito"),"⚠ El destino debe ser tarjeta de crédito",IF(AND(P69="Gasto",E69="Depósitos y retiros"),"⚠ Usa tipo Transferencia",IF(AND(P69="Resultado trading",AD69<>"Cuenta de trading"),"⚠ Usa una cuenta de trading",IF(AND(G69<=0,P69<>"Ajuste",P69<>"Resultado trading"),"⚠ El monto debe ser positivo","✓"))))))))))))))) | P69: =IF(OR(B69="",G69=""),"",IF(C69="","Gasto",C69)) | Q69: =IF(P69="","",IF(J69<>"",J69,CuentaPred&"")) | R69: =IF(P69="","",IF(ISNUMBER(I69),I69,TasaUSD)) | S69: =IF(P69="","",IF(H69="USD",G69*R69,G69)) | T69: =IF(P69="","",IF(H69="USD",G69,IF(R69>0,G69/R69,0))) | U69: =IF(P69="","",IF(P69="Gasto",S69,IF(P69="Reembolso",-S69,0))) | V69: =IF(P69="","",IF(P69="Ingreso",S69,0)) | W69: =IF(P69="","",IF(P69="Resultado trading",S69,0)) | X69: =IF(OR(P69="Gasto",P69="Reembolso"),IF(M69<>"",M69,IFERROR(INDEX(catClasif,MATCH(D69&"|"&E69,catClave,0))&"","Variable")),"") | Y69: =IF(P69="","",IFERROR(INDEX(catGrupo,MATCH(D69&"|"&E69,catClave,0))&"","")) | Z69: =IF(P69="","",WEEKDAY(B69,2)) | AA69: =IF(P69="","",IF(AND(P69="Gasto",X69="Variable",D69<>catTrading,S69>0,S69<=Umbral),1,0)) | AB69: =IF(OR(P69="",Q69=""),"",IFERROR(IF(INDEX(ctaVinc,MATCH(Q69,ctaNombre,0))&""<>"",INDEX(ctaVinc,MATCH(Q69,ctaNombre,0))&"",Q69),Q69)) | AC69: =IF(OR(K69="",AND(P69<>"Transferencia",P69<>"Pago tarjeta")),"",IFERROR(IF(INDEX(ctaVinc,MATCH(K69,ctaNombre,0))&""<>"",INDEX(ctaVinc,MATCH(K69,ctaNombre,0))&"",K69),K69)) | AD69: =IF(AB69="","",IFERROR(INDEX(ctaTipo,MATCH(AB69,ctaNombre,0))&"","")) | AE69: =IF(AC69="","",IFERROR(INDEX(ctaTipo,MATCH(AC69,ctaNombre,0))&"","")) | AF69: =IF(OR(P69="",AB69=""),"",IF(OR(P69="Gasto",P69="Transferencia",P69="Pago tarjeta"),-1,1)*IF(IFERROR(INDEX(ctaMoneda,MATCH(AB69,ctaNombre,0))&"","DOP")="USD",T69,S69)) | AG69: =IF(AC69="","",IF(IFERROR(INDEX(ctaMoneda,MATCH(AC69,ctaNombre,0))&"","DOP")="USD",T69,S69)) | AH69: =IF(P69="","",IF(AND(AD69<>"",COUNTIFS(tcTipo,AD69,tcLiq,"Sí")>0),IF(OR(P69="Gasto",P69="Transferencia",P69="Pago tarjeta"),-1,1)*S69,0)+IF(AND(AE69<>"",COUNTIFS(tcTipo,AE69,tcLiq,"Sí")>0),S69,0)) | AI69: =IF(OR(L69="",P69=""),"",IF(COUNTIFS(L$6:L69,L69,P$6:P69,"?*")=1,MAX(AI$5:AI68)+1,""))
B70: 46262 | C70: Gasto | D70: Alimentación | E70: Bebidas, snacks y otros consumos | F70: DEMO · Jugo y galletas | G70: 120 | H70: DOP | J70: Efectivo | L70: Cafetería del trabajo | N70: DEMOSTRACIÓN | O70: =IF(AND(B70="",G70="",C70="",D70="",J70=""),"",IF(B70="","⚠ Falta fecha",IF(G70="","⚠ Falta monto",IF(Q70="","⚠ Falta cuenta",IF(ISNA(MATCH(Q70,ctaNombre,0)),"⚠ Cuenta no registrada",IF(AND(OR(P70="Gasto",P70="Reembolso"),D70=""),"⚠ Falta categoría",IF(AND(D70<>"",E70<>"",ISNA(MATCH(D70&"|"&E70,catClave,0))),"⚠ Subcategoría no corresponde",IF(AND(OR(P70="Transferencia",P70="Pago tarjeta"),K70=""),"⚠ Falta cuenta destino",IF(AND(K70<>"",P70<>"Transferencia",P70<>"Pago tarjeta"),"⚠ Destino solo aplica a transferencias",IF(AND(K70<>"",K70=Q70),"⚠ Origen igual a destino",IF(AND(K70<>"",ISNA(MATCH(K70,ctaNombre,0))),"⚠ Destino no registrado",IF(AND(P70="Pago tarjeta",AE70<>"Tarjeta de crédito"),"⚠ El destino debe ser tarjeta de crédito",IF(AND(P70="Gasto",E70="Depósitos y retiros"),"⚠ Usa tipo Transferencia",IF(AND(P70="Resultado trading",AD70<>"Cuenta de trading"),"⚠ Usa una cuenta de trading",IF(AND(G70<=0,P70<>"Ajuste",P70<>"Resultado trading"),"⚠ El monto debe ser positivo","✓"))))))))))))))) | P70: =IF(OR(B70="",G70=""),"",IF(C70="","Gasto",C70)) | Q70: =IF(P70="","",IF(J70<>"",J70,CuentaPred&"")) | R70: =IF(P70="","",IF(ISNUMBER(I70),I70,TasaUSD)) | S70: =IF(P70="","",IF(H70="USD",G70*R70,G70)) | T70: =IF(P70="","",IF(H70="USD",G70,IF(R70>0,G70/R70,0))) | U70: =IF(P70="","",IF(P70="Gasto",S70,IF(P70="Reembolso",-S70,0))) | V70: =IF(P70="","",IF(P70="Ingreso",S70,0)) | W70: =IF(P70="","",IF(P70="Resultado trading",S70,0)) | X70: =IF(OR(P70="Gasto",P70="Reembolso"),IF(M70<>"",M70,IFERROR(INDEX(catClasif,MATCH(D70&"|"&E70,catClave,0))&"","Variable")),"") | Y70: =IF(P70="","",IFERROR(INDEX(catGrupo,MATCH(D70&"|"&E70,catClave,0))&"","")) | Z70: =IF(P70="","",WEEKDAY(B70,2)) | AA70: =IF(P70="","",IF(AND(P70="Gasto",X70="Variable",D70<>catTrading,S70>0,S70<=Umbral),1,0)) | AB70: =IF(OR(P70="",Q70=""),"",IFERROR(IF(INDEX(ctaVinc,MATCH(Q70,ctaNombre,0))&""<>"",INDEX(ctaVinc,MATCH(Q70,ctaNombre,0))&"",Q70),Q70)) | AC70: =IF(OR(K70="",AND(P70<>"Transferencia",P70<>"Pago tarjeta")),"",IFERROR(IF(INDEX(ctaVinc,MATCH(K70,ctaNombre,0))&""<>"",INDEX(ctaVinc,MATCH(K70,ctaNombre,0))&"",K70),K70)) | AD70: =IF(AB70="","",IFERROR(INDEX(ctaTipo,MATCH(AB70,ctaNombre,0))&"","")) | AE70: =IF(AC70="","",IFERROR(INDEX(ctaTipo,MATCH(AC70,ctaNombre,0))&"","")) | AF70: =IF(OR(P70="",AB70=""),"",IF(OR(P70="Gasto",P70="Transferencia",P70="Pago tarjeta"),-1,1)*IF(IFERROR(INDEX(ctaMoneda,MATCH(AB70,ctaNombre,0))&"","DOP")="USD",T70,S70)) | AG70: =IF(AC70="","",IF(IFERROR(INDEX(ctaMoneda,MATCH(AC70,ctaNombre,0))&"","DOP")="USD",T70,S70)) | AH70: =IF(P70="","",IF(AND(AD70<>"",COUNTIFS(tcTipo,AD70,tcLiq,"Sí")>0),IF(OR(P70="Gasto",P70="Transferencia",P70="Pago tarjeta"),-1,1)*S70,0)+IF(AND(AE70<>"",COUNTIFS(tcTipo,AE70,tcLiq,"Sí")>0),S70,0)) | AI70: =IF(OR(L70="",P70=""),"",IF(COUNTIFS(L$6:L70,L70,P$6:P70,"?*")=1,MAX(AI$5:AI69)+1,""))
B71: 46262 | C71: Gasto | D71: Alimentación | E71: Delivery | F71: DEMO · Pedido a domicilio | G71: 850 | H71: DOP | J71: Tarjeta de crédito | L71: App de delivery | N71: DEMOSTRACIÓN | O71: =IF(AND(B71="",G71="",C71="",D71="",J71=""),"",IF(B71="","⚠ Falta fecha",IF(G71="","⚠ Falta monto",IF(Q71="","⚠ Falta cuenta",IF(ISNA(MATCH(Q71,ctaNombre,0)),"⚠ Cuenta no registrada",IF(AND(OR(P71="Gasto",P71="Reembolso"),D71=""),"⚠ Falta categoría",IF(AND(D71<>"",E71<>"",ISNA(MATCH(D71&"|"&E71,catClave,0))),"⚠ Subcategoría no corresponde",IF(AND(OR(P71="Transferencia",P71="Pago tarjeta"),K71=""),"⚠ Falta cuenta destino",IF(AND(K71<>"",P71<>"Transferencia",P71<>"Pago tarjeta"),"⚠ Destino solo aplica a transferencias",IF(AND(K71<>"",K71=Q71),"⚠ Origen igual a destino",IF(AND(K71<>"",ISNA(MATCH(K71,ctaNombre,0))),"⚠ Destino no registrado",IF(AND(P71="Pago tarjeta",AE71<>"Tarjeta de crédito"),"⚠ El destino debe ser tarjeta de crédito",IF(AND(P71="Gasto",E71="Depósitos y retiros"),"⚠ Usa tipo Transferencia",IF(AND(P71="Resultado trading",AD71<>"Cuenta de trading"),"⚠ Usa una cuenta de trading",IF(AND(G71<=0,P71<>"Ajuste",P71<>"Resultado trading"),"⚠ El monto debe ser positivo","✓"))))))))))))))) | P71: =IF(OR(B71="",G71=""),"",IF(C71="","Gasto",C71)) | Q71: =IF(P71="","",IF(J71<>"",J71,CuentaPred&"")) | R71: =IF(P71="","",IF(ISNUMBER(I71),I71,TasaUSD)) | S71: =IF(P71="","",IF(H71="USD",G71*R71,G71)) | T71: =IF(P71="","",IF(H71="USD",G71,IF(R71>0,G71/R71,0))) | U71: =IF(P71="","",IF(P71="Gasto",S71,IF(P71="Reembolso",-S71,0))) | V71: =IF(P71="","",IF(P71="Ingreso",S71,0)) | W71: =IF(P71="","",IF(P71="Resultado trading",S71,0)) | X71: =IF(OR(P71="Gasto",P71="Reembolso"),IF(M71<>"",M71,IFERROR(INDEX(catClasif,MATCH(D71&"|"&E71,catClave,0))&"","Variable")),"") | Y71: =IF(P71="","",IFERROR(INDEX(catGrupo,MATCH(D71&"|"&E71,catClave,0))&"","")) | Z71: =IF(P71="","",WEEKDAY(B71,2)) | AA71: =IF(P71="","",IF(AND(P71="Gasto",X71="Variable",D71<>catTrading,S71>0,S71<=Umbral),1,0)) | AB71: =IF(OR(P71="",Q71=""),"",IFERROR(IF(INDEX(ctaVinc,MATCH(Q71,ctaNombre,0))&""<>"",INDEX(ctaVinc,MATCH(Q71,ctaNombre,0))&"",Q71),Q71)) | AC71: =IF(OR(K71="",AND(P71<>"Transferencia",P71<>"Pago tarjeta")),"",IFERROR(IF(INDEX(ctaVinc,MATCH(K71,ctaNombre,0))&""<>"",INDEX(ctaVinc,MATCH(K71,ctaNombre,0))&"",K71),K71)) | AD71: =IF(AB71="","",IFERROR(INDEX(ctaTipo,MATCH(AB71,ctaNombre,0))&"","")) | AE71: =IF(AC71="","",IFERROR(INDEX(ctaTipo,MATCH(AC71,ctaNombre,0))&"","")) | AF71: =IF(OR(P71="",AB71=""),"",IF(OR(P71="Gasto",P71="Transferencia",P71="Pago tarjeta"),-1,1)*IF(IFERROR(INDEX(ctaMoneda,MATCH(AB71,ctaNombre,0))&"","DOP")="USD",T71,S71)) | AG71: =IF(AC71="","",IF(IFERROR(INDEX(ctaMoneda,MATCH(AC71,ctaNombre,0))&"","DOP")="USD",T71,S71)) | AH71: =IF(P71="","",IF(AND(AD71<>"",COUNTIFS(tcTipo,AD71,tcLiq,"Sí")>0),IF(OR(P71="Gasto",P71="Transferencia",P71="Pago tarjeta"),-1,1)*S71,0)+IF(AND(AE71<>"",COUNTIFS(tcTipo,AE71,tcLiq,"Sí")>0),S71,0)) | AI71: =IF(OR(L71="",P71=""),"",IF(COUNTIFS(L$6:L71,L71,P$6:P71,"?*")=1,MAX(AI$5:AI70)+1,""))
B72: 46264 | C72: Gasto | D72: Alimentación | E72: Ingredientes para cocinar | F72: DEMO · Vegetales, carne y víveres | G72: 575 | H72: DOP | J72: Efectivo | L72: Mercado del barrio | N72: DEMOSTRACIÓN | O72: =IF(AND(B72="",G72="",C72="",D72="",J72=""),"",IF(B72="","⚠ Falta fecha",IF(G72="","⚠ Falta monto",IF(Q72="","⚠ Falta cuenta",IF(ISNA(MATCH(Q72,ctaNombre,0)),"⚠ Cuenta no registrada",IF(AND(OR(P72="Gasto",P72="Reembolso"),D72=""),"⚠ Falta categoría",IF(AND(D72<>"",E72<>"",ISNA(MATCH(D72&"|"&E72,catClave,0))),"⚠ Subcategoría no corresponde",IF(AND(OR(P72="Transferencia",P72="Pago tarjeta"),K72=""),"⚠ Falta cuenta destino",IF(AND(K72<>"",P72<>"Transferencia",P72<>"Pago tarjeta"),"⚠ Destino solo aplica a transferencias",IF(AND(K72<>"",K72=Q72),"⚠ Origen igual a destino",IF(AND(K72<>"",ISNA(MATCH(K72,ctaNombre,0))),"⚠ Destino no registrado",IF(AND(P72="Pago tarjeta",AE72<>"Tarjeta de crédito"),"⚠ El destino debe ser tarjeta de crédito",IF(AND(P72="Gasto",E72="Depósitos y retiros"),"⚠ Usa tipo Transferencia",IF(AND(P72="Resultado trading",AD72<>"Cuenta de trading"),"⚠ Usa una cuenta de trading",IF(AND(G72<=0,P72<>"Ajuste",P72<>"Resultado trading"),"⚠ El monto debe ser positivo","✓"))))))))))))))) | P72: =IF(OR(B72="",G72=""),"",IF(C72="","Gasto",C72)) | Q72: =IF(P72="","",IF(J72<>"",J72,CuentaPred&"")) | R72: =IF(P72="","",IF(ISNUMBER(I72),I72,TasaUSD)) | S72: =IF(P72="","",IF(H72="USD",G72*R72,G72)) | T72: =IF(P72="","",IF(H72="USD",G72,IF(R72>0,G72/R72,0))) | U72: =IF(P72="","",IF(P72="Gasto",S72,IF(P72="Reembolso",-S72,0))) | V72: =IF(P72="","",IF(P72="Ingreso",S72,0)) | W72: =IF(P72="","",IF(P72="Resultado trading",S72,0)) | X72: =IF(OR(P72="Gasto",P72="Reembolso"),IF(M72<>"",M72,IFERROR(INDEX(catClasif,MATCH(D72&"|"&E72,catClave,0))&"","Variable")),"") | Y72: =IF(P72="","",IFERROR(INDEX(catGrupo,MATCH(D72&"|"&E72,catClave,0))&"","")) | Z72: =IF(P72="","",WEEKDAY(B72,2)) | AA72: =IF(P72="","",IF(AND(P72="Gasto",X72="Variable",D72<>catTrading,S72>0,S72<=Umbral),1,0)) | AB72: =IF(OR(P72="",Q72=""),"",IFERROR(IF(INDEX(ctaVinc,MATCH(Q72,ctaNombre,0))&""<>"",INDEX(ctaVinc,MATCH(Q72,ctaNombre,0))&"",Q72),Q72)) | AC72: =IF(OR(K72="",AND(P72<>"Transferencia",P72<>"Pago tarjeta")),"",IFERROR(IF(INDEX(ctaVinc,MATCH(K72,ctaNombre,0))&""<>"",INDEX(ctaVinc,MATCH(K72,ctaNombre,0))&"",K72),K72)) | AD72: =IF(AB72="","",IFERROR(INDEX(ctaTipo,MATCH(AB72,ctaNombre,0))&"","")) | AE72: =IF(AC72="","",IFERROR(INDEX(ctaTipo,MATCH(AC72,ctaNombre,0))&"","")) | AF72: =IF(OR(P72="",AB72=""),"",IF(OR(P72="Gasto",P72="Transferencia",P72="Pago tarjeta"),-1,1)*IF(IFERROR(INDEX(ctaMoneda,MATCH(AB72,ctaNombre,0))&"","DOP")="USD",T72,S72)) | AG72: =IF(AC72="","",IF(IFERROR(INDEX(ctaMoneda,MATCH(AC72,ctaNombre,0))&"","DOP")="USD",T72,S72)) | AH72: =IF(P72="","",IF(AND(AD72<>"",COUNTIFS(tcTipo,AD72,tcLiq,"Sí")>0),IF(OR(P72="Gasto",P72="Transferencia",P72="Pago tarjeta"),-1,1)*S72,0)+IF(AND(AE72<>"",COUNTIFS(tcTipo,AE72,tcLiq,"Sí")>0),S72,0)) | AI72: =IF(OR(L72="",P72=""),"",IF(COUNTIFS(L$6:L72,L72,P$6:P72,"?*")=1,MAX(AI$5:AI71)+1,""))
